Workbook

Sheet Sheet8
B1: First Name | H1: Email | AU1: Filter Rows to Merge
A2: 45753.909 | B2: Brian | C2: Davids | D2: 23388 | E2: davidsbg@bc.edu | F2: bzachdavids@gmail.com | G2: College/Secondary email: | H2: =IF(G2="College/Secondary email:",E2,F2) -> davidsbg@bc.edu | I2: Glenn Dale | J2: Analyst | K2: +13015182003 | L2: Male | M2: Spring 2024 | N2: 2027 | O2: North America | P2: Boston (U.S.) | Q2: Yes | R2: Long Horizon Partners | S2: Virtual | T2: Private Equity | U2: 1 | V2: N/A | W2: PWC | X2: New York, NY | Y2: Consulting | Z2: 1 | AA2: N/A | AB2: Evercore | AC2: New York, NY | AD2: Investment Banking | AE2: 1 | AF2: N/A | AG2: N/A | AH2: Boston College | AI2: Newton, MA | AJ2: Target | AK2: 3.7 | AL2: Finance and Business Analytics | AM2: 2027 | AN2: MLT, SEO | AO2: https://drive.google.com/open?id=1XWClHCwCx5aNJniGdFhaFayO5decO7qu | AP2: Investment Banking, Private Equity, Venture Capital, Hedge Funds | AQ2: Advent, DE Shaw, Warburg | AR2: Pursuing Banking but interested in Public and Private Markets Investing for After Analyst Years | AT2: Analyst
A3: 45753.91 | B3: EJ | C3: Ibhawoh | D3: 23043 | E3: ibhawoha@mcmaster.ca | F3: ejiyeibhawoh@gmail.com | G3: College/Secondary email: | H3: =IF(G3="College/Secondary email:",E3,F3) -> ibhawoha@mcmaster.ca | I3: Hamilton | J3: Analyst | K3: 19057450150 | L3: Male | M3: Fall 2022 | N3: 2026 | O3: North America | P3: Toronto (Canada) | Q3: Yes | R3: BDC | S3: Toronto | T3: Venture Capital | U3: N/A | V3: N/A | W3: CIBC | X3: Toronto | Y3: Sales & Trading | Z3: N/A | AA3: N/A | AB3: RBC | AC3: Toronto | AD3: Investment Banking | AE3: N/A | AF3: N/A | AG3: N/A | AH3: McMaster University | AI3: Hamilton | AJ3: Non-target | AK3: 4 | AL3: Commerce | AM3: 2026 | AN3: Bridging the Gap | AO3: https://drive.google.com/open?id=1iSck4HjUOK-tMmh3tgnAAAmBNI8Eytqq | AP3: Investment Banking, Private Equity, Asset Management | AQ3: JP Morgan, Goldman Sachs, Morgan Stanley | AR3: Any American Investment Banking Position | AT3: Analyst
A4: 45753.911 | B4: Allegra | C4: Nshuti | D4: 23260 | E4: an3161@columbia.edu | F4: allegranshuti123@gmail.com | G4: Personal email | H4: =IF(G4="College/Secondary email:",E4,F4) -> allegranshuti123@gmail.com | I4: Kigali | J4: Community Member | K4: 19173851412 | L4: Female | M4: Spring 2023 | N4: 2026 | O4: North America | P4: New York City (U.S.) | Q4: Yes | R4: Rwanda Development Board | S4: Kigali | T4: Venture Capital | U4: 1 | V4: Na | W4: Morgan stanley | X4: New York | Y4: Private wealth | Z4: 1 | AA4: Na | AB4: Morgan stanley | AC4: New York | AD4: Sales and Trading | AE4: 0 | AF4: Na | AG4: Na | AH4: Columbia University | AI4: New york | AJ4: Target | AK4: 3.7 | AL4: Economics | AM4: 2026 | AN4: None | AO4: https://drive.google.com/open?id=10Dcy0cDIANA1n3UOdPrdOCwxXztrh1VS | AP4: Sales and Trading, Private Equity, Venture Capital, Hedge Funds | AQ4: Na | AR4: Na | AT4: Community Member
A5: 45753.911 | B5: Keyonte’ | C5: Doughty | D5: BLK - 23311 | E5: keyonte.d.doughty@vanderbilt.edu | F5: kd.doughty66@gmail.com | G5: Personal email | H5: =IF(G5="College/Secondary email:",E5,F5) -> kd.doughty66@gmail.com | I5: Tuscaloosa, AL | J5: Senior analyst | K5: 2058726413 | L5: Male | M5: Spring 2024 | N5: 2025 | O5: North America | P5: N/A | Q5: Yes | R5: Congressional Black Caucus Foundation | S5: Washington, D.C. | T5: Government | U5: N/A | V5: N/A | W5: Affiliated Managers Group | X5: Boston, MA | Y5: Asset Management | Z5: N/A | AA5: N/A | AB5: Citigroup | AC5: New York, New York | AD5: Sales & Trading | AE5: 1 | AF5: N/A | AG5: Citi | AH5: Vanderbilt University | AI5: Nashville, TN | AJ5: Target | AK5: 3.63 | AL5: Human & Organizational Development, Political Science | AM5: 2025 | AN5: SEO | AO5: https://drive.google.com/open?id=1AWIuUcQF6mEJKQCCW_AbEXIbW1fEi7WZ | AP5: Investment Banking, Sales and Trading, Private Equity, Real Estate, Legal, Risk & Compliance | AQ5: Bain & Capital, Carlyle Group, J.P. Morgan, Goldman Sachs, TD Cowen | AR5: Interested in going to PE post S&T | AT5: Alumni (only select if you are graduated/graduating this year)
A6: 45753.912 | B6: Malik | C6: Denney | D6: BLK-23146 | E6: Malik.Denney@bison.Howard.edu | F6: Malik.denney1@gmail.con | G6: Personal email | H6: =IF(G6="College/Secondary email:",E6,F6) -> Malik.denney1@gmail.con | I6: Atlanta | J6: Analyst | K6: 4046838903 | L6: Male | M6: Spring 2023 | N6: 2026 | O6: North America | P6: N/A | Q6: Yes | R6: Deloittw | S6: Atlanta, GA | T6: Consulting | U6: 2 | V6: Higher pay | W6: Permira Advisors | X6: New York, New York | Y6: Private equity | Z6: 3 | AA6: Prestige | AB6: BMO Capital Markets | AC6: New York, NY | AD6: Investment Banking | AE6: 1 | AF6: Na | AG6: Na | AH6: Howard University | AI6: Washington D.C | AJ6: Non-target | AK6: 3.3 | AL6: Finance | AM6: 2026 | AN6: Huig | AO6: https://drive.google.com/open?id=1lMpAUbh_PZNJoJMd4p5HEoGGoWu_6ITj | AP6: Investment Banking | AQ6: Evercore | AT6: Education Pathways (IB, AWM, or PE)
A7: 45753.913 | B7: Glenn | C7: Osemeha | D7: 23036 | E7: Gosemeha@wesleyan.edu | F7: gosemeha@gmail.com | G7: Personal email | H7: =IF(G7="College/Secondary email:",E7,F7) -> gosemeha@gmail.com | I7: West Orange | J7: Community Member | K7: +19739815898 | L7: Male | M7: Spring 2023 | N7: 2026 | O7: North America | P7: Boston (U.S.) | Q7: Yes | R7: Alyeska Investment group | S7: Chicago IL | T7: Hedgefund | U7: 2 | V7: N/a | W7: TD Securities | X7: New York NY | Y7: Sales and trading | Z7: N/A | AA7: N/A | AB7: N/A | AC7: N/A | AD7: N/A | AE7: N/A | AF7: N/A | AG7: N/A | AH7: Wesleyan University | AI7: Middletown | AJ7: Liberal Arts College, Non-Target School | AK7: 3.4 | AL7: Economics | AM7: 2026 | AN7: SEO | AO7: https://drive.google.com/open?id=1htBzQ4U9JmmsO98nKwZ23co1nEs2PV01 | AP7: Asset Management | AQ7: Citi | AT7: Community Member
A8: 45753.916 | B8: Patrick | C8: Bongo | D8: 24020 | E8: patrick.m.bongo.27@dartmouth.edu | F8: MVOO21032GMAIL.COM | G8: College/Secondary email: | H8: =IF(G8="College/Secondary email:",E8,F8) -> patrick.m.bongo.27@dartmouth.edu | I8: Mombasa | J8: Analyst | K8: +6032668130 | L8: Male | M8: Spring 2024 | N8: 2027 | O8: North America | P8: N/A | Q8: Yes | R8: N/A | S8: N/A | T8: N/A | U8: N/A | V8: N/A | W8: N/A | X8: N/A | Y8: N/A | Z8: N/A | AA8: N/A | AB8: Nomura | AC8: NYC | AD8: Sales & Trading | AE8: 2 | AF8: Preference | AG8: N/A | AH8: Dartmouth College | AI8: Hanover | AJ8: Target | AK8: 3.74 | AL8: Comp Science | AM8: 2027 | AN8: Black Gen Finance | AO8: https://drive.google.com/open?id=16Pz6ikkt1Lbyfoxv_PL_tlhdmij0Vh2w | AP8: Investment Banking, Sales and Trading, Private Equity | AQ8: PE | AR8: PE and any other PE organizations | AT8: Analyst
A9: 45753.916 | B9: Aiden | C9: Nelson | D9: 23353 | E9: anelson02@wesleyan.edu | F9: aidensnelson6@gmail.com | G9: College/Secondary email: | H9: =IF(G9="College/Secondary email:",E9,F9) -> anelson02@wesleyan.edu | I9: Hagerstown | J9: Community Member | K9: 3015733122 | L9: Male | M9: Fall 2024 | N9: 2027 | O9: North America | P9: N/A | Q9: Yes | R9: Clark Construction | S9: Mclean VA | T9: Accounting | U9: N/A | V9: N/A | W9: J.p. morgan Chase | X9: New York, NY | Y9: Securities Services | Z9: N/A | AA9: N/A | AB9: N/A | AC9: N/A | AD9: N/A | AE9: N/A | AF9: N/A | AG9: N/A | AH9: Wesleyan University | AI9: Middletown | AJ9: Liberal Arts College, Non-Target School | AK9: 3.5 | AL9: Econ | AM9: 2027 | AN9: SEO | AO9: https://drive.google.com/open?id=19Q2fe54IpFcNi90QvVWZ1goYYwkfpKQg | AP9: Sales and Trading | AQ9: JP, Citi, MS, GS, WF | AT9: Analyst
A10: 45753.922 | B10: Maya | C10: Lewis | D10: BLK-24102 | E10: mayajlewis@uchicago.edu | F10: mayajasmine05@gmail.com | G10: College/Secondary email: | H10: =IF(G10="College/Secondary email:",E10,F10) -> mayajlewis@uchicago.edu | I10: Burlington, NJ | J10: Analyst | K10: 9083009622 | L10: Female | M10: Fall 2024 | N10: 2028 | O10: North America | P10: N/A | Q10: Yes | R10: N/A | S10: N/A | T10: N/A | U10: N/A | V10: N/A | W10: N/A | X10: N/A | Y10: N/A | Z10: N/A | AA10: N/A | AB10: N/A | AC10: N/A | AD10: N/A | AE10: N/A | AF10: N/A | AG10: N/A | AH10: University of Chicago | AI10: Chicago | AJ10: Target | AK10: 3.3 | AL10: Business Economics & Public Policy | AM10: 2028 | AN10: INROADS, Girls Who Invest, Project Destined | AO10: https://drive.google.com/open?id=1RiHQVITmVo-4QtHRbp2hoX6czBXfkctD | AP10: Sales and Trading, Venture Capital, Hedge Funds, Economic Consulting, Equity Research | AQ10: Nera, US Bank, Cornerstone Research | AT10: Analyst
A11: 45753.923 | B11: Jamari | C11: Myers | D11: BLK - 23372 | E11: jamari_myers@brown.edu | F11: jamari.myers2023@gmail.com | G11: College/Secondary email: | H11: =IF(G11="College/Secondary email:",E11,F11) -> jamari_myers@brown.edu | I11: Mansfield, TX | J11: Analyst | K11: +19789980846 | L11: Male | M11: Spring 2024 | N11: 2027 | O11: North America | P11: N/A | Q11: Yes | R11: Decatur Street Capital | S11: Remote | T11: Private Equity - Search Fund | U11: 3 | V11: This internship was the best fit for what I hoped to gain. | W11: J.P. Morgan | X11: New York, New York | Y11: Investment Banking | Z11: 1 | AA11: N/A | AB11: N/A, J.P. Morgan | AC11: New York, New York | AD11: Investment Banking | AE11: N/A | AF11: N/A | AG11: N/A | AH11: Brown University | AI11: Providence, RI | AJ11: Target | AK11: 3.75 | AL11: Business Economics and Entrepreneurship | AM11: 2027 | AN11: SEO | AO11: https://drive.google.com/open?id=1cvj_Ut2UurUuoFcS8Zx3chzUe28w8nzo | AP11: Investment Banking, Private Equity, Business & Entreprenuership | AQ11: Apollo | AT11: Analyst
A12: 45753.923 | B12: Christela | C12: Bosco | D12: BLK - 23351 | E12: Christelabosco@gmail.com | F12: Christelabosco@gmail.com | G12: Personal email | H12: =IF(G12="College/Secondary email:",E12,F12) -> Christelabosco@gmail.com | I12: Nashville, TN | J12: Roark fellow | K12: 1 | L12: Female | M12: Spring 2024 | N12: 2027 | O12: North America | P12: Atlanta (U.S.) | Q12: Yes | R12: N/A | S12: N/A | T12: N/A | U12: N/A | V12: N/A | W12: N/A | X12: N/A | Y12: N/A | Z12: N/A | AA12: N/A | AB12: N/A | AC12: N/A | AD12: N/A | AE12: N/A | AF12: N/A | AG12: N/A | AH12: University of Tennessee | AI12: Knoxville | AJ12: Non-target | AK12: 4 | AL12: Business | AM12: 2027 | AN12: SEO, Girls Who Invest | AO12: https://drive.google.com/open?id=130pSyXHdOXzXoDZg7PCHxTxFFC30zM46 | AP12: Private Equity, Management Consulting, Real Estate, Legal, Risk & Compliance | AQ12: Blackstone, Ares, Carlyle, KKR | AT12: Community Member
A13: 45753.927 | B13: Matthew | C13: Frazier | D13: BLK-23233 | E13: Mfrazier1@babson.edu | F13: Mkfrazier.edu@gmail.com | G13: Personal email | H13: =IF(G13="College/Secondary email:",E13,F13) -> Mkfrazier.edu@gmail.com | I13: Chicago | J13: Portfolio Manager | K13: +16172299484 | L13: Male | M13: Fall 2023 | N13: 2026 | O13: North America | P13: Boston (U.S.) | Q13: Yes | R13: Evercore | S13: New York City, New York | T13: Equity Research, Sales & Trading | U13: 1 | V13: N/A | W13: Cleardrop Investment | X13: Remote | Y13: Hedge Fund | Z13: 1 | AA13: N/A | AB13: N/A | AC13: N/A | AD13: N/A | AE13: N/A | AF13: N/A | AG13: N/A | AH13: Babson College | AI13: Wellesley, MA | AJ13: Non-target | AK13: 3.73 | AL13: Finance | AM13: 2026 | AN13: MLT, SEO, INROADS | AO13: https://drive.google.com/open?id=1NqojdFJqYC3WoOhaXKdGTluJmPBLgibM | AP13: Investment Banking, Sales and Trading, Private Equity, Asset Management, Management Consulting, Hedge Funds | AQ13: N/A | AR13: N/A | AT13: Community Member
A14: 45753.939 | B14: Steve | C14: Fotso | D14: BLK - 24074 | E14: fotsos@mcmaster.ca | F14: fotsoryan@gmail.com | G14: Personal email | H14: =IF(G14="College/Secondary email:",E14,F14) -> fotsoryan@gmail.com | I14: Hamilton, Canada | J14: Senior analyst | K14: 12265064621 | L14: Male | M14: Fall 2024 | N14: 2026 | O14: North America | P14: Toronto (Canada) | Q14: No | R14: Investment Management Corporation of Ontario (IMCO) | S14: Toronto, Ontario | T14: Asset Managament | U14: N/A | V14: N/A | W14: Toronto Dominion (TD) Bank | X14: Toronto, Ontario | Y14: Compliance | Z14: N/A | AA14: N/A | AB14: N/A | AC14: N/A | AD14: N/A | AE14: N/A | AF14: N/A | AG14: N/A | AH14: McMaster University | AI14: Hamilton, Canada | AJ14: Non-target | AK14: 3.7 | AL14: Finance | AM14: 2026 | AN14: BLK, Investa | AO14: https://drive.google.com/open?id=12TOa85ti3NI1BDLBYA6chnLLNueEtTGS | AP14: Investment Banking, Sales and Trading, Asset Management | AQ14: TD Securities | AT14: Education Pathways (IB, AWM, or PE)
A15: 45753.94 | B15: Madison | C15: Duff | D15: BLK-24131 | E15: madison_duff@brown.edu | F15: munk7@icloud.com | G15: College/Secondary email: | H15: =IF(G15="College/Secondary email:",E15,F15) -> madison_duff@brown.edu | I15: Grosse Pointe Farms, MI | J15: Community Member | K15: +13139104525 | L15: Female | M15: Fall 2024 | N15: 2027 | O15: North America | P15: Boston (U.S.) | Q15: Yes | R15: N/A | S15: N/A | T15: N/A | U15: N/A | V15: N/A | W15: Research through Brown University | X15: Providence, RI | Y15: Economic and Public Policy Research | Z15: N/A | AA15: N/A | AB15: N/A | AC15: N/A | AD15: N/A | AE15: N/A | AF15: N/A | AG15: N/A | AH15: Brown University | AI15: Providence, RI | AJ15: Ivy League | AK15: 3.9 | AL15: Applied Mathematics-Economics (BS) | AM15: 2027 | AN15: MLT, BLK Consulting | AO15: https://drive.google.com/open?id=10KVYEU3vbAxxWv0TMBH85d_6tQXNG0Ng | AP15: Private Equity, Asset Management, Management Consulting, Economic Consulting | AQ15: Bain, BCG, McKinsey, FTI Consulting | AR15: I am the most interested in consulting, either management or economic consulting. | AT15: Community Member
A16: 45753.941 | B16: Olatundun | C16: Badmus | D16: BLK - 24040 | E16: sxb1851@student.bham.ac.uk | F16: olatundun.badmus@yahoo.com | G16: Personal email | H16: =IF(G16="College/Secondary email:",E16,F16) -> olatundun.badmus@yahoo.com | I16: London | J16: Community Member | K16: +447380901007 | L16: Female | M16: Fall 2024 | N16: 2026 | O16: EMEA | P16: London (EMEA) | Q16: No | R16: Schroders | S16: London, UK | T16: Wealth Management | U16: 1 | V16: n/a | W16: Crowe | X16: London, UK | Y16: Accounting | Z16: 1 | AA16: n/a | AB16: n/a | AC16: n/a | AD16: n/a | AE16: n/a | AF16: n/a | AG16: n/a | AH16: University of Birmingham | AI16: Birmingham | AJ16: Russell Group | AK16: n/a | AL16: Economics | AM16: 2026 | AN16: SEO (EMEA), UpReach, Rare Recruitment | AO16: https://drive.google.com/open?id=17V0WdpCBdwelY-oyJoG7avPvWZnasMDQ | AP16: Investment Banking, Asset Management | AQ16: JP morgan | AT16: Education Pathways (IB, AWM, or PE)
A17: 45753.942 | B17: James | C17: Owusu-Ansah | D17: BLK-24045 | E17: jo444@cornell.edu | F17: jowuansah49@gmail.com | G17: College/Secondary email: | H17: =IF(G17="College/Secondary email:",E17,F17) -> jo444@cornell.edu | I17: Ithaca | J17: Community Member | K17: +16073272769 | L17: Male | M17: Fall 2024 | N17: 2027 | O17: North America | P17: New York City (U.S.) | Q17: Yes | R17: N/A | S17: N/A | T17: N/A | U17: N/A | V17: N/A | W17: Lafayette Square | X17: New York, New York | Y17: Private Credit | Z17: n/a | AA17: n/a | AB17: n/a | AC17: n/a | AD17: n/a | AE17: n/a | AF17: n/a | AG17: n/a | AH17: Cornell University | AI17: Ithaca | AJ17: Target | AK17: 3.5 | AL17: Information Science | AM17: 2027 | AN17: BLK | AO17: https://drive.google.com/open?id=1gleLrgWONtmCi6xKomYTsxA4y99K3af0 | AP17: Investment Banking, Sales and Trading, Private Equity, Asset Management, Venture Capital, Hedge Funds | AQ17: Ares Management | AT17: Analyst
A18: 45753.944 | B18: Ava | C18: Brown | D18: BLK - 24046 | E18: avabrown@stanford.edu | F18: aariellebrown@gmail.com | G18: Personal email | H18: =IF(G18="College/Secondary email:",E18,F18) -> aariellebrown@gmail.com | I18: Folsom, CA | J18: Community Member | K18: +19164910955 | L18: Female | M18: Fall 2024 | N18: 2026 | O18: North America | P18: N/A | Q18: Yes | R18: Milliman | S18: Chicago, IL | T18: actuarial | U18: 7-10 | V18: better compensation, better city, opportunity to work on a data science team | W18: Goldman Sachs | X18: New York City, NY | Y18: investment banking | Z18: 2 | AA18: wanted to work in investment banking, not insurance | AB18: Bridgewater Associates | AC18: New York City, NY | AD18: hedge fund | AE18: 2 | AF18: wanted to try something other than investment banking | AG18: NA | AH18: Stanford University | AI18: Stanford, CA | AJ18: Target | AK18: 4.1 | AL18: Data Science BS | AM18: 2026 | AN18: Girls Who Invest | AO18: https://drive.google.com/open?id=1WKm-vBi_KztdpCij9q61Tfiz4cSnw3a_ | AP18: Quantitative Finance (eg. Quant Trading), Management Consulting, Venture Capital, Hedge Funds, Technology | AQ18: Tech VC, roles blending business/CS/math/finance | AT18: Community Member
A19: 45753.947 | B19: Zorian | C19: Facey | D19: BLK-24144 | E19: Zorian_facey@brown.edu | F19: Zorianfacey@gmail.com | G19: Personal email | H19: =IF(G19="College/Secondary email:",E19,F19) -> Zorianfacey@gmail.com | I19: Oviedo, FL | J19: Analyst | K19: +13217465351 | L19: Female | M19: Fall 2024 | N19: 2027 | O19: North America | P19: N/A | Q19: Yes | R19: Leo Legacy (search fund) | S19: Remote | T19: Private equity analyst | U19: N/A | V19: N/A | W19: Wellington Management (incoming) | X19: Boston, MA | Y19: Asset management | Z19: I got matched through Girls Who Invest and was not permitted to apply elsewhere. | AA19: N/A | AB19: N/A | AC19: N/A | AD19: N/A | AE19: N/A | AF19: N/A | AG19: N/A | AH19: Brown University | AI19: Providence, RI | AJ19: Semi-target | AK19: 3.75 | AL19: Applied Mathematics & Economics | AM19: 2027 | AN19: MLT, Girls Who Invest | AO19: https://drive.google.com/open?id=1MWO7gqjlYq4Y2teYnEPNrc0iDJzyD2ti | AP19: Investment Banking, Private Equity, Asset Management, Equity Research | AQ19: Bain Capital, Carlyle, KKR, Fidelity, GS, MS | AR19: Very interested in PE, though I also am exploring investment management and research. | AT19: Analyst
A20: 45753.948 | B20: Obed | C20: Antwi-Baidoo | D20: 22250 | E20: oantwiba@nd.edu | F20: obedantwibaidoo@gmail.com | G20: Personal email | H20: =IF(G20="College/Secondary email:",E20,F20) -> obedantwibaidoo@gmail.com | I20: Ejisu-Krapa | J20: Executive board | K20: +12407080341 | L20: Male | M20: Spring 2022 | N20: 2025 | O20: North America | P20: N/A | Q20: Yes, but would need visa sponsorship after 3 years when my STEM OPT expires. | R20: University of Notre Dame | S20: Notre Dame, IN | T20: Wealth Management | U20: N/A | V20: N/A | W20: Bank of America | X20: New York, NY | Y20: Sales and trading | Z20: 2 | AA20: Wanted to explore | AB20: The Carlyle Group | AC20: New York, NY | AD20: Asset management | AE20: 5+ | AF20: Wanted a wider breadth of experience | AG20: N/A | AH20: University of Notre Dame | AI20: Notre Dame | AJ20: Target | AK20: 3.5 | AL20: Finance and Quantitative Economics | AM20: 2025 | AN20: SEO | AO20: https://drive.google.com/open?id=1ISb_VodWIGWqe4CZJ2oBkLi7fnoKSI_P | AP20: Investment Banking, Sales and Trading, Private Equity, Asset Management, Quantitative Finance (eg. Quant Trading), Management Consulting, Venture Capital, Hedge Funds, Business & Entreprenuership, Technology, Real Estate, Legal, Risk & Compliance, HR | AQ20: Any | AR20: I want to start from a point with the most optionality. | AT20: Alumni (only select if you are graduated/graduating this year)
A21: 45753.958 | B21: Paul | C21: Owusu-Ansah | D21: BLK - 24252 | E21: Rayvon.owusu-ansah@city.ac.uk | F21: paul.owusu-ansah@outlook.com | G21: Personal email | H21: =IF(G21="College/Secondary email:",E21,F21) -> paul.owusu-ansah@outlook.com | I21: London | J21: Analyst | K21: 07395543260 | L21: Male | M21: Fall 2024 | N21: 2026 | O21: EMEA | P21: London (EMEA) | Q21: No | R21: N/A | S21: N/A | T21: N/A | U21: N/A | V21: N/A | W21: Morgan Stanley | X21: London | Y21: Market Risk | Z21: Received full time offer | AA21: N/A | AB21: N/A | AC21: N/A | AD21: N/A | AE21: N/A | AF21: N/A | AG21: Received full time offer for MS didn’t accept because it was not my preferred business area. | AH21: City University of London | AI21: Londo | AJ21: Non-target | AK21: Expected 1st Class Honours | AL21: Mechanical Engineering | AM21: 2026 | AN21: SEO (EMEA) | AO21: https://drive.google.com/open?id=1rACKWwWt9yWzd14P3W2TjFPaGo90ni_- | AP21: Investment Banking, Private Equity | AQ21: N/A | AT21: Analyst
A22: 45753.961 | B22: Nihmatalai | C22: Olaojo | D22: BLK - 24188 | E22: n.olaojo@lse.ac.uk | F22: nihmatalai.olaojo8@gmail.com | G22: Personal email | H22: =IF(G22="College/Secondary email:",E22,F22) -> nihmatalai.olaojo8@gmail.com | I22: London | J22: Analyst | K22: +447955422844 | L22: Female | M22: Fall 2024 | N22: 2027 | O22: EMEA | P22: London (EMEA) | Q22: No | R22: N/A | S22: N/A | T22: N/A | U22: N/A | V22: N/A | W22: N/A | X22: N/A | Y22: N/A | Z22: N/A | AA22: N/A | AB22: N/A | AC22: N/A | AD22: N/A | AE22: N/A | AF22: N/A | AG22: N/A | AH22: London School of Economics and Political Science | AI22: London | AJ22: Target | AK22: N/A | AL22: Accounting and Finance | AM22: 2027 | AN22: SEO (EMEA), Rare Recruitment | AO22: https://drive.google.com/open?id=1OnqIhS613hbnxmlt64_QLYlrUWOfggHq | AP22: Investment Banking, Private Equity, Asset Management, Real Estate | AQ22: N/A | AT22: Analyst
A23: 45753.983 | B23: Xamora | C23: Reed | D23: BLK - 24194 | E23: xreed@aggies.ncat.edu | F23: reed.xamora@gmail.com | G23: Personal email | H23: =IF(G23="College/Secondary email:",E23,F23) -> reed.xamora@gmail.com | I23: Charlotte, NC | J23: Analyst | K23: +17048044258 | L23: Female | M23: Fall 2024 | N23: 2027 | O23: North America | P23: N/A | Q23: Yes | R23: Wells Fargo | S23: Charlotte, NC | T23: Corporate Finance | U23: 1 | V23: N/A | W23: N/A | X23: N/A | Y23: N/A | Z23: N/A | AA23: N/A | AB23: N/A | AC23: N/A | AD23: N/A | AE23: N/A | AF23: N/A | AG23: N/A | AH23: North Carolina A&T State University | AI23: Greensboro, NC | AJ23: HBCU (Historically Black Colleges and Universities) | AK23: 4 | AL23: Economics (Law) | AM23: 2027 | AN23: MLT, Forte, Greenwood Project | AO23: https://drive.google.com/open?id=1FbdVgS-aPP6RzHZx6vasc8lxS2jTXtx2 | AP23: Investment Banking, Sales and Trading, Private Equity, Asset Management, Venture Capital, Hedge Funds | AQ23: Alphine, Bain Capital, Evercore, Goldman Sachs, JP Morgan, KKR, Lazard, Morgan Stanley, Neuberger Berman, PWP, Roark, UBS, Warburg Pincus, Wells Fargo | AT23: Analyst
A24: 45753.994 | B24: Anelda | C24: Agyei | D24: BLK - 24056 | E24: aaagyei@gustavus.edu | F24: ladyanelda14@gmail.com | G24: Personal email | H24: =IF(G24="College/Secondary email:",E24,F24) -> ladyanelda14@gmail.com | I24: Houston | J24: Community Member | K24: +18325857515 | L24: Female | M24: Fall 2024 | N24: 2027 | O24: North America | P24: N/A | Q24: Require sponsorship in the future | R24: N/A | S24: N/A | T24: M/A | U24: N/A | V24: N/A | W24: NA | X24: N/A | Y24: N/A | Z24: N/A | AA24: N/A | AB24: N/A | AC24: N/A | AD24: N/A | AE24: N/A | AF24: N/A | AG24: N/A | AH24: Gustavus Adolphus College | AI24: St Peter | AJ24: Liberal Arts College, Non-Target School | AK24: 3.5 | AL24: Computer science | AM24: 2027 | AN24: Colorstack, rewriting the code | AO24: https://drive.google.com/open?id=1WF_7X5QlG_t0c9WCs9RXUTtO1WkOp6Wg | AP24: Asset Management, Technology | AQ24: Alphine | AT24: Community Member
A25: 45754.005 | B25: Chijioke | C25: Achebe | D25: BLK - 22249 | E25: coa13@georgetown.edu | F25: chijioke.achebe@gmail.com | G25: Personal email | H25: =IF(G25="College/Secondary email:",E25,F25) -> chijioke.achebe@gmail.com | I25: West Orange, NJ | J25: Analyst | K25: +19735184496 | L25: Male | M25: Fall 2022 | N25: 2025 | O25: North America | P25: N/A | Q25: Yes | R25: Essex County Prosecutor's Office | S25: West Orange, NJ | T25: Government | U25: N/A | V25: N/A | W25: UBA America | X25: New York, NY | Y25: Corporate Banking/Trade Finance | Z25: N/A | AA25: N/A | AB25: Morgan Stanley | AC25: New York, NY | AD25: Public Finance Investment Banking | AE25: 1 | AF25: N/A | AG25: N/A | AH25: Georgetown University | AI25: Washington, DC | AJ25: Target | AK25: 3.36 | AL25: International Politics | AM25: 2025 | AN25: N/A | AO25: https://drive.google.com/open?id=1vBAa5PcfoUUihYPMYN4PSi-xZ6Qq2YNR | AP25: Investment Banking, Sales and Trading, Private Equity, Asset Management, Management Consulting, Hedge Funds | AQ25: Morgan Stanley, Goldman Sachs, J.P. Morgan, Bank of America, Citi | AR25: I'm also very interested in commodity trading. Eventually, I want to invest in infrastructure projects across Africa - mining, railroads, energy, airports, ports, shipping, etc | AT25: Alumni (only select if you are graduated/graduating this year)
A26: 45754.094 | B26: Ezinne | C26: Okwesilieze | D26: BLK-24196 | E26: eo6856j@gre.ac.uk | F26: eokwesilieze1@gmail.com | G26: Personal email | H26: =IF(G26="College/Secondary email:",E26,F26) -> eokwesilieze1@gmail.com | I26: Essex | J26: Analyst | K26: +447908100192 | L26: Female | M26: Fall 2024 | N26: 2026 | O26: EMEA | P26: London (EMEA) | Q26: If I gain a work visa | R26: N/A | S26: N/A | T26: N/A | U26: N/A | V26: N/A | W26: Wellcome Trust | X26: Euston, London | Y26: Asset/Investment Management | Z26: I wasn’t of the right year yet to get an offer | AA26: N/A | AB26: N/A | AC26: N/A | AD26: N/A | AE26: N/A | AF26: N/A | AG26: N/A | AH26: Medway School of Pharmacy | AI26: Kent | AJ26: Non-target | AK26: 2:1 | AL26: Pharmacy | AM26: 2026 | AN26: SEO (EMEA), Rare Recruitment | AO26: https://drive.google.com/open?id=1rpc33kD4sQfekQWeOLZ2oaP8_AUetpmg | AP26: Private Equity, Asset Management, Venture Capital, Business & Entreprenuership | AQ26: Any reputable and inspiring firms | AR26: After doing an internship in asset management, investment management, and venture capital, I realized that my pharmacy background could be a great fit for these fields. I’m drawn to the idea of having a bigger impact by shaping industries like healthcare, tech, or pharmaceuticals on a larger scale, beyond just working directly with patients. The critical thinking and data analysis skills I’ve developed in pharmacy are highly transferable, and my knowledge of the healthcare industry can help identify investment opportunities in emerging technologies or drug developments. I’m also interested in the entrepreneurial side of these fields, where I could apply my expertise to fund or start innovative companies. Additionally, asset and investment management offer more career variety and growth, with the chance to work across different industries and expand my professional network. Lastly, the potential for higher compensation is an attractive incentive, especially as I look to build long-term financial security while tackling new challenges. Moving into these fields feels like a natural next step where I can leverage my skills, learn new ones, and make a bigger impact. | AT26: Education Pathways (IB, AWM, or PE)
A27: 45754.099 | B27: Jonathan | C27: Colon | D27: 24256 | E27: Jonathan.Colon58@bcmail.cuny.edu | F27: jonathanacolon2012@gmail.com | G27: Personal email | H27: =IF(G27="College/Secondary email:",E27,F27) -> jonathanacolon2012@gmail.com | I27: New York, NY | J27: Analyst | K27: 9293619519 | L27: Male | M27: Fall 2024 | N27: 2027 | O27: North America | P27: New York City (U.S.) | Q27: Yes | R27: Soundboard Venturefund | S27: New York, NY | T27: Venture Capital | U27: N/A | V27: N/A | W27: Brown Advisory | X27: New York, NY | Y27: Buyside, Wealth Management | Z27: 1 | AA27: N/A | AB27: MD Sass Investment Services | AC27: New York, NY | AD27: Equity Research | AE27: N/A | AF27: N/A | AG27: Morgan Stanley | AH27: Brooklyn College | AI27: CUNY Brooklyn College | AJ27: Non-target | AK27: 4 | AL27: Economic Analysis | AM27: 2027 | AN27: SEO, Project Destined, ALPFA, Wall Street Bound, Hello HIVE, Student Government | AO27: https://drive.google.com/open?id=1v6m_bFc2VA4CUqqLEAuuSJvSw3uVdkd3 | AP27: Investment Banking, Private Equity, Venture Capital, Real Estate | AQ27: Black Rock, Blackstone, Goldman Sachs, Bridgewater, UBS, DWS, CBRE, Blue Owl Capital, Warburg Pincus | AR27: I am very interested in breaking into IB, and heading down a career path that lands me at a Private Equity Fund, or in a role involving Capital Markets within Real Estate Investment Banking | AT27: Analyst
A28: 45754.148 | B28: Charbel | C28: Adjogble | D28: BLK - 24011 | E28: cadjogble@bowdoin.edu | F28: charbelelomadjogble@gmail.com | G28: Personal email | H28: =IF(G28="College/Secondary email:",E28,F28) -> charbelelomadjogble@gmail.com | I28: Newark | J28: Community Member | K28: 9737155324 | L28: Male | M28: Spring 2024 | N28: 2026 | O28: North America | P28: New York City (U.S.) | Q28: Yes | R28: N/A | S28: N/A | T28: N/A | U28: N/A | V28: N/A | W28: N/A | X28: N/A | Y28: N/A | Z28: N/A | AA28: N/A | AB28: Bank of America | AC28: Dallas, Texas | AD28: Global Operations Development | AE28: 1 | AF28: N/A | AG28: N/A | AH28: Bowdoin College | AI28: Brunswick, Maine | AJ28: Liberal Arts College, Non-Target School | AK28: 3.1 | AL28: Economics | AM28: 2026 | AN28: SEO | AO28: https://drive.google.com/open?id=1WAhefabIEtjXWtfxzIVLU2Z3-q4owKus | AP28: Private Equity, Asset Management, Management Consulting, Business & Entreprenuership, Technology | AQ28: JPMorgan Chase, Deutsche Bank | AT28: Community Member
A29: 45754.202 | B29: David | C29: Ariyo | D29: BLK-24246 | E29: Ucnvd08@ucl.ac.uk | F29: DavidArriyo15@gmail.com | G29: Personal email | H29: =IF(G29="College/Secondary email:",E29,F29) -> DavidArriyo15@gmail.com | I29: London | J29: Analyst | K29: +447930300316 | L29: Male | M29: Fall 2024 | N29: 2025 | O29: EMEA | P29: London (EMEA) | Q29: No | R29: N/A | S29: N/A | T29: N/A | U29: N/A | V29: N/A | W29: N/A | X29: N/A | Y29: N/A | Z29: N/A | AA29: N/A | AB29: Standard Chartered | AC29: London | AD29: Client coverage | AE29: 1 | AF29: N/A | AG29: Standard Chartered | AH29: University College London | AI29: London | AJ29: Russed group | AK29: 2:1 | AL29: Pharmacy | AM29: 2025 | AN29: N/A | AO29: https://drive.google.com/open?id=10ngrzdNG30QZicjH9i2arBJa3DmSo_wM | AP29: Asset Management, Wealth management, Credit risk | AQ29: JP morgan, Goldman Sachs | AT29: Alumni (only select if you are graduated/graduating this year)
A30: 45754.23 | B30: Ausar | C30: Myers | D30: 24089 | E30: Ausarmyers@sandiego.edu | F30: Am23.myers@gmail.com | G30: College/Secondary email: | H30: =IF(G30="College/Secondary email:",E30,F30) -> Ausarmyers@sandiego.edu | I30: Miami, Florida | J30: Analyst | K30: 17866605695 | L30: Male | M30: Fall 2024 | N30: 2027 | O30: North America | P30: N/A | Q30: Yes | R30: The Shark Group | S30: Miami, Florida | T30: Private Equity | U30: 1 | V30: N/A | W30: Project Destined | X30: New York, New York | Y30: Provate Equity | Z30: 1 | AA30: N/A | AB30: Nomura | AC30: New York, New York | AD30: Global Markets | AE30: 1 | AF30: N/A | AG30: N/A | AH30: The University of San Diego | AI30: San Diego | AJ30: Non-target | AK30: 3.7 | AL30: International Business | AM30: 2027 | AN30: MLT, Project Destined, HeadStart | AO30: https://drive.google.com/open?id=1GB2pvqbWT4-z8lbu0-KVcJahLlKrgp4P | AP30: Private Equity, Venture Capital, Business & Entreprenuership | AQ30: LLR, Roark, Advent, Bain Capital, Carlyle, and Alpine | AR30: I have currently found my Junior summer internship but as I align more with private equity, I am preparing for my graduating summer. | AT30: Analyst
A31: 45754.239 | B31: Odelia | C31: Uwanogho | D31: BLK - 24062 | E31: odelia.uwanogho1@gmail.com | F31: odelia.uwanogho1@gmail.com | G31: Personal email | H31: =IF(G31="College/Secondary email:",E31,F31) -> odelia.uwanogho1@gmail.com | I31: Bristol | J31: Community Member | K31: +447309681988 | L31: Female | M31: Fall 2024 | N31: 2028 | O31: EMEA | P31: N/A | Q31: No | R31: N/A | S31: N/A | T31: N/A | U31: N/A | V31: N/A | W31: N/A | X31: N/A | Y31: N/A | Z31: N/A | AA31: N/A | AB31: N/A | AC31: N/A | AD31: N/A | AE31: N/A | AF31: N/A | AG31: N/A | AH31: University of Bristol | AI31: Bristol | AJ31: Target | AK31: N/A | AL31: Business and management with innovation | AM31: 2028 | AN31: n/a | AO31: https://drive.google.com/open?id=1WA-a3a2Hel79BTArfeKJeMMGslea8Iok | AP31: Investment Banking, Private Equity, Asset Management, Management Consulting, Business & Entreprenuership | AQ31: N/A | AT31: Education Pathways (IB, AWM, or PE)
A32: 45754.259 | B32: Leon | C32: Ross | D32: 23276 | E32: va22924@bristol.ac.uk | F32: leon2ross9@gmail.com | G32: Personal email | H32: =IF(G32="College/Secondary email:",E32,F32) -> leon2ross9@gmail.com | I32: Bristol | J32: Executive board | K32: 447398562010 | L32: Male | M32: Fall 2023 | N32: 2025 | O32: EMEA | P32: N/A | Q32: No | R32: Lloyds Banking Group | S32: London | T32: Commercial Banking | U32: 1 | V32: n/a | W32: J.P. Morgan | X32: London | Y32: Investment Banking | Z32: 1 | AA32: n/a | AB32: n/a | AC32: n/a | AD32: n/a | AE32: n/a | AF32: n/a | AG32: J.P. Morgan | AH32: University of Bristol | AI32: Bristol | AJ32: Target | AK32: 1st | AL32: Mathematics | AM32: 2025 | AN32: SEO (EMEA), UpReach, Rare Recruitment | AO32: https://drive.google.com/open?id=1luHQ_wUzQNC-2WXeESQqkxrrq6zD2T7H | AP32: Investment Banking, Private Equity | AQ32: All private equity firms | AR32: Interested in Private Equity opportunities in the UK and US | AT32: Alumni (only select if you are graduated/graduating this year)
A33: 45754.282 | B33: Justin | C33: Holmes | D33: BLK-23056 | E33: Justin.holmes@bc.edu | F33: Justindavidholmes@gmail.com | G33: College/Secondary email: | H33: =IF(G33="College/Secondary email:",E33,F33) -> Justin.holmes@bc.edu | I33: Westport, CT | J33: Community Member | K33: +12039706135 | L33: Male | M33: Spring 2023 | N33: 2026 | O33: North America | P33: Boston (U.S.) | Q33: Yes | R33: Artemis Real Estate Partners | S33: Washington, D.C. | T33: RE Private Equity | U33: N/a | V33: N/A` | W33: Revelstoke Capital Partners | X33: Denver, Colorado | Y33: Private Equity | Z33: 2 | AA33: Decided not to do consulting, was more interested in PE. Also another firm was in NYC and I wanted a change of scenery. | AB33: Moelis & Co. | AC33: New York, New York | AD33: Investment Banking | AE33: 5 | AF33: Moelis & Co. was top choice for my self. | AG33: N/A | AH33: Boston College | AI33: Boston, MA | AJ33: Target | AK33: 3.75 | AL33: Finance | AM33: 2026 | AN33: MLT, SEO | AO33: https://drive.google.com/open?id=1OHxZ5DOIMQMSqsFJ-N6WgncBxisKLZld | AP33: Investment Banking, Private Equity, Hedge Funds, Real Estate | AQ33: Arsenal Capital Partners, Bain Capital, Carlyle, KKR, Roark Capital Partners, Warburg Pincus | AR33: Upcoming internship is generalist program, I am still undecided on where I want to go but want to try all the different groups to see what I am most interested in. Currently I am most interested in TMT, RE, and Healthcare/Consumer Retail. | AT33: Community Member
A34: 45754.297 | B34: George | C34: Orji | D34: BLK-24095 | E34: george.orji@warwick.ac.uk | F34: georgeorji05@gmail.com | G34: Personal email | H34: =IF(G34="College/Secondary email:",E34,F34) -> georgeorji05@gmail.com | I34: London | J34: Community Member | K34: +447947693396 | L34: Male | M34: Fall 2024 | N34: 2026 | O34: EMEA | P34: N/A | Q34: No | R34: AKO Capital | S34: London, United Kingdom | T34: Asset Management | U34: 2 | V34: Internship was not long enough - would only be for 1 week | W34: Baird | X34: London, United Kingdom | Y34: Investment Banking | Z34: 1 | AA34: N/A | AB34: N/A | AC34: N/A | AD34: N/A | AE34: N/A | AF34: N/A | AG34: N/A | AH34: The University of Warwick | AI34: Coventry | AJ34: Target | AK34: 0.71 | AL34: Economics - Politics Minor | AM34: 2026 | AN34: SEO (EMEA), Rare Recruitment | AO34: https://drive.google.com/open?id=1rVsOCqIWQZhBvMfIr5YAFGJMzeMVTBGW | AP34: Investment Banking | AQ34: Citi, UBS, Barclays | AR34: Aim is to spend 2-4 years in investment banking before pivoting to the buy-side, with a particular interest in Private Equity | AT34: Community Member
A35: 45754.316 | B35: Otman | C35: Atfi | D35: BLK-24005 | E35: otmanatfi@vt.edu | F35: otmanatfi04@gmail.com | G35: Personal email | H35: =IF(G35="College/Secondary email:",E35,F35) -> otmanatfi04@gmail.com | I35: Richmond, VA | J35: Analyst | K35: +16176787176 | L35: Male | M35: Spring 2024 | N35: 2026 | O35: North America | P35: N/A | Q35: Yes | R35: N/A | S35: N/A | T35: N/A | U35: N/A | V35: N/A | W35: Dominion Energy | X35: Richmond, VA | Y35: Energy | Z35: 1 | AA35: N/A | AB35: Wells Fargo | AC35: Boston, MA | AD35: Banking | AE35: 3 | AF35: I believed that this opportunity closely aligns with my future goals. | AG35: N/A | AH35: Virginia Tech | AI35: Blacksburg | AJ35: Non-target | AK35: 3.63 | AL35: Entrepreneurship Innovation Technology and Business Management | AM35: 2026 | AN35: SEO | AO35: https://drive.google.com/open?id=1H9Yxs0NaibyPCNQOwnx1lGDikSIGWFmd | AP35: Asset Management, Management Consulting, Business & Entreprenuership | AQ35: Goldman Sachs, J.P. Morgan, Morgan Stanley, UBS | AT35: Community Member
A36: 45754.319 | B36: James | C36: Benjamin | D36: BLK - 23397 | E36: j.benjamin3@lse.ac.uk | F36: jm.benjamin@outlook.com | G36: Personal email | H36: =IF(G36="College/Secondary email:",E36,F36) -> jm.benjamin@outlook.com | I36: London | J36: Executive board | K36: +447478243983 | L36: Male | M36: Spring 2024 | N36: 2025 | O36: EMEA | P36: London (EMEA) | Q36: No | R36: HSBC, PwC | S36: London, UK | T36: Asset Management | U36: 2 | V36: N/A | W36: PwC | X36: London | Y36: Investment Banking | Z36: 1 | AA36: N/A | AB36: Barings Investment Management | AC36: London | AD36: Asset Management | AE36: 2 | AF36: Pay package | AG36: Morgan Stanley (off-cycle internship) | AH36: The London School of Economics and Political Science | AI36: London | AJ36: Target | AK36: 3.7 | AL36: MSc Accounting and Finance | AM36: 2025 | AN36: SEO (EMEA), Rare Recruitment | AO36: https://drive.google.com/open?id=1KIavo1mW6_AQnsL9bVVi9Um_E8Wy77oK | AP36: Investment Banking, Private Equity, Asset Management, Hedge Funds | AQ36: All Partners | AR36: Looking to move into private credit or private equity long-term | AT36: Alumni (only select if you are graduated/graduating this year)
A37: 45754.354 | B37: Isaiah | C37: Joyner | D37: 24244 | E37: ijjoyner@unc.edu | F37: i.joyner023@gmail.com | G37: Personal email | H37: =IF(G37="College/Secondary email:",E37,F37) -> i.joyner023@gmail.com | I37: Asheville | J37: Analyst | K37: 8284421521 | L37: Male | M37: Fall 2024 | N37: 2027 | O37: North America | P37: N/A | Q37: Yes | R37: International Investments LLC | S37: Raleigh, NC | T37: Investment Management | U37: N/A | V37: N/A | W37: Unc Management Company | X37: Chapel Hill, NC | Y37: Endowment Management | Z37: 2 | AA37: N/A | AB37: N/A | AC37: N/A | AD37: N/A | AE37: N/A | AF37: N/A | AG37: N/A | AH37: University of North Carolina at Chapel Hill | AI37: Chapel Hill | AJ37: Non-target | AK37: 3.63 | AL37: Business Admin(Finance) | AM37: 2027 | AN37: MLT, SEO | AO37: https://drive.google.com/open?id=1cc79unHY2I3HtGKSyqYgAcrb4LjPGcbn | AP37: Investment Banking, Private Equity, Asset Management, Venture Capital, Hedge Funds | AQ37: BB Investment Banks, Asset managers, Hedge Funds | AR37: I’m interested in banking or fundamental type investing jobs. | AT37: Analyst
A38: 45754.368 | B38: Che | C38: Bernard | D38: 23322 | E38: che.bernard@st-hughs.ox.ac.uk | F38: chelarsbernard@gmail.com | G38: Personal email | H38: =IF(G38="College/Secondary email:",E38,F38) -> chelarsbernard@gmail.com | I38: London | J38: Community Member | K38: +447306527785 | L38: Male | M38: Spring 2023 | N38: 2027 | O38: EMEA | P38: London (EMEA) | Q38: No | R38: Allenby Capital | S38: London | T38: Investment Banking | U38: 1 | V38: N/A | W38: Millenium Management | X38: London | Y38: Hedge Fund | Z38: 1 | AA38: N/A | AB38: N/A | AC38: N/A | AD38: N/A | AE38: N/A | AF38: N/A | AG38: N/A | AH38: University of Oxford | AI38: Oxford | AJ38: Target | AK38: 2:1 | AL38: Chemistry | AM38: 2027 | AN38: SEO (EMEA), UpReach, Rare Recruitment | AO38: https://drive.google.com/open?id=1AyGTWUHp1KyUV2kK6soptECDt8SPTkcK | AP38: Investment Banking, Private Equity, Hedge Funds | AQ38: Citadel, Blackstone | AT38: Community Member
A39: 45754.397 | B39: Jaden | C39: Mighten | D39: BLK - 23038 | E39: jdmighten@gmail.com | F39: mightenjaden@gmail.com | G39: Personal email | H39: =IF(G39="College/Secondary email:",E39,F39) -> mightenjaden@gmail.com | I39: Nottingham | J39: Portfolio Manager | K39: +447546287551 | L39: Male | M39: Spring 2023 | N39: 2026 | O39: EMEA | P39: London (EMEA) | Q39: No | R39: Scotiabank | S39: London | T39: Investment Banking | U39: 23 Spring week offers, 8 summer internship offers | V39: NA | W39: Goldman Sachs | X39: London | Y39: Investment Banking | Z39: NA | AA39: NA | AB39: NA | AC39: NA | AD39: NA | AE39: NA | AF39: NA | AG39: NA | AH39: LSE | AI39: London | AJ39: Target | AK39: 4 | AL39: Economics | AM39: 2026 | AN39: SEO (EMEA), UpReach, Rare Recruitment | AO39: https://drive.google.com/open?id=1l8zmVYfBkZu0lYCnwIFsH4oejyObf2uT | AP39: Investment Banking, Private Equity, Asset Management, Quantitative Finance (eg. Quant Trading), Hedge Funds, Business & Entreprenuership | AQ39: Private Equity Firms, Hedge Funds | AR39: 2 + 2, IB to HF/PE | AT39: Analyst
A40: 45754.409 | B40: Jeffrey | C40: Odiase | D40: 23119 | E40: odiase@bu.edu | F40: jeoj.ntw@gmail.com | G40: College/Secondary email: | H40: =IF(G40="College/Secondary email:",E40,F40) -> odiase@bu.edu | I40: Newark, New Jersey | J40: Community Member | K40: 9735190398 | L40: Male | M40: Spring 2024 | N40: 2027 | O40: North America | P40: Boston (U.S.) | Q40: Yes | R40: BlackRock | S40: Manhattan, NY | T40: Asset Management | U40: N/A | V40: N/A | W40: BlackRock | X40: Manhattan, NY | Y40: Asset Management | Z40: N/A | AA40: N/A | AB40: N/A | AC40: N/A | AD40: N/A | AE40: N/A | AF40: N/A | AG40: N/A | AH40: Boston University | AI40: Boston, MA | AJ40: Non-target | AK40: 3.03 | AL40: Economics and Computer Science | AM40: 2027 | AN40: N/A | AO40: https://drive.google.com/open?id=162jGPQdvCw12F78RltRi2JIWogkAO5Qu | AP40: Sales and Trading, Private Equity, Asset Management, Quantitative Finance (eg. Quant Trading), Venture Capital, Hedge Funds, Business & Entreprenuership, Technology, Real Estate | AQ40: Jane Street, Fidelity, JPMorgan | AT40: Education Pathways (IB, AWM, or PE)
A41: 45754.413 | B41: Mohamed | C41: El Hadj Sidi | D41: BLK - 24193 | E41: Melhadjs@gmu.edu | F41: Mohamedhadjsidi11@gmail.com | G41: Personal email | H41: =IF(G41="College/Secondary email:",E41,F41) -> Mohamedhadjsidi11@gmail.com | I41: Falls Church | J41: Community Member | K41: 2025603389 | L41: Male | M41: Fall 2024 | N41: 2027 | O41: North America | P41: N/A | Q41: Yes | R41: NA | S41: Na | T41: Na | U41: 1 | V41: Na | W41: Andersen Financial Services | X41: DC | Y41: Accounting Tax | Z41: Na | AA41: Na | AB41: JPM | AC41: New York City | AD41: Markets | AE41: 1 | AF41: Na | AG41: Na | AH41: George Mason University | AI41: Fairfax | AJ41: Non-target | AK41: 3.91 | AL41: Accounting and Finance Double Major | AM41: 2027 | AN41: MLT, SEO | AO41: https://drive.google.com/open?id=1a9ztFInv5FtTtTHKZ3BOzcfFyzpQG-8N | AP41: Research | AQ41: Nothing, thank you! | AT41: Community Member
A42: 45754.424 | B42: Makenzie | C42: Swann | D42: BLK-23181 | E42: mswann@email.sc.edu | F42: makenzieswann623@gmail.com | G42: Personal email | H42: =IF(G42="College/Secondary email:",E42,F42) -> makenzieswann623@gmail.com | I42: Rock Hill, SC | J42: Analyst | K42: 19088213315 | L42: Female | M42: Fall 2023 | N42: 2026 | O42: North America | P42: N/A | Q42: Yes | R42: N/A | S42: N/A | T42: N/A | U42: N/A | V42: N/A | W42: KPMG | X42: New York City, NY | Y42: Financial Services | Z42: 2 | AA42: The 2nd company waited too long to give out offers | AB42: PwC | AC42: New York City, NY | AD42: M&A | AE42: 3 | AF42: PwC had the most potential for growth and increased personal interest | AG42: N/A | AH42: University of South Carolina | AI42: Columbia, SC | AJ42: Public Flagship University | AK42: 3.5 | AL42: Accounting, Finance, Biz Analytics | AM42: 2026 | AN42: none | AO42: https://drive.google.com/open?id=1vsKwDCx3ofiCCcsXooF8InXXwWPQSv-H | AP42: Asset Management, Management Consulting, Business & Entreprenuership, Technology | AQ42: N/A | AR42: N/A | AT42: Analyst
A43: 45754.427 | B43: Finhas Mesfin | C43: Legesse | D43: BLK-24047 | E43: legessfi@shu.edu | F43: finhaslegesse@gmail.com | G43: Personal email | H43: =IF(G43="College/Secondary email:",E43,F43) -> finhaslegesse@gmail.com | I43: Riverdale | J43: Community Member | K43: +15713147790 | L43: Male | M43: Fall 2024 | N43: 2027 | O43: North America | P43: New York City (U.S.) | Q43: Yes | R43: HST Consulting | S43: Addis Ababa, Ethiopia | T43: Consulting | U43: N/A | V43: N/A | W43: N/A | X43: N/A | Y43: N/A | Z43: N/A | AA43: N/A | AB43: Citi | AC43: New York City, New York | AD43: Sales & Trading | AE43: 1 | AF43: N/A | AG43: N/A | AH43: Seton Hall University | AI43: South Orange, New Jersey | AJ43: Non-target | AK43: 3.7 | AL43: (B.S.) Mathematical Finance & (B.S.) Quantitative Economics and Econometrics | AM43: 2027 | AN43: Project Destined | AO43: https://drive.google.com/open?id=1i-GLYTEv1td-L28t7_U_TdnHF2Zm99G8 | AP43: Investment Banking, Sales and Trading, Private Equity, Venture Capital, Hedge Funds | AQ43: Goldman Sachs, Morgan Stanley, KKR, Jane Street, Sixth Street Partners, Vanguard | AR43: I’m really interested in Capital Markets, and Leveraged Finance in particular, because I enjoy the challenge of assessing credit risk. I find it exciting to understand a firms capital structure, and think critically about how market conditions affect both risk and pricing. I’ve accepted an offer to join Citi next summer as a Sales & Trading Summer Analyst, and I plan to use internal mobility to hopefully land on a LevFin desk. I think starting on the trading floor will give me great insight into how credit is priced and traded, which is an experience that would translate well into a LevFin role down the line. | AT43: Analyst
A44: 45754.432 | B44: So-Owunari | C44: Danagogo | D44: BLK-23382 | E44: So-Owunari.danagogo@warwick.ac.uk | F44: Sophieroyalty@gmail.com | G44: Personal email | H44: =IF(G44="College/Secondary email:",E44,F44) -> Sophieroyalty@gmail.com | I44: Coventry | J44: Community Member | K44: +447555288123 | L44: Female | M44: Spring 2024 | N44: 2025 | O44: EMEA | P44: London (EMEA) | Q44: No | R44: Lloyds Banking Group | S44: London | T44: Corporate Banking | U44: N/A | V44: N/A | W44: Legal & General | X44: London | Y44: Asset management | Z44: 1 | AA44: N/A | AB44: N/A | AC44: N/A | AD44: N/A | AE44: N/A | AF44: N/A | AG44: Legal and General | AH44: University of Warwick | AI44: Coventry | AJ44: Target | AK44: First | AL44: Economics and Global Sustainable Development | AM44: 2025 | AN44: None | AO44: https://drive.google.com/open?id=1T5bw-gOGkByYSp1uW-wHMCrXCX4Wz_3Q | AP44: Private Equity, Asset Management, Venture Capital, Hedge Funds, Real Estate | AQ44: Ares Management | AT44: Community Member
A45: 45754.435 | B45: Kai | C45: Antoine | D45: BLK - 24245 | E45: kantoine@uwo.ca | F45: kaiantoiner@gmail.com | G45: Personal email | H45: =IF(G45="College/Secondary email:",E45,F45) -> kaiantoiner@gmail.com | I45: Oakville, Ontario | J45: Analyst | K45: +19054664419 | L45: Male | M45: Fall 2024 | N45: 2027 | O45: North America | P45: N/A | Q45: Yes | R45: One Queen Capital Inc. | S45: Toronto, Ontario | T45: Private Equity | U45: n/a | V45: n/a | W45: One Queen Capital Inc. | X45: Toronto, Ontario | Y45: Private Equity | Z45: n/a | AA45: n/a | AB45: n/a | AC45: n/a | AD45: n/a | AE45: n/a | AF45: n/a | AG45: n/a | AH45: Western University | AI45: London, Ontario | AJ45: Non-target | AK45: 3.7 | AL45: Economics | AM45: 2027 | AN45: n/a | AO45: https://drive.google.com/open?id=17n1v7X9Lkvt-zjfsdZTB_Bcfc4QsRZao | AP45: Investment Banking, Sales and Trading, Private Equity, Asset Management, Venture Capital, Business & Entreprenuership | AQ45: Warburg Pincus, Sixth Street Partners, Evercore, Lazard, Carlyle | AR45: I'm passionate about investing and facilitating investments in innovation and backing businesses that are shaping the future. I'm especially interested in how thoughtful capital allocation can accelerate growth, drive operational excellence, and create lasting impact. Whether through advising companies or directly investing in them, I’m drawn to opportunities where analysis and strategic thinking can help unlock long-term value. | AT45: Analyst
A46: 45754.445 | B46: Kosi | C46: Udochukwu | D46: BLK - 22311 | E46: N/A | F46: kosiudochukwu@gmail.com | G46: Personal email | H46: =IF(G46="College/Secondary email:",E46,F46) -> kosiudochukwu@gmail.com | I46: Lagos | J46: Analyst | K46: +14709207034 | L46: Male | M46: Spring 2022 | N46: 2025 | O46: North America | P46: Atlanta (U.S.) | Q46: Yes | R46: N/A | S46: N/A | T46: N/A | U46: N/A | V46: N/A | W46: PricewaterhouseCoopers | X46: Atlanta, GA | Y46: Start Internship | Z46: N/A | AA46: N/A | AB46: Advisory | AC46: Washington, D.C | AD46: Advisory | AE46: 1 | AF46: Money wasn't enough for Palo Alto | AG46: PricewaterhouseCoopers | AH46: Emory University | AI46: Atlanta, Georgia | AJ46: Semi-Target | AK46: 3.7 | AL46: Finance and Organization & Management | AM46: 2025 | AN46: SEO, INROADS, Project Destined | AO46: https://drive.google.com/open?id=1cXfIB4Mhx1849VcyS0Rbfg5EgXZ9bhr3 | AP46: Sales and Trading, Asset Management, Management Consulting, Business & Entreprenuership, Technology, Real Estate, Legal, Risk & Compliance | AQ46: Wells Fargo, Brigade Capital, Bain Capital, Aristeia Capital, Acadian Asset Management. | AR46: I am interested in risk, entrepreneurship, consulting, asset management, and financial markets. | AT46: Alumni (only select if you are graduated/graduating this year)
A47: 45754.447 | B47: Ayeyi Akua Asantewaa | C47: Nyarko-Lartey | D47: 24145 | E47: ayeyi_akua_asantewaa.nyarko-lartey@fs-students.de | F47: ayeyi.nyarkolartey@gmail.com | G47: Personal email | H47: =IF(G47="College/Secondary email:",E47,F47) -> ayeyi.nyarkolartey@gmail.com | I47: Frankfurt am Main | J47: Community Member | K47: +4917623422482 | L47: Female | M47: Fall 2024 | N47: 2025 | O47: EMEA | P47: Frankfurt (EMEA) | Q47: Currently I am not authorised to work in the US. | R47: AIESEC | S47: Accra, Ghana | T47: Not-For -Profit Organization | U47: N/A | V47: N/A | W47: N/A | X47: N/A | Y47: N/A | Z47: N/A | AA47: N/A | AB47: N/A | AC47: N/A | AD47: N/A | AE47: N/A | AF47: N/A | AG47: N/A | AH47: Frankfurt School of Finance & Management | AI47: Frankfurt am Main | AJ47: Target | AK47: Not yet available. Current average grade 2.87 / 6 with 1 being best. | AL47: Finance - Risk Management | AM47: 2025 | AN47: No | AO47: https://drive.google.com/open?id=1oq1H-Y0kKRIr7no_2oIe9BMBbSjQlf57 | AP47: Investment Banking, Quantitative Finance (eg. Quant Trading), Hedge Funds | AQ47: JP Morgan, Goldman Sachs, Lazard, Standard Chartered, Citi | AR47: I’m interested in financial analyst roles for starters, especially as I look to land my first full-time role. I'm eager to develop a strong foundation in financial modeling, valuation, and data analysis. One area I’m particularly drawn to is mergers and acquisitions—I find the strategic aspect of M&A fascinating, especially how companies assess synergies and growth opportunities. I’m hoping to join a team where I can learn from experienced professionals, contribute to impactful projects, and build the skills needed for a long-term career in corporate finance or investment banking. | AT47: Alumni (only select if you are graduated/graduating this year)
A48: 45754.481 | B48: Mariam | C48: Abisoye | D48: BLK-23367 | E48: maabisoye04@my.fisk.edu | F48: mariamabisoye3@gmail.com | G48: Personal email | H48: =IF(G48="College/Secondary email:",E48,F48) -> mariamabisoye3@gmail.com | I48: Nashville | J48: Roark fellow | K48: +1 | L48: Female | M48: Spring 2023 | N48: 2027 | O48: North America | P48: N/A | Q48: Yes | R48: Deloitte | S48: Houston, TX | T48: Accounting | U48: 1 | V48: N/A | W48: Morgan Stanley | X48: New York, NY | Y48: Global Capital Markets | Z48: N/A | AA48: N/A | AB48: N/A | AC48: N/A | AD48: N/A | AE48: N/A | AF48: N/A | AG48: N/A | AH48: Fisk University | AI48: Nashville | AJ48: Liberal Arts College, Non-Target School | AK48: 3.88/4.0 | AL48: Business Administration (Financial Economics) & Data Science | AM48: 2027 | AN48: N/A | AO48: https://drive.google.com/open?id=1s6LsxOPZaEv7JcCLtutkb1R1F9KbE5pp | AP48: Management Consulting | AQ48: No preference | AT48: Analyst
A49: 45754.482 | B49: Nicole | C49: Ogunlaja | D49: BLK - 23328 | E49: no349@bath.ac.uk | F49: nicoleogu@icloud.com | G49: Personal email | H49: =IF(G49="College/Secondary email:",E49,F49) -> nicoleogu@icloud.com | I49: London | J49: Trainee Analyst | K49: +447415169864 | L49: Female | M49: Spring 2024 | N49: 2027 | O49: EMEA | P49: London (EMEA) | Q49: Yes | R49: Alma Strategic Communications | S49: London | T49: Financial Communications PR | U49: 1 | V49: N/A | W49: N/A | X49: N/A | Y49: N/A | Z49: N/A | AA49: N/A | AB49: N/A | AC49: N/A | AD49: N.A | AE49: N/A | AF49: N/A | AG49: N/A | AH49: University of Bath | AI49: Bath | AJ49: Non - Russel Group | AK49: First Class | AL49: International Development with Economics | AM49: 2027 | AN49: SEO | AO49: https://drive.google.com/open?id=12p7No97xJZ8wNsX9cRlitD9fuOwvH5Wc | AP49: Sales and Trading, Private Equity, Asset Management | AQ49: Advent, Barings, Jane Street | AT49: Community Member
A50: 45754.495 | B50: Chidubem | C50: Eneanya | D50: BLK - 22304 | E50: tud52483@temple.edu | F50: dubieneanya@gmail.com | G50: Personal email | H50: =IF(G50="College/Secondary email:",E50,F50) -> dubieneanya@gmail.com | I50: Philadelphia | J50: Analyst | K50: +12673984860 | L50: Male | M50: Fall 2022 | N50: 2025 | O50: North America | P50: Philadelphia (U.S.) | Q50: Yes | R50: N/A | S50: N/A | T50: N/A | U50: N/A | V50: N/A | W50: N/A | X50: N/A | Y50: N/A | Z50: N/A | AA50: N/A | AB50: N/A | AC50: N/A | AD50: N/A | AE50: N/A | AF50: N/A | AG50: N/A | AH50: Lewis Katz School of Medicine at Temple University | AI50: Philadelphia | AJ50: Non-target | AK50: 3.36 | AL50: Biomedical Sciences / Neuroscience | AM50: 2025 | AN50: N/A | AO50: https://drive.google.com/open?id=1FCPViZHE_Vie8qq3USbQfCJldcAAtTWm | AP50: Hedge Funds, Equity Research | AQ50: N/A | AR50: N/A | AT50: Alumni (only select if you are graduated/graduating this year)
A51: 45754.496 | B51: Elijah | C51: Jacobs | D51: BLK - 24122 | E51: eli.n.jacobs.28@dartmouth.edu | F51: elijahjacobs113@gmail.com | G51: College/Secondary email: | H51: =IF(G51="College/Secondary email:",E51,F51) -> eli.n.jacobs.28@dartmouth.edu | I51: Raleigh, North Carolina | J51: Community Member | K51: +19197488842 | L51: Male | M51: Fall 2024 | N51: 2028 | O51: North America | P51: N/A | Q51: Yes | R51: Backstage Capital | S51: Los Angles, CA | T51: Venture Capital | U51: N/A | V51: N/A | W51: N/A | X51: N/A | Y51: N/A | Z51: N/A | AA51: N/A | AB51: N/A | AC51: N/A | AD51: N/A | AE51: N/A | AF51: N/A | AG51: N/A | AH51: Dartmouth College | AI51: Hanover, NH | AJ51: Target | AK51: 3.7 | AL51: Economics & International Studies | AM51: 2028 | AN51: Project Destined | AO51: https://drive.google.com/open?id=1ScaR3I-T_rPsV5nnCoT0R8-v9FgCbUpg | AP51: Investment Banking, Sales and Trading, Asset Management, Management Consulting, Venture Capital, Hedge Funds | AQ51: Bain, JP Morgan, Goldman Sachs | AT51: Education Pathways (IB, AWM, or PE)
A52: 45754.497 | B52: Clay | C52: Griffin | D52: BLK - 24227 | E52: clayg@smu.edu | F52: claygriffin01@gmail.com | G52: Personal email | H52: =IF(G52="College/Secondary email:",E52,F52) -> claygriffin01@gmail.com | I52: Cos Cob | J52: Analyst | K52: +19173273292 | L52: Male | M52: Fall 2024 | N52: 2026 | O52: North America | P52: New York City (U.S.) | Q52: Yes | R52: Bank of America Merrill Lynch | S52: New York, NY | T52: Wealth Management | U52: 1 | V52: N/A | W52: Bank of America Merrill Lynch | X52: New York, NY | Y52: Wealth Management | Z52: 1 | AA52: N/A | AB52: Fortress Investment Group | AC52: New York, NY | AD52: Private Equity and Credit | AE52: 1 | AF52: N/A | AG52: N/A | AH52: Southern Methodist University | AI52: Dallas | AJ52: Non-target | AK52: 3.59 | AL52: Financial Economics | AM52: 2026 | AN52: SEO | AO52: https://drive.google.com/open?id=1_DOcoO8FeK9BFZSrDhwMlCx3MSo_1eui | AP52: Investment Banking, Private Equity, Venture Capital, Hedge Funds | AQ52: All Partners | AT52: Analyst
A53: 45754.498 | B53: Marieme | C53: N'Diaye | D53: 24106 | E53: msn2157@barnard.edu | F53: mariemesndiaye5@gmail.com | G53: College/Secondary email: | H53: =IF(G53="College/Secondary email:",E53,F53) -> msn2157@barnard.edu | I53: Weehawken | J53: Analyst | K53: 9178224037 | L53: Female | M53: Fall 2024 | N53: 2027 | O53: North America | P53: New York City (U.S.) | Q53: Yes | R53: N/A | S53: N/A | T53: N/A | U53: N/A | V53: N/A | W53: Casey Family Programs | X53: New York City, NY | Y53: Investment Management | Z53: 2 | AA53: Location | AB53: JP Morgan ( Incoming 2026) | AC53: NYC | AD53: Equity Research | AE53: 3 | AF53: Job role | AG53: .N/A | AH53: Barnard College of Columbia University | AI53: NYC, NY | AJ53: Target | AK53: 3.6 | AL53: Economics | AM53: 2027 | AN53: Girls Who Invest | AO53: https://drive.google.com/open?id=1AKBxBz1s0gA3OGQ8BH5XVeI1XotiE-mS | AP53: Sales and Trading, Asset Management, Research | AQ53: JPM, Goldman, UBS | AT53: Analyst
A54: 45754.508 | B54: Jordan | C54: During | D54: BLK - 24109 | E54: jcd99@pitt.edu | F54: jduring2022@gmail.com | G54: Personal email | H54: =IF(G54="College/Secondary email:",E54,F54) -> jduring2022@gmail.com | I54: Houston | J54: Analyst | K54: +18322127272 | L54: Male | M54: Fall 2024 | N54: 2026 | O54: North America | P54: N/A | Q54: Yes | R54: Connors Group | S54: Pittsburgh, PA | T54: Consulting | U54: 6 | V54: Consulting included paid travel and per diem all summer | W54: Accenture Strategy | X54: Houston | Y54: Consulting | Z54: 5 | AA54: Not equivalent pay or opportunity to practice strategy | AB54: Bain & Co | AC54: Houston | AD54: consulting | AE54: 2 | AF54: Opportunity was not positioned as well for career growth | AG54: NA | AH54: University of Pittsburgh | AI54: Pittsburgh | AJ54: Non-target | AK54: 3.6 | AL54: Industrial Engineering | AM54: 2026 | AN54: MLT, INROADS | AO54: https://drive.google.com/open?id=1ostY7whu4h_FDopRCeEo9Y5V0V6tRm3M | AP54: Private Equity, Management Consulting, Venture Capital, Business & Entreprenuership, Technology | AQ54: Moelis & Company, Bain Capital | AR54: PE, VC, Climatech INvesting, Infrastructure Investing | AT54: Analyst
A55: 45754.514 | B55: Darius | C55: Ephrem | D55: BLK - 24203 | E55: darius.ephrem@durham.ac.uk | F55: Darius4ephrem@gmail.com | G55: Personal email | H55: =IF(G55="College/Secondary email:",E55,F55) -> Darius4ephrem@gmail.com | I55: London, England | J55: Analyst | K55: +447899136264 | L55: Male | M55: Fall 2024 | N55: 2026 | O55: EMEA | P55: N/A | Q55: No | R55: Saunders Street Capital | S55: New York, New York | T55: Private Equity/Search Fund | U55: 1 | V55: N/A | W55: J.P. Morgan | X55: London, England | Y55: Investment Banking | Z55: 1 | AA55: N/A | AB55: N/A | AC55: N/A | AD55: N/A | AE55: N/A | AF55: N/A | AG55: N/A | AH55: Durham University | AI55: Durham, England | AJ55: Semi-Target | AK55: First (1:1) | AL55: Finance | AM55: 2026 | AN55: SEO (EMEA), Rare Recruitment | AO55: https://drive.google.com/open?id=1oXAhLs9fdc5J3dkaxehnQT1cVvbt4I8r | AP55: Investment Banking, Private Equity, Asset Management, Management Consulting, Venture Capital, Hedge Funds, Business & Entreprenuership, Real Estate | AT55: Analyst
A56: 45754.515 | B56: Abi | C56: Debebe | D56: BLK - 24226 | E56: abidebe@wharton.upenn.edu | F56: abidebebe1@gmail.com | G56: College/Secondary email: | H56: =IF(G56="College/Secondary email:",E56,F56) -> abidebe@wharton.upenn.edu | I56: Atlanta, GA | J56: Trainee Analyst | K56: 14709891067 | L56: Female | M56: Fall 2024 | N56: 2027 | O56: North America | P56: Philadelphia (U.S.) | Q56: Yes | R56: Citadel and Citadel Securities | S56: New York, NY | T56: Hedge Fund | U56: 1 | V56: n/a | W56: Penn Office of Investments | X56: Philadelphia, PA | Y56: Investment Management | Z56: 1 | AA56: n/a | AB56: UBS | AC56: New York, NY | AD56: Investment Banking | AE56: 1 | AF56: n/a | AG56: n/a | AH56: University of Pennsylvania | AI56: Philadelphia | AJ56: Target | AK56: 3.64 | AL56: Economics and International Studies | AM56: 2027 | AN56: SEO, Girls Who Invest | AO56: https://drive.google.com/open?id=1UiqYu23GSUMoalNw4dRUyLtsp6yJP_bO | AP56: Investment Banking, Private Equity, Hedge Funds, Business & Entreprenuership, Legal, Risk & Compliance | AQ56: UBS | AT56: Community Member
A57: 45754.522 | B57: Samuel | C57: Yacob | D57: BLK - 23442 | E57: syacob@u.rochester.edu | F57: samuelyacobb@gmail.com | G57: Personal email | H57: =IF(G57="College/Secondary email:",E57,F57) -> samuelyacobb@gmail.com | I57: Rochester | J57: Community Member | K57: +15853519433 | L57: Male | M57: Spring 2024 | N57: 2027 | O57: North America | P57: N/A | Q57: Yes | R57: N/A | S57: N/A | T57: N/A | U57: N/A | V57: N/A | W57: Ernst & Young | X57: New York City, NY | Y57: Risk Consulting | Z57: 2 | AA57: Compensation and benefits | AB57: N/A | AC57: N/A | AD57: N/A | AE57: N/A | AF57: N/A | AG57: N/A | AH57: University of Rochester | AI57: Rochester | AJ57: Non-target | AK57: 3.01 | AL57: Data Science, Economics | AM57: 2027 | AN57: SEO | AO57: https://drive.google.com/open?id=1907PrWkSCFAdLs64Q8qJkcsdRR0gUgpc | AP57: Quantitative Finance (eg. Quant Trading), Technology, Legal, Risk & Compliance | AQ57: Jane Street, Sixth Street, Vanguard, American Securities, PGIM | AR57: Technology Risk, Risk Management, Technology Consulting | AT57: Community Member
A58: 45754.533 | B58: Quentin | C58: Wei-Henrys | D58: BLK - 24163 | E58: q.w.wei-henrys@wustl.edu | F58: quentinweihenrys@gmail.com | G58: Personal email | H58: =IF(G58="College/Secondary email:",E58,F58) -> quentinweihenrys@gmail.com | I58: Oak Park, IL | J58: Analyst | K58: +17086163706 | L58: Male | M58: Fall 2024 | N58: 2027 | O58: North America | P58: N/A | Q58: Yes | R58: Thirty-5 Capital | S58: Chicago, IL | T58: Private Equity & Venture Capital | U58: 1 | V58: N/A | W58: N/A | X58: N/A | Y58: N/A | Z58: N/A | AA58: N/A | AB58: Jefferies (Incoming for 2026) | AC58: New York, NY | AD58: Investment Banking | AE58: 2 | AF58: I received my offer at Jefferies before the other one. | AG58: N/A | AH58: Washington University in St. Louis | AI58: St. Louis, MO | AJ58: Semi-Target | AK58: 3.79 | AL58: Finance | AM58: 2027 | AN58: SEO | AO58: https://drive.google.com/open?id=1PYv67EjFLXyN-0UN0cV6Wm2oP2vpWUah | AP58: Investment Banking, Private Equity, Venture Capital | AQ58: N/A | AT58: Community Member
A59: 45754.548 | B59: Soukeyna | C59: Dale | D59: BLK-24058 | E59: soukeyna.dale@dillard.edu | F59: soukeynadale@gmail.com | G59: Personal email | H59: =IF(G59="College/Secondary email:",E59,F59) -> soukeynadale@gmail.com | I59: Milwaukee, WI | J59: Community Member | K59: 4148881824 | L59: Female | M59: Fall 2024 | N59: 2025 | O59: North America | P59: N/A | Q59: Yes | R59: N/A | S59: - | T59: - | U59: - | V59: - | W59: - | X59: - | Y59: - | Z59: - | AA59: - | AB59: - | AC59: - | AD59: - | AE59: - | AF59: - | AG59: Associated Bank | AH59: Dillard University | AI59: New Orleans | AJ59: HBCU (Historically Black Colleges and Universities) | AK59: 4 | AL59: Business Administration | AM59: 2025 | AN59: Girls Who Invest | AO59: https://drive.google.com/open?id=1RSYxZVZBdRnWXOVh6hbHYeRyKvVWV4ao | AP59: consulting | AQ59: - | AT59: Alumni (only select if you are graduated/graduating this year)
A60: 45754.552 | B60: Yafet | C60: Yacob | D60: BLK - 23134 | E60: yny3@scarletmail.rutgers.edu | F60: yacob4.yafet@gmail.com | G60: Personal email | H60: =IF(G60="College/Secondary email:",E60,F60) -> yacob4.yafet@gmail.com | I60: Dayton | J60: Community Member | K60: 17329049158 | L60: Male | M60: Spring 2023 | N60: 2026 | O60: North America | P60: New York City (U.S.) | Q60: Yes | R60: PWC | S60: virtual | T60: consulting | U60: 1 | V60: N/A | W60: Rutgers Endowment | X60: Piscataway, NJ | Y60: Asset Management | Z60: 1 | AA60: N/A | AB60: Standard Charter | AC60: New York, NY | AD60: Corporate Banking | AE60: 1 | AF60: N/A | AG60: N/A | AH60: Rutgers University | AI60: Piscataway | AJ60: Non-target | AK60: 3.5 | AL60: Finance | AM60: 2026 | AN60: SEO | AO60: https://drive.google.com/open?id=171YnWCbjPsxgm3gBbXUIOruybCPoJiQO | AP60: Corporate Banking | AQ60: N/A | AT60: Community Member
A61: 45754.555 | B61: Judah | C61: Fakile | D61: BLK - 24100 | E61: jmf200@cam.ac.uk | F61: judahm.fakile@gmail.com | G61: Personal email | H61: =IF(G61="College/Secondary email:",E61,F61) -> judahm.fakile@gmail.com | I61: Cambridge | J61: Analyst | K61: +447914669588 | L61: Male | M61: Fall 2024 | N61: 2027 | O61: EMEA | P61: London (EMEA) | Q61: With authorisations | R61: N/A | S61: N/A | T61: N/A | U61: N/A | V61: N/A | W61: N/A | X61: N/A | Y61: N/A | Z61: N/A | AA61: N/A | AB61: N/A | AC61: N/A | AD61: N/A | AE61: N/A | AF61: N/A | AG61: N/A | AH61: University of Cambridge | AI61: Cambridge | AJ61: Target | AK61: 4 | AL61: Economics | AM61: 2027 | AN61: SEO (EMEA), UpReach, Rare Recruitment | AO61: https://drive.google.com/open?id=1QspDR84xl0uvIDXDb0DxD5j4DxX9arcQ | AP61: Investment Banking, Private Equity, Asset Management, Quantitative Finance (eg. Quant Trading), Management Consulting, Venture Capital, Hedge Funds | AQ61: Advent, Alpine, DE Shaw, Arsenal Capital, Bain Capital, Jane Street, Roark, | AR61: Interested in finding a first year summer in the space of PE, Growth Equity or VC before securing a second year summer to create an easier exit opportunity. | AT61: Education Pathways (IB, AWM, or PE)
A62: 45754.561 | B62: Leonard | C62: Ukpaka | D62: 23335 | E62: llylu1@nottingham.ac.uk | F62: leonardorji09@gmail.com | G62: College/Secondary email: | H62: =IF(G62="College/Secondary email:",E62,F62) -> llylu1@nottingham.ac.uk | I62: London | J62: Executive board | K62: +447404094436 | L62: Male | M62: Spring 2024 | N62: 2026 | O62: EMEA | P62: London (EMEA) | Q62: No | R62: Sixth Street | S62: London | T62: Private Equity | U62: 3 | V62: Preferred Sixth Street | W62: Citi | X62: London | Y62: Investment Banking | Z62: 3 | AA62: preferred M/A | AB62: N/A | AC62: N/A | AD62: N/A | AE62: N/A | AF62: N/A | AG62: N/A | AH62: University of Nottingham | AI62: Nottingham | AJ62: Target | AK62: 3.8 | AL62: Law | AM62: 2026 | AN62: SEO, UpReach, Rare Recruitment | AO62: https://drive.google.com/open?id=1Eb0_8Og7U6pxyXhbYyLyxQmDoAoL7s33 | AP62: Investment Banking, Private Equity, Hedge Funds | AQ62: Point 72, Warburg Pincus, Morgan Stanley | AT62: Community Member
A63: 45754.568 | B63: Aadil | C63: Mohamed | D63: 24183 | E63: amohamed26@cmc.edu | F63: aadilmohamed04@gmail.com | G63: Personal email | H63: =IF(G63="College/Secondary email:",E63,F63) -> aadilmohamed04@gmail.com | I63: Portland, OR | J63: Community Member | K63: +19712462968 | L63: Male | M63: Fall 2024 | N63: 2026 | O63: North America | P63: Los Angeles (U.S.) | Q63: Yes | R63: Marquam Capital | S63: Portland, OR | T63: Asset Management | U63: N/A | V63: N/A | W63: Deloitte | X63: Los Angeles, CA | Y63: Audit and Assurance | Z63: N/A | AA63: N/A | AB63: Deloitte | AC63: Portland, OR | AD63: Audit and Assurance | AE63: N/A | AF63: N/A | AG63: N/A | AH63: Claremont McKenna College | AI63: Los Angeles, California | AJ63: Liberal Arts College, Non-Target School | AK63: 3.6 | AL63: Economics-Accounting | AM63: 2026 | AN63: MLT, SEO | AO63: https://drive.google.com/open?id=1DxAE87-NCMON7jicVIhnJFb8BGVw0xy3 | AP63: Investment Banking, Management Consulting, Venture Capital | AQ63: TD Securities, KKR, Goldman Sachs, JP Morgan | AT63: Analyst
A64: 45754.573 | B64: Eugene | C64: Burse | D64: BLK-23045 | E64: burseeh@mail.uc.edu | F64: eugeneburse32@gmail.com | G64: College/Secondary email: | H64: =IF(G64="College/Secondary email:",E64,F64) -> burseeh@mail.uc.edu | I64: Cincinnati | J64: Community Member | K64: +5132378095 | L64: Male | M64: Spring 2023 | N64: 2026 | O64: North America | P64: N/A | Q64: Yes | R64: Truepoint Wealth Counsel | S64: Cincinnati, OH | T64: Wealth Management | U64: 2 | V64: it was a startup company with a subpar culture | W64: Principal Asset Management | X64: Manhattan, NY | Y64: Equity Research | Z64: 1 | AA64: n/a | AB64: Piper Sandler | AC64: Chicago, IL | AD64: investment banking | AE64: 1 | AF64: N/A | AG64: N/A | AH64: University of Cincinnati | AI64: Cincinnati | AJ64: Non-target | AK64: 3.43 | AL64: Finance and Economics | AM64: 2026 | AN64: MLT, SEO | AO64: https://drive.google.com/open?id=1_ZoQaAXrgfAsHGv8CWJg7KkuiFRe8U0Y | AP64: Investment Banking, Private Equity, Asset Management, Business & Entreprenuership | AQ64: Alpine, Acadian, Taconic, Advent International | AR64: Consumer ib and pe | AT64: Community Member
A65: 45754.575 | B65: Binham | C65: Seyoum | D65: BLK - 24017 | E65: binham.seyoum@student.manchester.ac.uk | F65: binham90210@gmail.com | G65: Personal email | H65: =IF(G65="College/Secondary email:",E65,F65) -> binham90210@gmail.com | I65: Manchester | J65: Analyst | K65: +447591977610 | L65: Male | M65: Fall 2023 | N65: 2025 | O65: EMEA | P65: London (EMEA) | Q65: Yes | R65: Bank of America | S65: Chester, England | T65: Investment Bank | U65: N/A | V65: N/A | W65: Freshfields | X65: London, England | Y65: Law firm | Z65: N/A | AA65: N/A | AB65: N/A | AC65: N/A | AD65: N/A | AE65: N/A | AF65: N/A | AG65: N/A | AH65: University of Manchester | AI65: Manchester | AJ65: Non-target | AK65: 2.1 | AL65: Biomedical Science | AM65: 2025 | AN65: SEO, SEO (EMEA), UpReach | AO65: https://drive.google.com/open?id=1Y9dG3Y-IrrKpHAM-2bpJnORLcgFGVHkp | AP65: Investment Banking, Sales and Trading, Asset Management, Management Consulting, Hedge Funds, Business & Entreprenuership, Real Estate, Legal, Risk & Compliance, HR | AQ65: PGIM | AT65: Analyst
A66: 45754.585 | B66: Alexander | C66: Adegbesan | D66: BLK - 24083 | E66: alexadegbesan@tamu.edu | F66: a.adegbesan06@gmail.com | G66: Personal email | H66: =IF(G66="College/Secondary email:",E66,F66) -> a.adegbesan06@gmail.com | I66: Houston, TX | J66: Analyst | K66: +17139224155 | L66: Male | M66: Fall 2024 | N66: 2028 | O66: North America | P66: N/A | Q66: Yes | R66: N/A | S66: N/A | T66: N/A | U66: N/A | V66: N/A | W66: N/A | X66: N/A | Y66: N/A | Z66: N/A | AA66: N/A | AB66: N/A | AC66: N/A | AD66: N/A | AE66: N/A | AF66: N/A | AG66: N/A | AH66: Texas A&M University | AI66: College Station | AJ66: Non-target | AK66: 3.8 | AL66: Finance | AM66: 2028 | AN66: SEO, HeadStart | AO66: https://drive.google.com/open?id=1OP3Ppn3nfmv-eQpKEQSHjX_BO555krvv | AP66: Investment Banking, Private Equity | AQ66: Evercore, Lazard, Moelis & Company | AR66: I would love to work at an Elite Boutique bank due to leaner deal teams | AT66: Analyst
A67: 45754.599 | B67: Denzel | C67: Louis | D67: BLK-24197 | E67: louis523@student.fus.edu | F67: denzlouis04@icloud.com | G67: Personal email | H67: =IF(G67="College/Secondary email:",E67,F67) -> denzlouis04@icloud.com | I67: Miami, FL | J67: Analyst | K67: +19548160641 | L67: Male | M67: Fall 2024 | N67: 2026 | O67: EMEA | P67: N/A | Q67: Yes | R67: N/A | S67: N/A | T67: N/A | U67: N/A | V67: N/A | W67: Green Children's House Montessori School | X67: Pompano Beach, FL | Y67: Business development | Z67: 1 | AA67: Northwestern mutual, didnt believe it to be reputable and took the SIE instead. | AB67: Decision is released by end of week | AC67: NY,NY | AD67: IB | AE67: N/A | AF67: N/A | AG67: N/A | AH67: Franklin University of Switzerland | AI67: Lugano, Switzerland | AJ67: Liberal Arts College, Non-Target School | AK67: 3.3/4 | AL67: Finance | AM67: 2026 | AN67: Project Destined | AO67: https://drive.google.com/open?id=14zMaY65Je9nYpaEu_P0HV0_XEL0eQYcq | AP67: Investment Banking, Private Equity, Asset Management, Management Consulting, Venture Capital, Hedge Funds, Business & Entreprenuership | AQ67: Black owned investment banks | AT67: Analyst
A68: 45754.606 | B68: Norah | C68: Ostin | D68: 22246 | E68: nostin@college.harvard.edu | F68: nostin03@gmail.com | G68: Personal email | H68: =IF(G68="College/Secondary email:",E68,F68) -> nostin03@gmail.com | I68: Pittsburgh | J68: Community Member | K68: +14125520191 | L68: Female | M68: Fall 2022 | N68: 2025 | O68: North America | P68: Boston (U.S.) | Q68: Yes | R68: N/A | S68: N/A | T68: N/A | U68: n/a | V68: n/a | W68: Bloomberg | X68: NYC, NY | Y68: markting | Z68: 2 | AA68: Chase Bank it was shorter term 6 weeks | AB68: Capital One | AC68: McLean, VA | AD68: Business Analyst | AE68: 1 | AF68: N/A | AG68: McMaster Carr | AH68: Harvard University | AI68: Cambridge MA | AJ68: Target | AK68: 3.7 | AL68: Sociology | AM68: 2025 | AN68: SEO | AO68: https://drive.google.com/open?id=1K_q8RGJu0SY-9iEB_OozPIbfU7lYV8fM | AP68: Management Consulting, Business & Entreprenuership, Technology | AQ68: N/A | AT68: Alumni (only select if you are graduated/graduating this year)
A69: 45754.609 | B69: Vassou | C69: Gikundiro | D69: BLK-24260 | E69: Cornell University | F69: gikundirov@gmail.com | G69: College/Secondary email: | H69: =IF(G69="College/Secondary email:",E69,F69) -> Cornell University | I69: Kigali-Rwanda | J69: Community Member | K69: +16073277897 | L69: Female | M69: Fall 2024 | N69: 2027 | O69: North America | P69: New York City (U.S.) | Q69: Yes | R69: N/A | S69: N/A | T69: N/A | U69: N/A | V69: N/A | W69: N/A | X69: N/A | Y69: N/A | Z69: N/A | AA69: N/A | AB69: N/A | AC69: N/A | AD69: N/A | AE69: N/A | AF69: N/A | AG69: N/A | AH69: Cornell University | AI69: Ithaca | AJ69: Target | AK69: 4 | AL69: Economics | AM69: 2027 | AN69: URMC | AO69: https://drive.google.com/open?id=1bj-5YpjBeiyvODZXEJgNHcilro02UiH1 | AP69: Investment Banking, Sales and Trading, Private Equity, Management Consulting, Business & Entreprenuership | AQ69: Ey, BainCapital, Jane street, Morgan Stanley | AT69: Community Member
A70: 45754.627 | B70: Muhammad | C70: Jaiteh | D70: BLK - 23012 | E70: Majaite@emory.edu | F70: Jaitehmuhammad@gmail.com | G70: College/Secondary email: | H70: =IF(G70="College/Secondary email:",E70,F70) -> Majaite@emory.edu | I70: Atlanta, Ga | J70: Community Member | K70: +14047238803 | L70: Male | M70: Spring 2023 | N70: 2025 | O70: North America | P70: Atlanta (U.S.) | Q70: Yes | R70: N/A | S70: N/A | T70: N/A | U70: N/A | V70: N/A | W70: The Hatchery, Emory University’s Center for entrepreneurship | X70: Atlanta, Ga | Y70: Entrepreneurship | Z70: N/A | AA70: N/A | AB70: Accenture | AC70: Atlanta, Ga | AD70: Consulting | AE70: 2 | AF70: I got an offer from Dell Technologies for Corporate Finance but choose Accenture because I wanted to do consulting | AG70: Accenture | AH70: Emory University, Goizueta Business School | AI70: Atlanta | AJ70: Non-target | AK70: 3.64 | AL70: Finance | AM70: 2025 | AN70: SEO | AO70: https://drive.google.com/open?id=1N7UUPX487lgyQAjsozwn4rZa6EU5_XT1 | AP70: Private Equity, Management Consulting, Venture Capital, Business & Entreprenuership, Technology | AQ70: Google Ventures | AS70: Roark Investment Fellowship | AT70: Community Member
A71: 45754.632 | B71: Jeremiah | C71: Griffith | D71: BLK - 24175 | E71: jg75@illinois.edu | F71: jgriffith161@gmail.com | G71: Personal email | H71: =IF(G71="College/Secondary email:",E71,F71) -> jgriffith161@gmail.com | I71: Chicago | J71: Community Member | K71: +13128829116 | L71: Male | M71: Fall 2024 | N71: 2027 | O71: North America | P71: Philadelphia (U.S.) | Q71: Yes | R71: Bridgespan Group | S71: Boston, Ma | T71: Nonprofit Consulting | U71: 1 | V71: n/a | W71: Loop Capital | X71: Chicago, IL | Y71: Investment Banking | Z71: 2 | AA71: Loop offered equity research position and the other offered investment banking position. I prefer equity research. | AB71: n/a | AC71: n/a | AD71: n/a | AE71: n/a | AF71: n/a | AG71: n/a | AH71: University of Illinois at Urbana-Champaign | AI71: Champaign | AJ71: Non-target | AK71: 3.9 | AL71: Economics/Psychology | AM71: 2027 | AN71: SEO | AO71: https://drive.google.com/open?id=1rXOxxcaP9LhAHZMoe5AejpK-vFv6sT2u | AP71: Asset Management, Venture Capital, Hedge Funds, Investment Research | AQ71: Wolfe Research, Alliance Bernstein | AR71: I am more interested in investment research on the sell-side or buy-side. Asset management roles as well. | AT71: Community Member
A72: 45754.644 | B72: Chidubem | C72: Obinani | D72: BLK - 24060 | E72: leyco6@nottingham.ac.uk | F72: chidubemobinani@gmail.com | G72: Personal email | H72: =IF(G72="College/Secondary email:",E72,F72) -> chidubemobinani@gmail.com | I72: Sheffield | J72: Community Member | K72: +447398109564 | L72: Male | M72: Fall 2024 | N72: 2027 | O72: EMEA | P72: N/A | Q72: No | R72: Forvis Mazars | S72: Leeds | T72: Audit, tax, advisory, consulting | U72: 2 | V72: N/A | W72: N/A | X72: N/A | Y72: N/A | Z72: N/A | AA72: N/A | AB72: N/A | AC72: N/A | AD72: N/A | AE72: N/A | AF72: N/A | AG72: N/A | AH72: University of Nottingham | AI72: Nottingham | AJ72: Semi-target | AK72: First | AL72: Economics | AM72: 2027 | AN72: SEO, Rare Recruitment | AO72: https://drive.google.com/open?id=16AFsvqUUOubi6VYEk0EJGh74XvC_AfXi | AP72: Investment Banking, Asset Management, Equity Research | AQ72: N/A | AR72: Mainly equity research and asset management but also investment banking. | AS72: no | AT72: Analyst
A73: 45754.655 | B73: Oyindamola | C73: Balogun | D73: BLK-24037 | E73: obalogu1@gsumail.gram.edu | F73: dbalogun2023@gmail.com | G73: Personal email | H73: =IF(G73="College/Secondary email:",E73,F73) -> dbalogun2023@gmail.com | I73: Grambling, LA | J73: Community Member | K73: +17046268418 | L73: Male | M73: Fall 2024 | N73: 2027 | O73: North America | P73: N/A | Q73: Yes | R73: N/A | S73: N/A | T73: N/A | U73: N/A | V73: N/A | W73: N/A | X73: N/A | Y73: N/A | Z73: N/A | AA73: N/A | AB73: N/A | AC73: N/A | AD73: N/A | AE73: N/A | AF73: N/A | AG73: N/A | AH73: Grambling State University | AI73: Grambling | AJ73: HBCU (Historically Black Colleges and Universities) | AK73: 3.82 | AL73: Computer Science and Mathematics | AM73: 2027 | AN73: MLT | AO73: https://drive.google.com/open?id=1S-MXYw7wfiEvfF8PdhiEZ7FWGvWcnGf7 | AP73: Sales and Trading, Quantitative Finance (eg. Quant Trading), Technology | AQ73: DE Shaw, Goldman Sachs, Jane Street, Morgan Stanley. | AT73: Community Member
A74: 45754.687 | B74: Uwa | C74: Osagie | D74: BLK - 24164 | E74: uo1g24@soton.ac.uk | F74: uwa.osagie@aol.co.uk | G74: Personal email | H74: =IF(G74="College/Secondary email:",E74,F74) -> uwa.osagie@aol.co.uk | I74: Birmingham | J74: Analyst | K74: +447449770706 | L74: Male | M74: Fall 2024 | N74: 2027 | O74: EMEA | P74: London (EMEA) | Q74: Yes | R74: N/A | S74: N/A | T74: N/A | U74: N/A | V74: N/A | W74: N/A | X74: N/A | Y74: N/A | Z74: N/A | AA74: N/A | AB74: N/A | AC74: N/A | AD74: N/A | AE74: N/A | AF74: N/A | AG74: N/A | AH74: University of Southampton | AI74: Southampton | AJ74: Russel group | AK74: 1st | AL74: Electrical & Electronic Engineering | AM74: 2027 | AN74: SEO, Rare Recruitment | AO74: https://drive.google.com/open?id=1XQSt06WZNnrNNseHRWyHwLjSJuHQQumy | AP74: Investment Banking, Sales and Trading, Private Equity, Asset Management, Quantitative Finance (eg. Quant Trading), Hedge Funds, Technology | AQ74: Jane street / JP Morgan / RBC | AR74: I’d like to go into quant trading because of my maths background but if any asset management or private equities roles are available I’d love to gain experience there aswell. | AS74: N/A | AT74: Analyst
A75: 45754.692 | B75: Temilade | C75: Onile | D75: BLK-23433 | E75: onile@bc.edu | F75: temilade.onile@gmail.com | G75: Personal email | H75: =IF(G75="College/Secondary email:",E75,F75) -> temilade.onile@gmail.com | I75: Norwood, MA | J75: Analyst | K75: +13392056711 | L75: Female | M75: Spring 2024 | N75: 2026 | O75: North America | P75: Boston (U.S.) | Q75: Yes | R75: MA State Treasury | S75: Boston, MA | T75: Audit | U75: NA | V75: NA | W75: NA | X75: NA | Y75: NA | Z75: NA | AA75: NA | AB75: Brown Advisory | AC75: Boston, MA | AD75: Wealth management | AE75: NA | AF75: NA | AG75: NA | AH75: Boston College | AI75: Chestnut Hill, MA | AJ75: Target | AK75: 3.431 | AL75: Finance and International Studies | AM75: 2026 | AN75: MLT | AO75: https://drive.google.com/open?id=1ELvI0E21WPkOrQ8R47PG6kHSRZ8xcRwJ | AP75: Asset Management, Wealth management | AQ75: Alliance Bernstein | AT75: Analyst
A76: 45754.7 | B76: Joshua | C76: Johnson | D76: BLK - 2334 | E76: jaj4775@utexas.edu | F76: joshua4222@gmail.com | G76: College/Secondary email: | H76: =IF(G76="College/Secondary email:",E76,F76) -> jaj4775@utexas.edu | I76: Houston | J76: Analyst | K76: 8325896723 | L76: Male | M76: Fall 2023 | N76: 2026 | O76: North America | P76: N/A | Q76: Yes | R76: Forte Capital | S76: New York, NY | T76: PE Fundraising | U76: N/A | V76: N/A | W76: JPM | X76: NY, NY | Y76: IB | Z76: 1 | AA76: Took another offer | AB76: PWP | AC76: NY | AD76: IB | AE76: TBD | AF76: TBD | AG76: Still in process | AH76: UT Austin | AI76: Austin | AJ76: Semi-Target | AK76: 3.6 | AL76: Finance | AM76: 2026 | AN76: MLT, SEO, Project Destined | AO76: https://drive.google.com/open?id=1JpyzxJTcCmotsZr6Vvmg4jAVShu_WMZe | AP76: Investment Banking, Private Equity, Hedge Funds | AQ76: Jane Street, Centerview, KKR, Blackstone, Raine Group, Vista Equity | AR76: I am interested in lateraling into Media PE or a L/S HF after my banking tenure. I specifically am interested in the media and entertainment space and can see my self working in the industry for the rest of my life. I have been fortunate to meet a bunch of people from some of the top firms such as WME and CAA, and being able to work as an advisor or investor with these companies or companies a like would be a dream come true. | AS76: BLK Conference December 2023, conn | AT76: Analyst
A77: 45754.709 | B77: Teniola | C77: Oyin jolayemi | D77: 24071 | E77: Texas tech | F77: tenijayy@gmail.com | G77: Personal email | H77: =IF(G77="College/Secondary email:",E77,F77) -> tenijayy@gmail.com | I77: Lagos,Nigeria | J77: Community Member | K77: 4698805653 | L77: Male | M77: Spring 2023 | N77: 2027 | O77: North America | P77: N/A | Q77: Yes | R77: Arclight capital Partners | S77: Boston, MA | T77: Private equity | U77: 1 | V77: N/A | W77: Jp Morgan | X77: New york, NY | Y77: Investment Banking | Z77: 1 | AA77: 2 - Brand name | AB77: N/A | AC77: N/A | AD77: N/A | AE77: N/A | AF77: N/A | AG77: N/A | AH77: Texas Tech | AI77: Lubbock, TX | AJ77: Non-target | AK77: 3.83 | AL77: Economics | AM77: 2027 | AN77: MLT, SEO | AO77: https://drive.google.com/open?id=1LQsi4gQQ00J9es58QQwtvotUBMAMGNpH | AP77: Investment Banking, Private Equity, Asset Management | AQ77: Fidelity(Private credit), DE Shaw, Lazard, LLR partners | AS77: Conference | AT77: Analyst
A78: 45754.71 | B78: Toni | C78: Akinola | D78: BLK-24168 | E78: leyoa11@nottingham.ac.uk | F78: akinolaoluwatoni@gmail.com | G78: Personal email | H78: =IF(G78="College/Secondary email:",E78,F78) -> akinolaoluwatoni@gmail.com | I78: Toronto | J78: Analyst | K78: +447498314886 | L78: Female | M78: Fall 2024 | N78: 2025 | O78: EMEA | P78: London (EMEA) | Q78: Yes | R78: N/A | S78: N/A | T78: N/A | U78: N/A | V78: N/A | W78: Shell | X78: London, UK | Y78: Oil and gas | Z78: 1 | AA78: N/A | AB78: N/A | AC78: N/A | AD78: N/A | AE78: N/A | AF78: N/A | AG78: N/A | AH78: University of Nottingham | AI78: Nottingham | AJ78: Non-target | AK78: N/A | AL78: Economics | AM78: 2025 | AN78: Girls Who Invest | AO78: https://drive.google.com/open?id=1-5aaeyAaahwIVU9x9hqjf3PUcDFR6eIA | AP78: Sales and Trading, Private Equity, Asset Management, Quantitative Finance (eg. Quant Trading), Management Consulting, Hedge Funds, Technology | AQ78: Morgan Stanley, TD Securities, Goldman Sachs, JP Morgan, Blackrock | AT78: Alumni (only select if you are graduated/graduating this year)
A79: 45754.749 | B79: Langston | C79: Minor | D79: N/A | E79: minorl@vcu.edu | F79: airlegend010804@gmail.com | G79: College/Secondary email: | H79: =IF(G79="College/Secondary email:",E79,F79) -> minorl@vcu.edu | I79: Richmond | J79: Trainee Analyst | K79: +18048320725 | L79: Male | M79: Fall 2024 | N79: 2026 | O79: North America | P79: N/A | Q79: Yes | R79: Lincoln Investment | S79: Richmond, VA | T79: Financial Services | U79: 2 | V79: N/A | W79: LISC | X79: Richmond, VA | Y79: Financial Services | Z79: 2 | AA79: N/A | AB79: N/A | AC79: N/A | AD79: N/A | AE79: N/A | AF79: N/A | AG79: N/A | AH79: Virginia Commonwealth University | AI79: Richmond, VA | AJ79: Non-target | AK79: 3.2 | AL79: Finance | AM79: 2026 | AN79: MLT, INROADS | AO79: https://drive.google.com/open?id=1goeFpZJZRxxANhEFeZe1m9VyvPOMZSq3 | AP79: Investment Banking, Sales and Trading, Private Equity, Asset Management, Quantitative Finance (eg. Quant Trading), Management Consulting, Venture Capital, Hedge Funds, Business & Entreprenuership | AQ79: all | AT79: Analyst
A80: 45754.763 | B80: Cristopher | C80: Ramirez | D80: BLK - 24157 | E80: Crisramirez@college.harvard.edu | F80: crismrr30@gmail.com | G80: College/Secondary email: | H80: =IF(G80="College/Secondary email:",E80,F80) -> Crisramirez@college.harvard.edu | I80: Queens, NY | J80: Analyst | K80: +19294349059 | L80: Male | M80: Fall 2024 | N80: 2028 | O80: North America | P80: Boston (U.S.) | Q80: Yes | R80: N/A | S80: N/A | T80: N/A | U80: N/A | V80: N/A | W80: N/A | X80: N/A | Y80: N/A | Z80: N/A | AA80: N/A | AB80: N/A | AC80: N/A | AD80: N/A | AE80: N/A | AF80: N/A | AG80: N/A | AH80: Harvard College | AI80: Cambridge | AJ80: Target | AK80: 3.9 | AL80: Economics & Philosophy | AM80: 2028 | AN80: SEO | AO80: https://drive.google.com/open?id=1hFr5R1o8AabW93BHoTV8k0oPqyEQ7Z8w | AP80: Investment Banking, Private Equity, Hedge Funds | AQ80: Alpine, Evercore, Goldman Sachs, J.P. Morgan, KKR, Lazard, Morgan Stanley, Roark, 6th Street Partners, Warburg Pincus | AT80: Analyst
A81: 45754.807 | B81: Immanuel | C81: Dange | D81: BLK - 24167 | E81: immanuel.dange@torontomu.ca | F81: immanueldange@gmail.com | G81: Personal email | H81: =IF(G81="College/Secondary email:",E81,F81) -> immanueldange@gmail.com | I81: Toronto | J81: Analyst | K81: +16475616054 | L81: Male | M81: Spring 2024 | N81: 2028 | O81: North America | P81: Toronto (Canada) | Q81: No | R81: N/A | S81: N/A | T81: N/A | U81: N/A | V81: N/A | W81: N/A | X81: N/A | Y81: N/A | Z81: N/A | AA81: N/A | AB81: N/A | AC81: N/A | AD81: N/A | AE81: N/A | AF81: N/A | AG81: N/A | AH81: Toronto Metropolitan University | AI81: Toronto | AJ81: Non-target | AK81: 3.5 | AL81: Business Administration | AM81: 2028 | AN81: N/A | AO81: https://drive.google.com/open?id=1wPSbBuTbI6vDb--DUHYhc1qRDnlYKyTk | AP81: Investment Banking, Private Equity, Quantitative Finance (eg. Quant Trading), Business & Entreprenuership, Technology, Real Estate, HR | AQ81: JPMorgan Chase, TD, RBC, Deloitte. | AS81: N/A | AT81: Analyst
A82: 45754.886 | B82: Fered | C82: Yousuf | D82: BLK - 23222 | E82: fyousuf2@illinois.edu | F82: feredyousuf14@icloud.com | G82: College/Secondary email: | H82: =IF(G82="College/Secondary email:",E82,F82) -> fyousuf2@illinois.edu | I82: Matteson, IL | J82: Roark fellow | K82: +17738181121 | L82: Male | M82: Fall 2023 | N82: 2027 | O82: North America | P82: N/A | Q82: Yes | R82: Charles Schwab | S82: Chicago, IL | T82: Asset Management | U82: 1 | V82: N/A | W82: Wells Fargo | X82: New York, NY | Y82: Investment Banking | Z82: 2 | AA82: N/A | AB82: N/A | AC82: N/A | AD82: N/A | AE82: N/A | AF82: N/A | AG82: N/A | AH82: University of Illinois at Urbana-Champaign | AI82: Champaign | AJ82: Public Flagship University | AK82: 4 | AL82: Finance & Accounting | AM82: 2027 | AN82: MLT, SEO | AO82: https://drive.google.com/open?id=1ZOhirEyRC1NeZyo1OVbTyaJG_XGhjrhY | AP82: Investment Banking, Private Equity, Venture Capital, Hedge Funds | AQ82: J.P Morgan | AT82: Community Member
A83: 45754.919 | B83: Arashi | C83: Hunter | D83: 24096 | E83: N/A, not currently in university | F83: Keithahunter5@gmail.com | G83: Personal email | H83: =IF(G83="College/Secondary email:",E83,F83) -> Keithahunter5@gmail.com | I83: Seattle | J83: Analyst | K83: +12069602351 | L83: Male | M83: Fall 2024 | N83: 2029 | O83: North America | P83: Boston (U.S.) | Q83: Yes | R83: N?A | S83: N/A | T83: N/A | U83: N/A | V83: N/A | W83: N/A | X83: N/A | Y83: N/A | Z83: N/A | AA83: N/A | AB83: N/A | AC83: N/A | AD83: N/A | AE83: N/A | AF83: N/A | AG83: N/A | AH83: Harvard College | AI83: Cambridge | AJ83: Target | AK83: N/A | AL83: Economics | AM83: 2029 | AN83: N/A | AO83: https://drive.google.com/open?id=1mXNz0Gzx5YKWECxgQBX2JqKJZtpVJ9Ed | AP83: Investment Banking, Private Equity, Asset Management, Hedge Funds | AQ83: UBS, Wolfe Research, KKR, Goldman Sachs, JP Morgan, Warburg Pincus | AR83: I am interested in pursuing a career either within equity research, asset management, or investment banking. I am interested in equity research due to it being such a detail oriented career option. Asset management also draws me due to also requiring strategy for investments while also having a social aspect as it requires connection with clients. Finally, I am attracted to investment banking as it requires team collaboration to advise on financial transactions. | AS83: The calls with KKR and Warburg Pincus have been especially insightful. | AT83: Analyst
A84: 45755.038 | B84: Omoyemi | C84: Fayemi | D84: BLK-24099 | E84: liyof5@nottingham.ac.uk | F84: yfayemi29@gmail.com | G84: Personal email | H84: =IF(G84="College/Secondary email:",E84,F84) -> yfayemi29@gmail.com | I84: Purfleet | J84: Analyst | K84: +447939403335 | L84: Male | M84: Fall 2024 | N84: 2026 | O84: EMEA | P84: N/A | Q84: No | R84: Level2 | S84: London, UK | T84: Quantitative Research/Trading | U84: 1 | V84: N/A | W84: N/A | X84: N/A | Y84: N/A | Z84: N/A | AA84: N/A | AB84: N/A | AC84: N/A | AD84: N/A | AE84: N/A | AF84: N/A | AG84: N/A | AH84: University of Nottingham | AI84: Nottingham | AJ84: Target | AK84: 1:1 | AL84: Finance, Accounting And Management | AM84: 2026 | AN84: SEO (EMEA), UpReach | AO84: https://drive.google.com/open?id=1mH4iNv85t1fJnIrechVblzU7GqitKYD_ | AP84: Investment Banking, Private Equity, Asset Management | AQ84: Rothschild & Co interests me the most. | AT84: Analyst
A85: 45755.134 | B85: Dipo | C85: Adedeji | D85: BLK - 24173 | E85: maa422@student.bham.ac.uk | F85: dipoadedeji@live.co.uk | G85: Personal email | H85: =IF(G85="College/Secondary email:",E85,F85) -> dipoadedeji@live.co.uk | I85: London | J85: Analyst | K85: +447375465243 | L85: Male | M85: Fall 2024 | N85: 2027 | O85: EMEA | P85: London (EMEA) | Q85: Yes | R85: JP Morgan | S85: London | T85: Sales & trading | U85: N/A | V85: N/A | W85: N/A | X85: N/A | Y85: N/A | Z85: N/A | AA85: N/a | AB85: N/a | AC85: N/a | AD85: N/a | AE85: N/a | AF85: N/a | AG85: N/a | AH85: University of Birmingham | AI85: Birmingham | AJ85: Target | AK85: First class | AL85: Economics | AM85: 2027 | AN85: Generating Genius | AO85: https://drive.google.com/open?id=1apeKY7bNjxhF6Nq9-4EhshJr4O3WzJhE | AP85: Investment Banking, Sales and Trading, Private Equity, Asset Management, Management Consulting, Hedge Funds | AQ85: JP Morgan, Deutsche Bank, Goldman Sachs | AT85: Education Pathways (IB, AWM, or PE)
A86: 45755.32 | B86: Nicole | C86: Tettey | D86: 23426 | E86: nmdt1@st-andrews.ac.uk | F86: tetteynicole@gmail.com | G86: College/Secondary email: | H86: =IF(G86="College/Secondary email:",E86,F86) -> nmdt1@st-andrews.ac.uk | I86: Vienna | J86: Analyst | K86: +447446214091 | L86: Female | M86: Spring 2024 | N86: 2026 | O86: EMEA | P86: N/A | Q86: No | R86: N/A | S86: N/A | T86: N/A | U86: N/A | V86: N/A | W86: N/A | X86: N/A | Y86: N/A | Z86: N/A | AA86: N/A | AB86: UBS | AC86: London | AD86: Investment Banking | AE86: 3 | AF86: My other offers were in Big 4 financial services consulting and in wealth management, and I felt that my exit opportunities would be wider in investment banking. | AG86: N/A | AH86: University of St Andrews | AI86: St Andrews | AJ86: Non-target | AK86: 0.75 | AL86: Economics and International Relations | AM86: 2026 | AN86: N/A | AO86: https://drive.google.com/open?id=1vhjT1LHsuLF1qmHF3J_0idz81VH6GnrM | AP86: Investment Banking, Private Equity | AQ86: UBS, Goldman Sachs, J. P. Morgan, Morgan Stanley | AS86: London Tour | AT86: Analyst
A87: 45755.352 | B87: Kiran | C87: Harper | D87: BLK - 24052 | E87: kiranhar@bu.edu | F87: kiranharper1@gmail.com | G87: College/Secondary email: | H87: =IF(G87="College/Secondary email:",E87,F87) -> kiranhar@bu.edu | I87: Los Angeles, CA | J87: Analyst | K87: 16615235716 | L87: Male | M87: Fall 2024 | N87: 2026 | O87: North America | P87: Boston (U.S.) | Q87: Yes | R87: N/A | S87: N/A | T87: N/A | U87: N/A | V87: N/A | W87: N/A | X87: N/A | Y87: N/A | Z87: N/A | AA87: N/A | AB87: Aberdeen Group | AC87: Boston, MA | AD87: Asset management | AE87: 1 | AF87: N/A | AG87: N/A | AH87: Boston University | AI87: Boston, MA | AJ87: Non-target | AK87: 3 | AL87: Business/Finance | AM87: 2026 | AN87: Project Destined | AO87: https://drive.google.com/open?id=11bOqHmeeLpvPMdGLZ4LpsfkXKePDzkpG | AP87: Investment Banking, Sales and Trading, Private Equity, Asset Management, Hedge Funds | AQ87: UBS, Arsenal Capital, Evercore | AR87: I am very interested in investment banking because I am more of a fast paced, deal person compared to asset management indsutry which I currently have an offer for. I was not sure what I was interested and once I decided, recruitment for banking was already over. I am now figuring out how to break into banking from asset management. | AS87: Conference and all of the zoom calls | AT87: Analyst
A88: 45755.379 | B88: Ty | C88: Gichina | D88: 24233 | E88: nss23kwu@uea.ac.uk | F88: tygichina@gmail.com | G88: Personal email | H88: =IF(G88="College/Secondary email:",E88,F88) -> tygichina@gmail.com | I88: Milton Keynes | J88: Analyst | K88: +447496687771 | L88: Male | M88: Fall 2024 | N88: 2026 | O88: EMEA | P88: London (EMEA) | Q88: Maybe | R88: HSBC | S88: London | T88: Investment Banking | U88: 1 | V88: N/A | W88: Pending | X88: London | Y88: Pending | Z88: Pending | AA88: Pending | AB88: N/A | AC88: N/A | AD88: N/A | AE88: N/A | AF88: N/A | AG88: N/A | AH88: University of East Anglia | AI88: Norwich | AJ88: Non-target | AK88: 2:1 | AL88: Accounting and Finance | AM88: 2026 | AN88: SEO (EMEA), Rare Recruitment | AO88: https://drive.google.com/open?id=1_GEIzMbx-gggKIWNX9kSc6EjeKsdIsbo | AP88: Investment Banking, Sales and Trading, Private Equity, Asset Management, Venture Capital, Hedge Funds | AQ88: Goldman Sachs, UBS, Vanguard, J.P. Morgan, Barings, Advent International, Carlyle, DE Shaw, KKR, PWP, Wells Fargo | AR88: Investment Banking, Sales (Sales & Trading), Private Equity, Private Banking/Wealth Management, Asset Management | AT88: Analyst
A89: 45755.528 | B89: Nabiel | C89: Yonas | D89: BLK-24187 | E89: kf24037@bristol.ac.uk | F89: nabielyonas123@icloud.com | G89: Personal email | H89: =IF(G89="College/Secondary email:",E89,F89) -> nabielyonas123@icloud.com | I89: London/Bristol | J89: Analyst | K89: +447376113622 | L89: Male | M89: Fall 2024 | N89: 2027 | O89: EMEA | P89: N/A | Q89: No | R89: N/A | S89: N/A | T89: N/A | U89: N/A | V89: N/A | W89: N/A | X89: N/A | Y89: N/A | Z89: N/A | AA89: N/A | AB89: N/A | AC89: N/A | AD89: N/A | AE89: N/A | AF89: N/A | AG89: N/A | AH89: University of Bristol | AI89: Bristol | AJ89: Semi-Target | AK89: 2:1 | AL89: Economics | AM89: 2027 | AN89: SEO (EMEA), UpReach | AO89: https://drive.google.com/open?id=1FgeiLO_-s-zPeoK4vOG0WfXCRZ_TqnGK | AP89: Investment Banking, Sales and Trading, Private Equity, Asset Management, Quantitative Finance (eg. Quant Trading), Venture Capital, Hedge Funds, Business & Entreprenuership, Legal, Risk & Compliance | AQ89: EMEA Based | AT89: Education Pathways (IB, AWM, or PE)
A90: 45755.564 | B90: Peter | C90: Haile | D90: BLK - 23215 | E90: Queen's University | F90: peterhaile23@gmail.com | G90: Personal email | H90: =IF(G90="College/Secondary email:",E90,F90) -> peterhaile23@gmail.com | I90: Toronto | J90: Senior analyst | K90: +16478046086 | L90: Male | M90: Fall 2023 | N90: 2026 | O90: North America | P90: Toronto (Canada) | Q90: Yes | R90: CIBC | S90: Toronto, Canada | T90: Real Estate Corporate Banking | U90: N/A | V90: N/A | W90: CIBC | X90: Toronto, Canada | Y90: Risk Management | Z90: n/a | AA90: N/A | AB90: RBC | AC90: Toronto, Canada | AD90: Investment Banking | AE90: N/A | AF90: N/A | AG90: N/A | AH90: Queen's University | AI90: Kingston | AJ90: Target | AK90: N/A | AL90: Commerce | AM90: 2026 | AN90: N/A | AO90: https://drive.google.com/open?id=1DF0d2BDoDO8kEuFe4D61feyH19zF_xO5 | AP90: Investment Banking | AQ90: Alpine, Evercore | AS90: Conference | AT90: Education Pathways (IB, AWM, or PE)
A91: 45755.602 | B91: Amonte | C91: McNair | D91: BLK-24068 | E91: admcnair@ncsu.edu | F91: amontemcnair21@gmail.com | G91: Personal email | H91: =IF(G91="College/Secondary email:",E91,F91) -> amontemcnair21@gmail.com | I91: Durham | J91: Community Member | K91: +19194641938 | L91: Male | M91: Fall 2024 | N91: 2026 | O91: North America | P91: N/A | Q91: Yes | R91: N/A | S91: N/A | T91: N/A | U91: N/A | V91: N/A | W91: The Preiss Company | X91: Raleigh, NC | Y91: Real Estate | Z91: 1 | AA91: N/A | AB91: Lowe's Home Improved | AC91: Mooresville, NC | AD91: Home Improvement | AE91: 1 | AF91: N/A | AG91: N/A | AH91: North Carolina State University | AI91: Raleigh | AJ91: Non-target | AK91: 3.1 | AL91: Business Administration: Finance Concentration | AM91: 2026 | AN91: N/A | AO91: https://drive.google.com/open?id=1fYiQKI5qdJgyW6wFuDArospSr4FPXUf- | AP91: Asset Management, Quantitative Finance (eg. Quant Trading), Business & Entreprenuership, Technology | AQ91: Vanguard, Fidelity Investments, Wells Fargo, LLR Partners | AS91: New York Conference & Insight Calls | AT91: Community Member
A92: 45755.722 | B92: Philip | C92: Giwa | D92: BLK- | E92: philip.giwa@baruchmail.cuny.edu | F92: jordangiwa1416@gmail.com | G92: Personal email | H92: =IF(G92="College/Secondary email:",E92,F92) -> jordangiwa1416@gmail.com | I92: Brooklyn | J92: Community Member | K92: 13473232330 | L92: Male | M92: Fall 2024 | N92: 2027 | O92: North America | P92: New York City (U.S.) | Q92: Yes | R92: N/A | S92: N/A | T92: N/A | U92: N/A | V92: N/A | W92: N/A | X92: N/A | Y92: N/A | Z92: N/A | AA92: N/A | AB92: N/A | AC92: N/A | AD92: N/A | AE92: N/A | AF92: N/A | AG92: N/A | AH92: Baruch College | AI92: NewYork | AJ92: Non-target | AK92: 3.4 | AL92: Finance | AM92: 2027 | AN92: MLT, SEO, INROADS | AO92: https://drive.google.com/open?id=1QEQzJZMSUyxtZDhIUTVjB4weJ686jHEr | AP92: Investment Banking, Sales and Trading, Private Equity, Business & Entreprenuership, Technology, Real Estate, HR | AQ92: JP Morgan, Morgan Stanley, UBS , Wells Fargo | AR92: I’m currently majoring in Finance at Baruch College, and I’m really interested in pursuing a career in investment banking. I’ve always been drawn to the fast-paced, high-impact nature of the field, especially the way investment banking allows you to work on major transactions like mergers and acquisitions, IPOs, and financial restructuring. I like the idea of helping companies grow, raise capital, or navigate big changes by providing strategic financial advice. | AS92: All the spotlight calls as a whole have helped me tremendously! | AT92: Education Pathways (IB, AWM, or PE)
A93: 45755.736 | B93: Nicole | C93: Balbuena Gutierrez | D93: BLK - 23362 | E93: nicole.balbuena@trincoll.edu | F93: nicolebalbuenaaa@gmail.com | G93: College/Secondary email: | H93: =IF(G93="College/Secondary email:",E93,F93) -> nicole.balbuena@trincoll.edu | I93: Bayside, NY | J93: Community Member | K93: +13478247758 | L93: Female | M93: Spring 2023 | N93: 2026 | O93: North America | P93: New York City (U.S.) | Q93: Yes | R93: JP Morgan Chase & Co | S93: New York, New York | T93: Sales & trading | U93: 1 | V93: I did not take my JP Morgan offer because I did not love the big bank intern experience and wanted to explore other options | W93: Jefferies LLC | X93: New York, New York | Y93: investment banking and sales & trading | Z93: 1 | AA93: I took my offer | AB93: Jefferies LLC | AC93: New York, New York | AD93: investment banking | AE93: 1 | AF93: N/A | AG93: N/A | AH93: Trinity College | AI93: Hartford, CT | AJ93: Liberal Arts College, Non-Target School | AK93: 3.3 | AL93: Computer Science and French | AM93: 2026 | AN93: Prep for Prep | AO93: https://drive.google.com/open?id=12EsO2q04uWN7FlvimyLAzf5khW_bpy0Q | AP93: Investment Banking, Private Equity, Venture Capital, Hedge Funds, Real Estate | AQ93: Jefferies | AT93: Analyst
A94: 45755.768 | B94: Tobi | C94: Dairo | D94: BLK-24092 | E94: td472@cam.ac.uk | F94: tobidairo@outlook.com | G94: Personal email | H94: =IF(G94="College/Secondary email:",E94,F94) -> tobidairo@outlook.com | I94: Cambridge | J94: Senior analyst | K94: +4407469244214 | L94: Male | M94: Fall 2024 | N94: 2027 | O94: EMEA | P94: London (EMEA) | Q94: No | R94: N/A | S94: N/A | T94: N/A | U94: N/A | V94: N/A | W94: Jane Street | X94: London, United Kingdom | Y94: Quantitative Trading | Z94: 1 | AA94: N/A | AB94: N/A | AC94: N/A | AD94: N/A | AE94: N/A | AF94: N/A | AG94: N/A | AH94: University of Cambridge | AI94: Cambridge | AJ94: Target | AK94: N/A | AL94: Medicine | AM94: 2027 | AN94: SEO (EMEA), Rare Recruitment | AO94: https://drive.google.com/open?id=1j-lJgaPIGee1tul0G45mgUEz6qNY_XGj | AP94: Investment Banking, Sales and Trading, Private Equity, Asset Management, Quantitative Finance (eg. Quant Trading), Management Consulting, Venture Capital, Hedge Funds, Business & Entreprenuership, Technology | AQ94: ⠀ | AT94: Analyst
A95: 45755.772 | B95: Tia | C95: Turner | D95: 23324 | E95: tia.turner@richmond.edu | F95: litiaturner@gmail.com | G95: College/Secondary email: | H95: =IF(G95="College/Secondary email:",E95,F95) -> tia.turner@richmond.edu | I95: Richmond, VA | J95: Trainee Analyst | K95: 18047188669 | L95: Female | M95: Spring 2024 | N95: 2026 | O95: North America | P95: N/A | Q95: Yes | R95: Dominion Energy | S95: Richmond, VA | T95: Energy | U95: N/A | V95: N/A | W95: Hudson Way Capital Management | X95: Dallas, TX | Y95: Hedge Fund | Z95: N/A | AA95: N/A | AB95: Bank of America | AC95: Jersey City, NJ | AD95: Wealth Management | AE95: 3 | AF95: Pay, ideal location, and job description was not ideal | AG95: N/A | AH95: University of Richmond | AI95: Richmond, VA | AJ95: Liberal Arts College, Non-Target School | AK95: 3.1 | AL95: Business Administration | AM95: 2026 | AN95: INROADS, Girls Who Invest | AO95: https://drive.google.com/open?id=1jQ4J0-cgXhYov2CZMcjtcCkCxekHObeI | AP95: Asset Management, Management Consulting, Business & Entreprenuership, HR, Wealth Management | AQ95: N/A | AT95: Analyst
A96: 45755.882 | B96: Iman | C96: Adeobafemi | D96: BLK-2242 | E96: iadeobafemi1@pride.hofstra.edu | F96: imooniximan@gmail.com | G96: Personal email | H96: =IF(G96="College/Secondary email:",E96,F96) -> imooniximan@gmail.com | I96: Jamaica, NY | J96: Executive board | K96: +19292329908 | L96: Female | M96: Fall 2022 | N96: 2025 | O96: North America | P96: New York City (U.S.) | Q96: Yes | R96: N/A | S96: N/A | T96: N/A | U96: N/A | V96: N/A | W96: Deloitte | X96: New York, New York | Y96: Professional Services | Z96: 1 | AA96: N/A | AB96: Deutsche Bank | AC96: New York, New York | AD96: Investment Banking | AE96: 2 | AF96: Better Work Culture and preferred subject matter. | AG96: Deloitte | AH96: Hofstra University | AI96: Hempstead | AJ96: Liberal Arts College, Non-Target School | AK96: 3.5 | AL96: Business Economics | AM96: 2025 | AN96: N/A | AO96: https://drive.google.com/open?id=15rTm5zgSp75qmB-MTQkeCHOGeQ9sgEhz | AP96: Investment Banking, Technology | AQ96: Jane Street, PGIM, Alpine | AR96: I'd like to work in a role that combines finance with technology or roles within Private Credit | AT96: Alumni (only select if you are graduated/graduating this year)
A97: 45755.967 | B97: April | C97: Thomas | D97: BLK - 23076 | E97: aprilthomas@miami.edu | F97: aplisat@gmail.om | G97: Personal email | H97: =IF(G97="College/Secondary email:",E97,F97) -> aplisat@gmail.om | I97: Rahway | J97: Community Member | K97: 9087593897 | L97: Female | M97: Spring 2023 | N97: 2025 | O97: North America | P97: N/A | Q97: Yes | R97: Healthy Amplified | S97: Chicago, IL | T97: Startups | U97: N/A | V97: N/A | W97: The Baupost Group | X97: Boston, MA | Y97: Valuation | Z97: N/A | AA97: N/A | AB97: Wells Fargo Securities | AC97: Charlotte, NC | AD97: Investment banking | AE97: N/A | AF97: N/S | AG97: Wells Fargo Securities | AH97: University of Miami | AI97: Miami, FL | AJ97: Non-target | AK97: 3.5 | AL97: Business Technology | AM97: 2025 | AN97: MLT, SEO, INROADS, Girls Who Invest, Project Destined | AO97: https://drive.google.com/open?id=1Jtr6pjLV_iRGiXxwZYJeW4Jx1NIx2M4c | AP97: Private Equity | AQ97: Vista Equity, Global Infrastructure Partners, Silver Lake ; any any generalist, tech, or infrastructure MM | AR97: Generalist, Tech, Real Estate or Infrastructure. Open to UMM and MM | AS97: it's been tough as I haven't really been attending. focused on PE technicals. | AT97: Alumni (only select if you are graduated/graduating this year)
A98: 45756.204 | B98: Naomi | C98: Omoroghomwan | D98: BLK - 23271 | E98: bt23496@qmul.ac.uk | F98: naomi6446@gmail.com | G98: College/Secondary email: | H98: =IF(G98="College/Secondary email:",E98,F98) -> bt23496@qmul.ac.uk | I98: Zurich | J98: Executive board | K98: +41779540745 | L98: Female | M98: Fall 2023 | N98: 2026 | O98: EMEA | P98: London (EMEA) | Q98: No | R98: Black in Cancer | S98: Exeter UK | T98: Cancer research | U98: n/a | V98: I want to do Finance | W98: NatWest group | X98: London | Y98: Corporate and commercial banking | Z98: 1 (spring week conversion so did not apply) | AA98: n/a interning this summer | AB98: n/a | AC98: n/a | AD98: n/a | AE98: n/a | AF98: n/a | AG98: n/a | AH98: Queen Mary Univeristy of London | AI98: London | AJ98: Non-target | AK98: UK - 2.1 degree class | AL98: Neuroscience | AM98: 2026 | AN98: SEO (EMEA) | AO98: https://drive.google.com/open?id=1Vfn0h1VNCr0XaBaQL2krlttXBZJr48ry | AP98: Management Consulting, Business & Entreprenuership, HR | AQ98: DE Shaw, KKR, JP Morgan, Lazard, UBS | AR98: Corporate banking, Relationship Management, Investor relations, client services | AS98: n/a | AT98: Community Member
A99: 45756.278 | B99: Nhyira | C99: Boateng | D99: 24103 | E99: nb716@cam.ac.uk | F99: nhyira0206@gmail.com | G99: Personal email | H99: =IF(G99="College/Secondary email:",E99,F99) -> nhyira0206@gmail.com | I99: Wellingborough | J99: Analyst | K99: +447508624611 | L99: Male | M99: Fall 2024 | N99: 2027 | O99: EMEA | P99: N/A | Q99: No | R99: N/A | S99: N/A | T99: N/A | U99: N/A | V99: N/A | W99: N/A | X99: N/A | Y99: N/A | Z99: N/A | AA99: N/A | AB99: N/A | AC99: N/A | AD99: N/A | AE99: N/A | AF99: N/A | AG99: N/A | AH99: University of Cambridge | AI99: Cambridge | AJ99: University | AK99: 3.7 | AL99: N/A | AM99: 2027 | AN99: SEO (EMEA), Rare Recruitment | AO99: https://drive.google.com/open?id=1i4dmCF0YTtPrOV6vXu4rB6qjyzvp93s4 | AP99: Investment Banking, Sales and Trading, Private Equity, Asset Management, Quantitative Finance (eg. Quant Trading), Management Consulting, Business & Entreprenuership, Technology | AQ99: JPM Bain BCG McKinsey | AT99: Community Member
A100: 45756.522 | B100: Salah | C100: Farouqi | D100: 24206 | E100: Salah_Farouqi@student.uml.edu | F100: salahfarouqi7@gmail.com | G100: Personal email | H100: =IF(G100="College/Secondary email:",E100,F100) -> salahfarouqi7@gmail.com | I100: Melrose, MA | J100: Analyst | K100: 7814753205 | L100: Male | M100: Fall 2024 | N100: 2026 | O100: North America | P100: Boston (U.S.) | Q100: Yes | R100: Inspire Clean Energy & NRG | S100: Field Sales Role(Multiple Territories, MA) | T100: Sales & Trading, Investment Banking | U100: 0 | V100: N/A | W100: MFS Investment Management | X100: Boston, MA | Y100: International Sales | Z100: N/A | AA100: N/A | AB100: Fannie Mae (Summer 2025) | AC100: Washington, D.C. | AD100: Financial services | AE100: 2 | AF100: Morgan Stanley offer was for WM with no relocation stipend. | AG100: N/A | AH100: University of Massachusetts Lowell | AI100: Lowell, MA | AJ100: Non-target | AK100: 3.6 | AL100: Finance | AM100: 2026 | AN100: SEO, Project Destined | AO100: https://drive.google.com/open?id=1PooztLna2yYDW6g9_e7gxtYHrdHhZqkW | AP100: Investment Banking, Sales and Trading, Real Estate | AQ100: I’m open to any firm where I can learn and contribute meaningfully. That said, I’d be especially interested in firms with strong real estate or investment banking platforms. | AR100: I’m interested in investment banking, specifically within the REGAL (Real Estate, Gaming, Lodging & Leisure) group. I enjoy the intersection of real assets and finance and would love to be considered for opportunities in this space | AS100: Financeable | AT100: Education Pathways (IB, AWM, or PE)
...

Sheet Mail merge sheet
A1: name | C1: Blk id | G1: Preffered Email | O1: City | AT1: Filter Rows to Merge
A2: Brian | B2: Davids | C2: 23388 | D2: davidsbg@bc.edu | E2: bzachdavids@gmail.com | F2: College/Secondary email: | G2: =IF(F2="College/Secondary email:",D2,E2) -> davidsbg@bc.edu | H2: Glenn Dale | I2: Analyst | J2: +13015182003 | K2: Male | L2: Spring 2024 | M2: 2027 | N2: North America | O2: Boston (U.S.) | P2: Yes | Q2: Long Horizon Partners | R2: Virtual | S2: Private Equity | T2: 1 | U2: N/A | V2: PWC | W2: New York, NY | X2: Consulting | Y2: 1 | Z2: N/A | AA2: Evercore | AB2: New York, NY | AC2: Investment Banking | AD2: 1 | AE2: N/A | AF2: N/A | AG2: Boston College | AH2: Newton, MA | AI2: Target | AJ2: 3.7 | AK2: Finance and Business Analytics | AL2: 2027 | AM2: MLT, SEO | AN2: https://drive.google.com/open?id=1XWClHCwCx5aNJniGdFhaFayO5decO7qu | AO2: Investment Banking, Private Equity, Venture Capital, Hedge Funds | AP2: Advent, DE Shaw, Warburg | AQ2: Pursuing Banking but interested in Public and Private Markets Investing for After Analyst Years | AS2: Analyst | AT2: Merged on Nov 07, 2025 18:05:00
A3: EJ | B3: Ibhawoh | C3: 23043 | D3: ibhawoha@mcmaster.ca | E3: ejiyeibhawoh@gmail.com | F3: College/Secondary email: | G3: =IF(F3="College/Secondary email:",D3,E3) -> ibhawoha@mcmaster.ca | H3: Hamilton | I3: Analyst | J3: 19057450150 | K3: Male | L3: Fall 2022 | M3: 2026 | N3: North America | O3: Toronto (Canada) | P3: Yes | Q3: BDC | R3: Toronto | S3: Venture Capital | T3: N/A | U3: N/A | V3: CIBC | W3: Toronto | X3: Sales & Trading | Y3: N/A | Z3: N/A | AA3: RBC | AB3: Toronto | AC3: Investment Banking | AD3: N/A | AE3: N/A | AF3: N/A | AG3: McMaster University | AH3: Hamilton | AI3: Non-target | AJ3: 4 | AK3: Commerce | AL3: 2026 | AM3: Bridging the Gap | AN3: https://drive.google.com/open?id=1iSck4HjUOK-tMmh3tgnAAAmBNI8Eytqq | AO3: Investment Banking, Private Equity, Asset Management | AP3: JP Morgan, Goldman Sachs, Morgan Stanley | AQ3: Any American Investment Banking Position | AS3: Analyst | AT3: Merged on Nov 07, 2025 18:05:01
A4: Keyonte’ | B4: Doughty | C4: BLK - 23311 | D4: keyonte.d.doughty@vanderbilt.edu | E4: kd.doughty66@gmail.com | F4: Personal email | G4: =IF(F4="College/Secondary email:",D4,E4) -> kd.doughty66@gmail.com | H4: Tuscaloosa, AL | I4: Senior analyst | J4: 2058726413 | K4: Male | L4: Spring 2024 | M4: 2025 | N4: North America | O4: N/A | P4: Yes | Q4: Congressional Black Caucus Foundation | R4: Washington, D.C. | S4: Government | T4: N/A | U4: N/A | V4: Affiliated Managers Group | W4: Boston, MA | X4: Asset Management | Y4: N/A | Z4: N/A | AA4: Citigroup | AB4: New York, New York | AC4: Sales & Trading | AD4: 1 | AE4: N/A | AF4: Citi | AG4: Vanderbilt University | AH4: Nashville, TN | AI4: Target | AJ4: 3.63 | AK4: Human & Organizational Development, Political Science | AL4: 2025 | AM4: SEO | AN4: https://drive.google.com/open?id=1AWIuUcQF6mEJKQCCW_AbEXIbW1fEi7WZ | AO4: Investment Banking, Sales and Trading, Private Equity, Real Estate, Legal, Risk & Compliance | AP4: Bain & Capital, Carlyle Group, J.P. Morgan, Goldman Sachs, TD Cowen | AQ4: Interested in going to PE post S&T | AS4: Alumni (only select if you are graduated/graduating this year) | AT4: Merged on Nov 07, 2025 18:05:04
A5: Malik | B5: Denney | C5: BLK-23146 | D5: Malik.Denney@bison.Howard.edu | E5: Malik.denney1@gmail.con | F5: Personal email | G5: =IF(F5="College/Secondary email:",D5,E5) -> Malik.denney1@gmail.con | H5: Atlanta | I5: Analyst | J5: 4046838903 | K5: Male | L5: Spring 2023 | M5: 2026 | N5: North America | O5: N/A | P5: Yes | Q5: Deloittw | R5: Atlanta, GA | S5: Consulting | T5: 2 | U5: Higher pay | V5: Permira Advisors | W5: New York, New York | X5: Private equity | Y5: 3 | Z5: Prestige | AA5: BMO Capital Markets | AB5: New York, NY | AC5: Investment Banking | AD5: 1 | AE5: Na | AF5: Na | AG5: Howard University | AH5: Washington D.C | AI5: Non-target | AJ5: 3.3 | AK5: Finance | AL5: 2026 | AM5: Huig | AN5: https://drive.google.com/open?id=1lMpAUbh_PZNJoJMd4p5HEoGGoWu_6ITj | AO5: Investment Banking | AP5: Evercore | AS5: Education Pathways (IB, AWM, or PE) | AT5: Merged on Nov 07, 2025 18:05:05
A6: Patrick | B6: Bongo | C6: 24020 | D6: patrick.m.bongo.27@dartmouth.edu | E6: MVOO21032GMAIL.COM | F6: College/Secondary email: | G6: =IF(F6="College/Secondary email:",D6,E6) -> patrick.m.bongo.27@dartmouth.edu | H6: Mombasa | I6: Analyst | J6: +6032668130 | K6: Male | L6: Spring 2024 | M6: 2027 | N6: North America | O6: N/A | P6: Yes | Q6: N/A | R6: N/A | S6: N/A | T6: N/A | U6: N/A | V6: N/A | W6: N/A | X6: N/A | Y6: N/A | Z6: N/A | AA6: Nomura | AB6: NYC | AC6: Sales & Trading | AD6: 2 | AE6: Preference | AF6: N/A | AG6: Dartmouth College | AH6: Hanover | AI6: Target | AJ6: 3.74 | AK6: Comp Science | AL6: 2027 | AM6: Black Gen Finance | AN6: https://drive.google.com/open?id=16Pz6ikkt1Lbyfoxv_PL_tlhdmij0Vh2w | AO6: Investment Banking, Sales and Trading, Private Equity | AP6: PE | AQ6: PE and any other PE organizations | AS6: Analyst | AT6: Merged on Nov 07, 2025 18:05:05
A7: Maya | B7: Lewis | C7: BLK-24102 | D7: mayajlewis@uchicago.edu | E7: tobidairo@outlook.com | F7: College/Secondary email: | G7: =IF(F7="College/Secondary email:",D7,E7) -> mayajlewis@uchicago.edu | H7: Burlington, NJ | I7: Analyst | J7: 9083009622 | K7: Female | L7: Fall 2024 | M7: 2028 | N7: North America | O7: N/A | P7: Yes | Q7: N/A | R7: N/A | S7: N/A | T7: N/A | U7: N/A | V7: N/A | W7: N/A | X7: N/A | Y7: N/A | Z7: N/A | AA7: N/A | AB7: N/A | AC7: N/A | AD7: N/A | AE7: N/A | AF7: N/A | AG7: University of Chicago | AH7: Chicago | AI7: Target | AJ7: 3.3 | AK7: Business Economics & Public Policy | AL7: 2028 | AM7: INROADS, Girls Who Invest, Project Destined | AN7: https://drive.google.com/open?id=1RiHQVITmVo-4QtHRbp2hoX6czBXfkctD | AO7: Sales and Trading, Venture Capital, Hedge Funds, Economic Consulting, Equity Research | AP7: Nera, US Bank, Cornerstone Research | AS7: Analyst | AT7: Merged on Nov 07, 2025 18:05:06
A8: Jamari | B8: Myers | C8: BLK - 23372 | D8: jamari_myers@brown.edu | E8: jamari.myers2023@gmail.com | F8: College/Secondary email: | G8: =IF(F8="College/Secondary email:",D8,E8) -> jamari_myers@brown.edu | H8: Mansfield, TX | I8: Analyst | J8: +19789980846 | K8: Male | L8: Spring 2024 | M8: 2027 | N8: North America | O8: N/A | P8: Yes | Q8: Decatur Street Capital | R8: Remote | S8: Private Equity - Search Fund | T8: 3 | U8: This internship was the best fit for what I hoped to gain. | V8: J.P. Morgan | W8: New York, New York | X8: Investment Banking | Y8: 1 | Z8: N/A | AA8: N/A, J.P. Morgan | AB8: New York, New York | AC8: Investment Banking | AD8: N/A | AE8: N/A | AF8: N/A | AG8: Brown University | AH8: Providence, RI | AI8: Target | AJ8: 3.75 | AK8: Business Economics and Entrepreneurship | AL8: 2027 | AM8: SEO | AN8: https://drive.google.com/open?id=1cvj_Ut2UurUuoFcS8Zx3chzUe28w8nzo | AO8: Investment Banking, Private Equity, Business & Entreprenuership | AP8: Apollo | AS8: Analyst | AT8: Merged on Nov 07, 2025 18:05:07
A9: Christela | B9: Bosco | C9: BLK - 23351 | D9: Christelabosco@gmail.com | E9: Christelabosco@gmail.com | F9: Personal email | G9: =IF(F9="College/Secondary email:",D9,E9) -> Christelabosco@gmail.com | H9: Nashville, TN | I9: Roark fellow | J9: 1 | K9: Female | L9: Spring 2024 | M9: 2027 | N9: North America | O9: Atlanta (U.S.) | P9: Yes | Q9: N/A | R9: N/A | S9: N/A | T9: N/A | U9: N/A | V9: N/A | W9: N/A | X9: N/A | Y9: N/A | Z9: N/A | AA9: N/A | AB9: N/A | AC9: N/A | AD9: N/A | AE9: N/A | AF9: N/A | AG9: University of Tennessee | AH9: Knoxville | AI9: Non-target | AJ9: 4 | AK9: Business | AL9: 2027 | AM9: SEO, Girls Who Invest | AN9: https://drive.google.com/open?id=130pSyXHdOXzXoDZg7PCHxTxFFC30zM46 | AO9: Private Equity, Management Consulting, Real Estate, Legal, Risk & Compliance | AP9: Blackstone, Ares, Carlyle, KKR | AS9: Community Member | AT9: Merged on Nov 07, 2025 18:05:08
A10: Steve | B10: Fotso | C10: BLK - 24074 | D10: fotsos@mcmaster.ca | E10: fotsoryan@gmail.com | F10: Personal email | G10: =IF(F10="College/Secondary email:",D10,E10) -> fotsoryan@gmail.com | H10: Hamilton, Canada | I10: Senior analyst | J10: 12265064621 | K10: Male | L10: Fall 2024 | M10: 2026 | N10: North America | O10: Toronto (Canada) | P10: No | Q10: Investment Management Corporation of Ontario (IMCO) | R10: Toronto, Ontario | S10: Asset Managament | T10: N/A | U10: N/A | V10: Toronto Dominion (TD) Bank | W10: Toronto, Ontario | X10: Compliance | Y10: N/A | Z10: N/A | AA10: N/A | AB10: N/A | AC10: N/A | AD10: N/A | AE10: N/A | AF10: N/A | AG10: McMaster University | AH10: Hamilton, Canada | AI10: Non-target | AJ10: 3.7 | AK10: Finance | AL10: 2026 | AM10: BLK, Investa | AN10: https://drive.google.com/open?id=12TOa85ti3NI1BDLBYA6chnLLNueEtTGS | AO10: Investment Banking, Sales and Trading, Asset Management | AP10: TD Securities | AS10: Education Pathways (IB, AWM, or PE) | AT10: Merged on Nov 07, 2025 18:05:09
A11: Zorian | B11: Facey | C11: BLK-24144 | D11: Zorian_facey@brown.edu | E11: Zorianfacey@gmail.com | F11: Personal email | G11: =IF(F11="College/Secondary email:",D11,E11) -> Zorianfacey@gmail.com | H11: Oviedo, FL | I11: Analyst | J11: +13217465351 | K11: Female | L11: Fall 2024 | M11: 2027 | N11: North America | O11: N/A | P11: Yes | Q11: Leo Legacy (search fund) | R11: Remote | S11: Private equity analyst | T11: N/A | U11: N/A | V11: Wellington Management (incoming) | W11: Boston, MA | X11: Asset management | Y11: I got matched through Girls Who Invest and was not permitted to apply elsewhere. | Z11: N/A | AA11: N/A | AB11: N/A | AC11: N/A | AD11: N/A | AE11: N/A | AF11: N/A | AG11: Brown University | AH11: Providence, RI | AI11: Semi-target | AJ11: 3.75 | AK11: Applied Mathematics & Economics | AL11: 2027 | AM11: MLT, Girls Who Invest | AN11: https://drive.google.com/open?id=1MWO7gqjlYq4Y2teYnEPNrc0iDJzyD2ti | AO11: Investment Banking, Private Equity, Asset Management, Equity Research | AP11: Bain Capital, Carlyle, KKR, Fidelity, GS, MS | AQ11: Very interested in PE, though I also am exploring investment management and research. | AS11: Analyst | AT11: Merged on Nov 07, 2025 18:05:10
A12: Paul | B12: Owusu-Ansah | C12: BLK - 24252 | D12: Rayvon.owusu-ansah@city.ac.uk | E12: paul.owusu-ansah@outlook.com | F12: Personal email | G12: =IF(F12="College/Secondary email:",D12,E12) -> paul.owusu-ansah@outlook.com | H12: London | I12: Analyst | J12: 07395543260 | K12: Male | L12: Fall 2024 | M12: 2026 | N12: EMEA | O12: London (EMEA) | P12: No | Q12: N/A | R12: N/A | S12: N/A | T12: N/A | U12: N/A | V12: Morgan Stanley | W12: London | X12: Market Risk | Y12: Received full time offer | Z12: N/A | AA12: N/A | AB12: N/A | AC12: N/A | AD12: N/A | AE12: N/A | AF12: Received full time offer for MS didn’t accept because it was not my preferred business area. | AG12: City University of London | AH12: Londo | AI12: Non-target | AJ12: Expected 1st Class Honours | AK12: Mechanical Engineering | AL12: 2026 | AM12: SEO (EMEA) | AN12: https://drive.google.com/open?id=1rACKWwWt9yWzd14P3W2TjFPaGo90ni_- | AO12: Investment Banking, Private Equity | AP12: N/A | AS12: Analyst | AT12: Merged on Nov 07, 2025 18:05:14
A13: Nihmatalai | B13: Olaojo | C13: BLK - 24188 | D13: n.olaojo@lse.ac.uk | E13: nihmatalai.olaojo8@gmail.com | F13: Personal email | G13: =IF(F13="College/Secondary email:",D13,E13) -> nihmatalai.olaojo8@gmail.com | H13: London | I13: Analyst | J13: +447955422844 | K13: Female | L13: Fall 2024 | M13: 2027 | N13: EMEA | O13: London (EMEA) | P13: No | Q13: N/A | R13: N/A | S13: N/A | T13: N/A | U13: N/A | V13: N/A | W13: N/A | X13: N/A | Y13: N/A | Z13: N/A | AA13: N/A | AB13: N/A | AC13: N/A | AD13: N/A | AE13: N/A | AF13: N/A | AG13: London School of Economics and Political Science | AH13: London | AI13: Target | AJ13: N/A | AK13: Accounting and Finance | AL13: 2027 | AM13: SEO (EMEA), Rare Recruitment | AN13: https://drive.google.com/open?id=1OnqIhS613hbnxmlt64_QLYlrUWOfggHq | AO13: Investment Banking, Private Equity, Asset Management, Real Estate | AP13: N/A | AS13: Analyst | AT13: Merged on Nov 07, 2025 18:05:15
A14: Xamora | B14: Reed | C14: BLK - 24194 | D14: xreed@aggies.ncat.edu | E14: reed.xamora@gmail.com | F14: Personal email | G14: =IF(F14="College/Secondary email:",D14,E14) -> reed.xamora@gmail.com | H14: Charlotte, NC | I14: Analyst | J14: +17048044258 | K14: Female | L14: Fall 2024 | M14: 2027 | N14: North America | O14: N/A | P14: Yes | Q14: Wells Fargo | R14: Charlotte, NC | S14: Corporate Finance | T14: 1 | U14: N/A | V14: N/A | W14: N/A | X14: N/A | Y14: N/A | Z14: N/A | AA14: N/A | AB14: N/A | AC14: N/A | AD14: N/A | AE14: N/A | AF14: N/A | AG14: North Carolina A&T State University | AH14: Greensboro, NC | AI14: HBCU (Historically Black Colleges and Universities) | AJ14: 4 | AK14: Economics (Law) | AL14: 2027 | AM14: MLT, Forte, Greenwood Project | AN14: https://drive.google.com/open?id=1FbdVgS-aPP6RzHZx6vasc8lxS2jTXtx2 | AO14: Investment Banking, Sales and Trading, Private Equity, Asset Management, Venture Capital, Hedge Funds | AP14: Alphine, Bain Capital, Evercore, Goldman Sachs, JP Morgan, KKR, Lazard, Morgan Stanley, Neuberger Berman, PWP, Roark, UBS, Warburg Pincus, Wells Fargo | AS14: Analyst | AT14: Merged on Nov 07, 2025 18:05:16
A15: Chijioke | B15: Achebe | C15: BLK - 22249 | D15: coa13@georgetown.edu | E15: chijioke.achebe@gmail.com | F15: Personal email | G15: =IF(F15="College/Secondary email:",D15,E15) -> chijioke.achebe@gmail.com | H15: West Orange, NJ | I15: Analyst | J15: +19735184496 | K15: Male | L15: Fall 2022 | M15: 2025 | N15: North America | O15: N/A | P15: Yes | Q15: Essex County Prosecutor's Office | R15: West Orange, NJ | S15: Government | T15: N/A | U15: N/A | V15: UBA America | W15: New York, NY | X15: Corporate Banking/Trade Finance | Y15: N/A | Z15: N/A | AA15: Morgan Stanley | AB15: New York, NY | AC15: Public Finance Investment Banking | AD15: 1 | AE15: N/A | AF15: N/A | AG15: Georgetown University | AH15: Washington, DC | AI15: Target | AJ15: 3.36 | AK15: International Politics | AL15: 2025 | AM15: N/A | AN15: https://drive.google.com/open?id=1vBAa5PcfoUUihYPMYN4PSi-xZ6Qq2YNR | AO15: Investment Banking, Sales and Trading, Private Equity, Asset Management, Management Consulting, Hedge Funds | AP15: Morgan Stanley, Goldman Sachs, J.P. Morgan, Bank of America, Citi | AQ15: I'm also very interested in commodity trading. Eventually, I want to invest in infrastructure projects across Africa - mining, railroads, energy, airports, ports, shipping, etc | AS15: Alumni (only select if you are graduated/graduating this year) | AT15: Merged on Nov 07, 2025 18:05:17
A16: Ezinne | B16: Okwesilieze | C16: BLK-24196 | D16: eo6856j@gre.ac.uk | E16: eokwesilieze1@gmail.com | F16: Personal email | G16: =IF(F16="College/Secondary email:",D16,E16) -> eokwesilieze1@gmail.com | H16: Essex | I16: Analyst | J16: +447908100192 | K16: Female | L16: Fall 2024 | M16: 2026 | N16: EMEA | O16: London (EMEA) | P16: If I gain a work visa | Q16: N/A | R16: N/A | S16: N/A | T16: N/A | U16: N/A | V16: Wellcome Trust | W16: Euston, London | X16: Asset/Investment Management | Y16: I wasn’t of the right year yet to get an offer | Z16: N/A | AA16: N/A | AB16: N/A | AC16: N/A | AD16: N/A | AE16: N/A | AF16: N/A | AG16: Medway School of Pharmacy | AH16: Kent | AI16: Non-target | AJ16: 2:1 | AK16: Pharmacy | AL16: 2026 | AM16: SEO (EMEA), Rare Recruitment | AN16: https://drive.google.com/open?id=1rpc33kD4sQfekQWeOLZ2oaP8_AUetpmg | AO16: Private Equity, Asset Management, Venture Capital, Business & Entreprenuership | AP16: Any reputable and inspiring firms | AQ16: After doing an internship in asset management, investment management, and venture capital, I realized that my pharmacy background could be a great fit for these fields. I’m drawn to the idea of having a bigger impact by shaping industries like healthcare, tech, or pharmaceuticals on a larger scale, beyond just working directly with patients. The critical thinking and data analysis skills I’ve developed in pharmacy are highly transferable, and my knowledge of the healthcare industry can help identify investment opportunities in emerging technologies or drug developments. I’m also interested in the entrepreneurial side of these fields, where I could apply my expertise to fund or start innovative companies. Additionally, asset and investment management offer more career variety and growth, with the chance to work across different industries and expand my professional network. Lastly, the potential for higher compensation is an attractive incentive, especially as I look to build long-term financial security while tackling new challenges. Moving into these fields feels like a natural next step where I can leverage my skills, learn new ones, and make a bigger impact. | AS16: Education Pathways (IB, AWM, or PE) | AT16: Merged on Nov 07, 2025 18:05:18
A17: Jonathan | B17: Colon | C17: 24256 | D17: Jonathan.Colon58@bcmail.cuny.edu | E17: jonathanacolon2012@gmail.com | F17: Personal email | G17: =IF(F17="College/Secondary email:",D17,E17) -> jonathanacolon2012@gmail.com | H17: New York, NY | I17: Analyst | J17: 9293619519 | K17: Male | L17: Fall 2024 | M17: 2027 | N17: North America | O17: New York City (U.S.) | P17: Yes | Q17: Soundboard Venturefund | R17: New York, NY | S17: Venture Capital | T17: N/A | U17: N/A | V17: Brown Advisory | W17: New York, NY | X17: Buyside, Wealth Management | Y17: 1 | Z17: N/A | AA17: MD Sass Investment Services | AB17: New York, NY | AC17: Equity Research | AD17: N/A | AE17: N/A | AF17: Morgan Stanley | AG17: Brooklyn College | AH17: CUNY Brooklyn College | AI17: Non-target | AJ17: 4 | AK17: Economic Analysis | AL17: 2027 | AM17: SEO, Project Destined, ALPFA, Wall Street Bound, Hello HIVE, Student Government | AN17: https://drive.google.com/open?id=1v6m_bFc2VA4CUqqLEAuuSJvSw3uVdkd3 | AO17: Investment Banking, Private Equity, Venture Capital, Real Estate | AP17: Black Rock, Blackstone, Goldman Sachs, Bridgewater, UBS, DWS, CBRE, Blue Owl Capital, Warburg Pincus | AQ17: I am very interested in breaking into IB, and heading down a career path that lands me at a Private Equity Fund, or in a role involving Capital Markets within Real Estate Investment Banking | AS17: Analyst | AT17: Merged on Nov 07, 2025 18:05:19
A18: David | B18: Ariyo | C18: BLK-24246 | D18: Ucnvd08@ucl.ac.uk | E18: DavidArriyo15@gmail.com | F18: Personal email | G18: =IF(F18="College/Secondary email:",D18,E18) -> DavidArriyo15@gmail.com | H18: London | I18: Analyst | J18: +447930300316 | K18: Male | L18: Fall 2024 | M18: 2025 | N18: EMEA | O18: London (EMEA) | P18: No | Q18: N/A | R18: N/A | S18: N/A | T18: N/A | U18: N/A | V18: N/A | W18: N/A | X18: N/A | Y18: N/A | Z18: N/A | AA18: Standard Chartered | AB18: London | AC18: Client coverage | AD18: 1 | AE18: N/A | AF18: Standard Chartered | AG18: University College London | AH18: London | AI18: Russed group | AJ18: 2:1 | AK18: Pharmacy | AL18: 2025 | AM18: N/A | AN18: https://drive.google.com/open?id=10ngrzdNG30QZicjH9i2arBJa3DmSo_wM | AO18: Asset Management, Wealth management, Credit risk | AP18: JP morgan, Goldman Sachs | AS18: Alumni (only select if you are graduated/graduating this year) | AT18: Merged on Nov 07, 2025 18:05:20
A19: Ausar | B19: Myers | C19: 24089 | D19: Ausarmyers@sandiego.edu | E19: Am23.myers@gmail.com | F19: College/Secondary email: | G19: =IF(F19="College/Secondary email:",D19,E19) -> Ausarmyers@sandiego.edu | H19: Miami, Florida | I19: Analyst | J19: 17866605695 | K19: Male | L19: Fall 2024 | M19: 2027 | N19: North America | O19: N/A | P19: Yes | Q19: The Shark Group | R19: Miami, Florida | S19: Private Equity | T19: 1 | U19: N/A | V19: Project Destined | W19: New York, New York | X19: Provate Equity | Y19: 1 | Z19: N/A | AA19: Nomura | AB19: New York, New York | AC19: Global Markets | AD19: 1 | AE19: N/A | AF19: N/A | AG19: The University of San Diego | AH19: San Diego | AI19: Non-target | AJ19: 3.7 | AK19: International Business | AL19: 2027 | AM19: MLT, Project Destined, HeadStart | AN19: https://drive.google.com/open?id=1GB2pvqbWT4-z8lbu0-KVcJahLlKrgp4P | AO19: Private Equity, Venture Capital, Business & Entreprenuership | AP19: LLR, Roark, Advent, Bain Capital, Carlyle, and Alpine | AQ19: I have currently found my Junior summer internship but as I align more with private equity, I am preparing for my graduating summer. | AS19: Analyst | AT19: Merged on Nov 07, 2025 18:05:21
A20: Otman | B20: Atfi | C20: BLK-24005 | D20: otmanatfi@vt.edu | E20: otmanatfi04@gmail.com | F20: Personal email | G20: =IF(F20="College/Secondary email:",D20,E20) -> otmanatfi04@gmail.com | H20: Richmond, VA | I20: Analyst | J20: +16176787176 | K20: Male | L20: Spring 2024 | M20: 2026 | N20: North America | O20: N/A | P20: Yes | Q20: N/A | R20: N/A | S20: N/A | T20: N/A | U20: N/A | V20: Dominion Energy | W20: Richmond, VA | X20: Energy | Y20: 1 | Z20: N/A | AA20: Wells Fargo | AB20: Boston, MA | AC20: Banking | AD20: 3 | AE20: I believed that this opportunity closely aligns with my future goals. | AF20: N/A | AG20: Virginia Tech | AH20: Blacksburg | AI20: Non-target | AJ20: 3.63 | AK20: Entrepreneurship Innovation Technology and Business Management | AL20: 2026 | AM20: SEO | AN20: https://drive.google.com/open?id=1H9Yxs0NaibyPCNQOwnx1lGDikSIGWFmd | AO20: Asset Management, Management Consulting, Business & Entreprenuership | AP20: Goldman Sachs, J.P. Morgan, Morgan Stanley, UBS | AS20: Community Member | AT20: Merged on Nov 07, 2025 18:05:22
A21: Isaiah | B21: Joyner | C21: 24244 | D21: ijjoyner@unc.edu | E21: i.joyner023@gmail.com | F21: Personal email | G21: =IF(F21="College/Secondary email:",D21,E21) -> i.joyner023@gmail.com | H21: Asheville | I21: Analyst | J21: 8284421521 | K21: Male | L21: Fall 2024 | M21: 2027 | N21: North America | O21: N/A | P21: Yes | Q21: International Investments LLC | R21: Raleigh, NC | S21: Investment Management | T21: N/A | U21: N/A | V21: Unc Management Company | W21: Chapel Hill, NC | X21: Endowment Management | Y21: 2 | Z21: N/A | AA21: N/A | AB21: N/A | AC21: N/A | AD21: N/A | AE21: N/A | AF21: N/A | AG21: University of North Carolina at Chapel Hill | AH21: Chapel Hill | AI21: Non-target | AJ21: 3.63 | AK21: Business Admin(Finance) | AL21: 2027 | AM21: MLT, SEO | AN21: https://drive.google.com/open?id=1cc79unHY2I3HtGKSyqYgAcrb4LjPGcbn | AO21: Investment Banking, Private Equity, Asset Management, Venture Capital, Hedge Funds | AP21: BB Investment Banks, Asset managers, Hedge Funds | AQ21: I’m interested in banking or fundamental type investing jobs. | AS21: Analyst | AT21: Merged on Nov 07, 2025 18:05:23
A22: Makenzie | B22: Swann | C22: BLK-23181 | D22: mswann@email.sc.edu | E22: makenzieswann623@gmail.com | F22: Personal email | G22: =IF(F22="College/Secondary email:",D22,E22) -> makenzieswann623@gmail.com | H22: Rock Hill, SC | I22: Analyst | J22: 19088213315 | K22: Female | L22: Fall 2023 | M22: 2026 | N22: North America | O22: N/A | P22: Yes | Q22: N/A | R22: N/A | S22: N/A | T22: N/A | U22: N/A | V22: KPMG | W22: New York City, NY | X22: Financial Services | Y22: 2 | Z22: The 2nd company waited too long to give out offers | AA22: PwC | AB22: New York City, NY | AC22: M&A | AD22: 3 | AE22: PwC had the most potential for growth and increased personal interest | AF22: N/A | AG22: University of South Carolina | AH22: Columbia, SC | AI22: Public Flagship University | AJ22: 3.5 | AK22: Accounting, Finance, Biz Analytics | AL22: 2026 | AM22: none | AN22: https://drive.google.com/open?id=1vsKwDCx3ofiCCcsXooF8InXXwWPQSv-H | AO22: Asset Management, Management Consulting, Business & Entreprenuership, Technology | AP22: N/A | AQ22: N/A | AS22: Analyst | AT22: Merged on Nov 07, 2025 18:05:27
A23: Kai | B23: Antoine | C23: BLK - 24245 | D23: kantoine@uwo.ca | E23: kaiantoiner@gmail.com | F23: Personal email | G23: =IF(F23="College/Secondary email:",D23,E23) -> kaiantoiner@gmail.com | H23: Oakville, Ontario | I23: Analyst | J23: +19054664419 | K23: Male | L23: Fall 2024 | M23: 2027 | N23: North America | O23: N/A | P23: Yes | Q23: One Queen Capital Inc. | R23: Toronto, Ontario | S23: Private Equity | T23: n/a | U23: n/a | V23: One Queen Capital Inc. | W23: Toronto, Ontario | X23: Private Equity | Y23: n/a | Z23: n/a | AA23: n/a | AB23: n/a | AC23: n/a | AD23: n/a | AE23: n/a | AF23: n/a | AG23: Western University | AH23: London, Ontario | AI23: Non-target | AJ23: 3.7 | AK23: Economics | AL23: 2027 | AM23: n/a | AN23: https://drive.google.com/open?id=17n1v7X9Lkvt-zjfsdZTB_Bcfc4QsRZao | AO23: Investment Banking, Sales and Trading, Private Equity, Asset Management, Venture Capital, Business & Entreprenuership | AP23: Warburg Pincus, Sixth Street Partners, Evercore, Lazard, Carlyle | AQ23: I'm passionate about investing and facilitating investments in innovation and backing businesses that are shaping the future. I'm especially interested in how thoughtful capital allocation can accelerate growth, drive operational excellence, and create lasting impact. Whether through advising companies or directly investing in them, I’m drawn to opportunities where analysis and strategic thinking can help unlock long-term value. | AS23: Analyst | AT23: Merged on Nov 07, 2025 18:05:27
A24: Kosi | B24: Udochukwu | C24: BLK - 22311 | D24: N/A | E24: kosiudochukwu@gmail.com | F24: Personal email | G24: =IF(F24="College/Secondary email:",D24,E24) -> kosiudochukwu@gmail.com | H24: Lagos | I24: Analyst | J24: +14709207034 | K24: Male | L24: Spring 2022 | M24: 2025 | N24: North America | O24: Atlanta (U.S.) | P24: Yes | Q24: N/A | R24: N/A | S24: N/A | T24: N/A | U24: N/A | V24: PricewaterhouseCoopers | W24: Atlanta, GA | X24: Start Internship | Y24: N/A | Z24: N/A | AA24: Advisory | AB24: Washington, D.C | AC24: Advisory | AD24: 1 | AE24: Money wasn't enough for Palo Alto | AF24: PricewaterhouseCoopers | AG24: Emory University | AH24: Atlanta, Georgia | AI24: Semi-Target | AJ24: 3.7 | AK24: Finance and Organization & Management | AL24: 2025 | AM24: SEO, INROADS, Project Destined | AN24: https://drive.google.com/open?id=1cXfIB4Mhx1849VcyS0Rbfg5EgXZ9bhr3 | AO24: Sales and Trading, Asset Management, Management Consulting, Business & Entreprenuership, Technology, Real Estate, Legal, Risk & Compliance | AP24: Wells Fargo, Brigade Capital, Bain Capital, Aristeia Capital, Acadian Asset Management. | AQ24: I am interested in risk, entrepreneurship, consulting, asset management, and financial markets. | AS24: Alumni (only select if you are graduated/graduating this year) | AT24: Merged on Nov 07, 2025 18:05:29
A25: Mariam | B25: Abisoye | C25: BLK-23367 | D25: maabisoye04@my.fisk.edu | E25: mariamabisoye3@gmail.com | F25: Personal email | G25: =IF(F25="College/Secondary email:",D25,E25) -> mariamabisoye3@gmail.com | H25: Nashville | I25: Roark fellow | J25: +1 | K25: Female | L25: Spring 2023 | M25: 2027 | N25: North America | O25: N/A | P25: Yes | Q25: Deloitte | R25: Houston, TX | S25: Accounting | T25: 1 | U25: N/A | V25: Morgan Stanley | W25: New York, NY | X25: Global Capital Markets | Y25: N/A | Z25: N/A | AA25: N/A | AB25: N/A | AC25: N/A | AD25: N/A | AE25: N/A | AF25: N/A | AG25: Fisk University | AH25: Nashville | AI25: Liberal Arts College, Non-Target School | AJ25: 3.88/4.0 | AK25: Business Administration (Financial Economics) & Data Science | AL25: 2027 | AM25: N/A | AN25: https://drive.google.com/open?id=1s6LsxOPZaEv7JcCLtutkb1R1F9KbE5pp | AO25: Management Consulting | AP25: No preference | AS25: Analyst | AT25: Merged on Nov 07, 2025 18:05:30
A26: Nicole | B26: Ogunlaja | C26: BLK - 23328 | D26: no349@bath.ac.uk | E26: nicoleogu@icloud.com | F26: Personal email | G26: =IF(F26="College/Secondary email:",D26,E26) -> nicoleogu@icloud.com | H26: London | I26: Trainee Analyst | J26: +447415169864 | K26: Female | L26: Spring 2024 | M26: 2027 | N26: EMEA | O26: London (EMEA) | P26: Yes | Q26: Alma Strategic Communications | R26: London | S26: Financial Communications PR | T26: 1 | U26: N/A | V26: N/A | W26: N/A | X26: N/A | Y26: N/A | Z26: N/A | AA26: N/A | AB26: N/A | AC26: N.A | AD26: N/A | AE26: N/A | AF26: N/A | AG26: University of Bath | AH26: Bath | AI26: Non - Russel Group | AJ26: First Class | AK26: International Development with Economics | AL26: 2027 | AM26: SEO | AN26: https://drive.google.com/open?id=12p7No97xJZ8wNsX9cRlitD9fuOwvH5Wc | AO26: Sales and Trading, Private Equity, Asset Management | AP26: Advent, Barings, Jane Street | AS26: Community Member | AT26: Merged on Nov 07, 2025 18:05:32
A27: Chidubem | B27: Eneanya | C27: BLK - 22304 | D27: tud52483@temple.edu | E27: dubieneanya@gmail.com | F27: Personal email | G27: =IF(F27="College/Secondary email:",D27,E27) -> dubieneanya@gmail.com | H27: Philadelphia | I27: Analyst | J27: +12673984860 | K27: Male | L27: Fall 2022 | M27: 2025 | N27: North America | O27: Philadelphia (U.S.) | P27: Yes | Q27: N/A | R27: N/A | S27: N/A | T27: N/A | U27: N/A | V27: N/A | W27: N/A | X27: N/A | Y27: N/A | Z27: N/A | AA27: N/A | AB27: N/A | AC27: N/A | AD27: N/A | AE27: N/A | AF27: N/A | AG27: Lewis Katz School of Medicine at Temple University | AH27: Philadelphia | AI27: Non-target | AJ27: 3.36 | AK27: Biomedical Sciences / Neuroscience | AL27: 2025 | AM27: N/A | AN27: https://drive.google.com/open?id=1FCPViZHE_Vie8qq3USbQfCJldcAAtTWm | AO27: Hedge Funds, Equity Research | AP27: N/A | AQ27: N/A | AS27: Alumni (only select if you are graduated/graduating this year) | AT27: Merged on Nov 07, 2025 18:05:34
A28: Clay | B28: Griffin | C28: BLK - 24227 | D28: clayg@smu.edu | E28: claygriffin01@gmail.com | F28: Personal email | G28: =IF(F28="College/Secondary email:",D28,E28) -> claygriffin01@gmail.com | H28: Cos Cob | I28: Analyst | J28: +19173273292 | K28: Male | L28: Fall 2024 | M28: 2026 | N28: North America | O28: New York City (U.S.) | P28: Yes | Q28: Bank of America Merrill Lynch | R28: New York, NY | S28: Wealth Management | T28: 1 | U28: N/A | V28: Bank of America Merrill Lynch | W28: New York, NY | X28: Wealth Management | Y28: 1 | Z28: N/A | AA28: Fortress Investment Group | AB28: New York, NY | AC28: Private Equity and Credit | AD28: 1 | AE28: N/A | AF28: N/A | AG28: Southern Methodist University | AH28: Dallas | AI28: Non-target | AJ28: 3.59 | AK28: Financial Economics | AL28: 2026 | AM28: SEO | AN28: https://drive.google.com/open?id=1_DOcoO8FeK9BFZSrDhwMlCx3MSo_1eui | AO28: Investment Banking, Private Equity, Venture Capital, Hedge Funds | AP28: All Partners | AS28: Analyst | AT28: Merged on Nov 07, 2025 18:05:35
A29: Marieme | B29: N'Diaye | C29: 24106 | D29: msn2157@barnard.edu | E29: mariemesndiaye5@gmail.com | F29: College/Secondary email: | G29: =IF(F29="College/Secondary email:",D29,E29) -> msn2157@barnard.edu | H29: Weehawken | I29: Analyst | J29: 9178224037 | K29: Female | L29: Fall 2024 | M29: 2027 | N29: North America | O29: New York City (U.S.) | P29: Yes | Q29: N/A | R29: N/A | S29: N/A | T29: N/A | U29: N/A | V29: Casey Family Programs | W29: New York City, NY | X29: Investment Management | Y29: 2 | Z29: Location | AA29: JP Morgan ( Incoming 2026) | AB29: NYC | AC29: Equity Research | AD29: 3 | AE29: Job role | AF29: .N/A | AG29: Barnard College of Columbia University | AH29: NYC, NY | AI29: Target | AJ29: 3.6 | AK29: Economics | AL29: 2027 | AM29: Girls Who Invest | AN29: https://drive.google.com/open?id=1AKBxBz1s0gA3OGQ8BH5XVeI1XotiE-mS | AO29: Sales and Trading, Asset Management, Research | AP29: JPM, Goldman, UBS | AS29: Analyst | AT29: Merged on Nov 07, 2025 18:05:37
A30: Jordan | B30: During | C30: BLK - 24109 | D30: jcd99@pitt.edu | E30: jduring2022@gmail.com | F30: Personal email | G30: =IF(F30="College/Secondary email:",D30,E30) -> jduring2022@gmail.com | H30: Houston | I30: Analyst | J30: +18322127272 | K30: Male | L30: Fall 2024 | M30: 2026 | N30: North America | O30: N/A | P30: Yes | Q30: Connors Group | R30: Pittsburgh, PA | S30: Consulting | T30: 6 | U30: Consulting included paid travel and per diem all summer | V30: Accenture Strategy | W30: Houston | X30: Consulting | Y30: 5 | Z30: Not equivalent pay or opportunity to practice strategy | AA30: Bain & Co | AB30: Houston | AC30: consulting | AD30: 2 | AE30: Opportunity was not positioned as well for career growth | AF30: NA | AG30: University of Pittsburgh | AH30: Pittsburgh | AI30: Non-target | AJ30: 3.6 | AK30: Industrial Engineering | AL30: 2026 | AM30: MLT, INROADS | AN30: https://drive.google.com/open?id=1ostY7whu4h_FDopRCeEo9Y5V0V6tRm3M | AO30: Private Equity, Management Consulting, Venture Capital, Business & Entreprenuership, Technology | AP30: Moelis & Company, Bain Capital | AQ30: PE, VC, Climatech INvesting, Infrastructure Investing | AS30: Analyst | AT30: Merged on Nov 07, 2025 18:05:38
A31: Darius | B31: Ephrem | C31: BLK - 24203 | D31: darius.ephrem@durham.ac.uk | E31: Darius4ephrem@gmail.com | F31: Personal email | G31: =IF(F31="College/Secondary email:",D31,E31) -> Darius4ephrem@gmail.com | H31: London, England | I31: Analyst | J31: +447899136264 | K31: Male | L31: Fall 2024 | M31: 2026 | N31: EMEA | O31: N/A | P31: No | Q31: Saunders Street Capital | R31: New York, New York | S31: Private Equity/Search Fund | T31: 1 | U31: N/A | V31: J.P. Morgan | W31: London, England | X31: Investment Banking | Y31: 1 | Z31: N/A | AA31: N/A | AB31: N/A | AC31: N/A | AD31: N/A | AE31: N/A | AF31: N/A | AG31: Durham University | AH31: Durham, England | AI31: Semi-Target | AJ31: First (1:1) | AK31: Finance | AL31: 2026 | AM31: SEO (EMEA), Rare Recruitment | AN31: https://drive.google.com/open?id=1oXAhLs9fdc5J3dkaxehnQT1cVvbt4I8r | AO31: Investment Banking, Private Equity, Asset Management, Management Consulting, Venture Capital, Hedge Funds, Business & Entreprenuership, Real Estate | AS31: Analyst | AT31: Merged on Nov 07, 2025 18:05:40
A32: Abi | B32: Debebe | C32: BLK - 24226 | D32: abidebe@wharton.upenn.edu | E32: abidebebe1@gmail.com | F32: College/Secondary email: | G32: =IF(F32="College/Secondary email:",D32,E32) -> abidebe@wharton.upenn.edu | H32: Atlanta, GA | I32: Trainee Analyst | J32: 14709891067 | K32: Female | L32: Fall 2024 | M32: 2027 | N32: North America | O32: Philadelphia (U.S.) | P32: Yes | Q32: Citadel and Citadel Securities | R32: New York, NY | S32: Hedge Fund | T32: 1 | U32: n/a | V32: Penn Office of Investments | W32: Philadelphia, PA | X32: Investment Management | Y32: 1 | Z32: n/a | AA32: UBS | AB32: New York, NY | AC32: Investment Banking | AD32: 1 | AE32: n/a | AF32: n/a | AG32: University of Pennsylvania | AH32: Philadelphia | AI32: Target | AJ32: 3.64 | AK32: Economics and International Studies | AL32: 2027 | AM32: SEO, Girls Who Invest | AN32: https://drive.google.com/open?id=1UiqYu23GSUMoalNw4dRUyLtsp6yJP_bO | AO32: Investment Banking, Private Equity, Hedge Funds, Business & Entreprenuership, Legal, Risk & Compliance | AP32: UBS | AS32: Community Member | AT32: Merged on Nov 07, 2025 18:05:45
A33: Quentin | B33: Wei-Henrys | C33: BLK - 24163 | D33: q.w.wei-henrys@wustl.edu | E33: quentinweihenrys@gmail.com | F33: Personal email | G33: =IF(F33="College/Secondary email:",D33,E33) -> quentinweihenrys@gmail.com | H33: Oak Park, IL | I33: Analyst | J33: +17086163706 | K33: Male | L33: Fall 2024 | M33: 2027 | N33: North America | O33: N/A | P33: Yes | Q33: Thirty-5 Capital | R33: Chicago, IL | S33: Private Equity & Venture Capital | T33: 1 | U33: N/A | V33: N/A | W33: N/A | X33: N/A | Y33: N/A | Z33: N/A | AA33: Jefferies (Incoming for 2026) | AB33: New York, NY | AC33: Investment Banking | AD33: 2 | AE33: I received my offer at Jefferies before the other one. | AF33: N/A | AG33: Washington University in St. Louis | AH33: St. Louis, MO | AI33: Semi-Target | AJ33: 3.79 | AK33: Finance | AL33: 2027 | AM33: SEO | AN33: https://drive.google.com/open?id=1PYv67EjFLXyN-0UN0cV6Wm2oP2vpWUah | AO33: Investment Banking, Private Equity, Venture Capital | AP33: N/A | AS33: Community Member | AT33: Merged on Nov 07, 2025 18:05:46
A34: Judah | B34: Fakile | C34: BLK - 24100 | D34: jmf200@cam.ac.uk | E34: judahm.fakile@gmail.com | F34: Personal email | G34: =IF(F34="College/Secondary email:",D34,E34) -> judahm.fakile@gmail.com | H34: Cambridge | I34: Analyst | J34: +447914669588 | K34: Male | L34: Fall 2024 | M34: 2027 | N34: EMEA | O34: London (EMEA) | P34: With authorisations | Q34: N/A | R34: N/A | S34: N/A | T34: N/A | U34: N/A | V34: N/A | W34: N/A | X34: N/A | Y34: N/A | Z34: N/A | AA34: N/A | AB34: N/A | AC34: N/A | AD34: N/A | AE34: N/A | AF34: N/A | AG34: University of Cambridge | AH34: Cambridge | AI34: Target | AJ34: 4 | AK34: Economics | AL34: 2027 | AM34: SEO (EMEA), UpReach, Rare Recruitment | AN34: https://drive.google.com/open?id=1QspDR84xl0uvIDXDb0DxD5j4DxX9arcQ | AO34: Investment Banking, Private Equity, Asset Management, Quantitative Finance (eg. Quant Trading), Management Consulting, Venture Capital, Hedge Funds | AP34: Advent, Alpine, DE Shaw, Arsenal Capital, Bain Capital, Jane Street, Roark, | AQ34: Interested in finding a first year summer in the space of PE, Growth Equity or VC before securing a second year summer to create an easier exit opportunity. | AS34: Education Pathways (IB, AWM, or PE) | AT34: Merged on Nov 07, 2025 18:05:48
A35: Binham | B35: Seyoum | C35: BLK - 24017 | D35: binham.seyoum@student.manchester.ac.uk | E35: binham90210@gmail.com | F35: Personal email | G35: =IF(F35="College/Secondary email:",D35,E35) -> binham90210@gmail.com | H35: Manchester | I35: Analyst | J35: +447591977610 | K35: Male | L35: Fall 2023 | M35: 2025 | N35: EMEA | O35: London (EMEA) | P35: Yes | Q35: Bank of America | R35: Chester, England | S35: Investment Bank | T35: N/A | U35: N/A | V35: Freshfields | W35: London, England | X35: Law firm | Y35: N/A | Z35: N/A | AA35: N/A | AB35: N/A | AC35: N/A | AD35: N/A | AE35: N/A | AF35: N/A | AG35: University of Manchester | AH35: Manchester | AI35: Non-target | AJ35: 2.1 | AK35: Biomedical Science | AL35: 2025 | AM35: SEO, SEO (EMEA), UpReach | AN35: https://drive.google.com/open?id=1Y9dG3Y-IrrKpHAM-2bpJnORLcgFGVHkp | AO35: Investment Banking, Sales and Trading, Asset Management, Management Consulting, Hedge Funds, Business & Entreprenuership, Real Estate, Legal, Risk & Compliance, HR | AP35: PGIM | AS35: Analyst | AT35: Merged on Nov 07, 2025 18:05:49
A36: Denzel | B36: Louis | C36: BLK-24197 | D36: louis523@student.fus.edu | E36: denzlouis04@icloud.com | F36: Personal email | G36: =IF(F36="College/Secondary email:",D36,E36) -> denzlouis04@icloud.com | H36: Miami, FL | I36: Analyst | J36: +19548160641 | K36: Male | L36: Fall 2024 | M36: 2026 | N36: EMEA | O36: N/A | P36: Yes | Q36: N/A | R36: N/A | S36: N/A | T36: N/A | U36: N/A | V36: Green Children's House Montessori School | W36: Pompano Beach, FL | X36: Business development | Y36: 1 | Z36: Northwestern mutual, didnt believe it to be reputable and took the SIE instead. | AA36: Decision is released by end of week | AB36: NY,NY | AC36: IB | AD36: N/A | AE36: N/A | AF36: N/A | AG36: Franklin University of Switzerland | AH36: Lugano, Switzerland | AI36: Liberal Arts College, Non-Target School | AJ36: 3.3/4 | AK36: Finance | AL36: 2026 | AM36: Project Destined | AN36: https://drive.google.com/open?id=14zMaY65Je9nYpaEu_P0HV0_XEL0eQYcq | AO36: Investment Banking, Private Equity, Asset Management, Management Consulting, Venture Capital, Hedge Funds, Business & Entreprenuership | AP36: Black owned investment banks | AS36: Analyst | AT36: Merged on Nov 07, 2025 18:05:50
A37: Uwa | B37: Osagie | C37: BLK - 24164 | D37: uo1g24@soton.ac.uk | E37: uwa.osagie@aol.co.uk | F37: Personal email | G37: =IF(F37="College/Secondary email:",D37,E37) -> uwa.osagie@aol.co.uk | H37: Birmingham | I37: Analyst | J37: +447449770706 | K37: Male | L37: Fall 2024 | M37: 2027 | N37: EMEA | O37: London (EMEA) | P37: Yes | Q37: N/A | R37: N/A | S37: N/A | T37: N/A | U37: N/A | V37: N/A | W37: N/A | X37: N/A | Y37: N/A | Z37: N/A | AA37: N/A | AB37: N/A | AC37: N/A | AD37: N/A | AE37: N/A | AF37: N/A | AG37: University of Southampton | AH37: Southampton | AI37: Russel group | AJ37: 1st | AK37: Electrical & Electronic Engineering | AL37: 2027 | AM37: SEO, Rare Recruitment | AN37: https://drive.google.com/open?id=1XQSt06WZNnrNNseHRWyHwLjSJuHQQumy | AO37: Investment Banking, Sales and Trading, Private Equity, Asset Management, Quantitative Finance (eg. Quant Trading), Hedge Funds, Technology | AP37: Jane street / JP Morgan / RBC | AQ37: I’d like to go into quant trading because of my maths background but if any asset management or private equities roles are available I’d love to gain experience there aswell. | AR37: N/A | AS37: Analyst | AT37: Merged on Nov 07, 2025 18:05:52
A38: Temilade | B38: Onile | C38: BLK-23433 | D38: onile@bc.edu | E38: temilade.onile@gmail.com | F38: Personal email | G38: =IF(F38="College/Secondary email:",D38,E38) -> temilade.onile@gmail.com | H38: Norwood, MA | I38: Analyst | J38: +13392056711 | K38: Female | L38: Spring 2024 | M38: 2026 | N38: North America | O38: Boston (U.S.) | P38: Yes | Q38: MA State Treasury | R38: Boston, MA | S38: Audit | T38: NA | U38: NA | V38: NA | W38: NA | X38: NA | Y38: NA | Z38: NA | AA38: Brown Advisory | AB38: Boston, MA | AC38: Wealth management | AD38: NA | AE38: NA | AF38: NA | AG38: Boston College | AH38: Chestnut Hill, MA | AI38: Target | AJ38: 3.431 | AK38: Finance and International Studies | AL38: 2026 | AM38: MLT | AN38: https://drive.google.com/open?id=1ELvI0E21WPkOrQ8R47PG6kHSRZ8xcRwJ | AO38: Asset Management, Wealth management | AP38: Alliance Bernstein | AS38: Analyst | AT38: Merged on Nov 07, 2025 18:05:53
A39: Joshua | B39: Johnson | C39: BLK - 2334 | D39: jaj4775@utexas.edu | E39: joshua4222@gmail.com | F39: College/Secondary email: | G39: =IF(F39="College/Secondary email:",D39,E39) -> jaj4775@utexas.edu | H39: Houston | I39: Analyst | J39: 8325896723 | K39: Male | L39: Fall 2023 | M39: 2026 | N39: North America | O39: N/A | P39: Yes | Q39: Forte Capital | R39: New York, NY | S39: PE Fundraising | T39: N/A | U39: N/A | V39: JPM | W39: NY, NY | X39: IB | Y39: 1 | Z39: Took another offer | AA39: PWP | AB39: NY | AC39: IB | AD39: TBD | AE39: TBD | AF39: Still in process | AG39: UT Austin | AH39: Austin | AI39: Semi-Target | AJ39: 3.6 | AK39: Finance | AL39: 2026 | AM39: MLT, SEO, Project Destined | AN39: https://drive.google.com/open?id=1JpyzxJTcCmotsZr6Vvmg4jAVShu_WMZe | AO39: Investment Banking, Private Equity, Hedge Funds | AP39: Jane Street, Centerview, KKR, Blackstone, Raine Group, Vista Equity | AQ39: I am interested in lateraling into Media PE or a L/S HF after my banking tenure. I specifically am interested in the media and entertainment space and can see my self working in the industry for the rest of my life. I have been fortunate to meet a bunch of people from some of the top firms such as WME and CAA, and being able to work as an advisor or investor with these companies or companies a like would be a dream come true. | AR39: BLK Conference December 2023, conn | AS39: Analyst | AT39: Merged on Nov 07, 2025 18:05:55
A40: Toni | B40: Akinola | C40: BLK-24168 | D40: leyoa11@nottingham.ac.uk | E40: akinolaoluwatoni@gmail.com | F40: Personal email | G40: =IF(F40="College/Secondary email:",D40,E40) -> akinolaoluwatoni@gmail.com | H40: Toronto | I40: Analyst | J40: +447498314886 | K40: Female | L40: Fall 2024 | M40: 2025 | N40: EMEA | O40: London (EMEA) | P40: Yes | Q40: N/A | R40: N/A | S40: N/A | T40: N/A | U40: N/A | V40: Shell | W40: London, UK | X40: Oil and gas | Y40: 1 | Z40: N/A | AA40: N/A | AB40: N/A | AC40: N/A | AD40: N/A | AE40: N/A | AF40: N/A | AG40: University of Nottingham | AH40: Nottingham | AI40: Non-target | AJ40: N/A | AK40: Economics | AL40: 2025 | AM40: Girls Who Invest | AN40: https://drive.google.com/open?id=1-5aaeyAaahwIVU9x9hqjf3PUcDFR6eIA | AO40: Sales and Trading, Private Equity, Asset Management, Quantitative Finance (eg. Quant Trading), Management Consulting, Hedge Funds, Technology | AP40: Morgan Stanley, TD Securities, Goldman Sachs, JP Morgan, Blackrock | AS40: Alumni (only select if you are graduated/graduating this year) | AT40: Merged on Nov 07, 2025 18:05:56
A41: Langston | B41: Minor | C41: N/A | D41: minorl@vcu.edu | E41: airlegend010804@gmail.com | F41: College/Secondary email: | G41: =IF(F41="College/Secondary email:",D41,E41) -> minorl@vcu.edu | H41: Richmond | I41: Trainee Analyst | J41: +18048320725 | K41: Male | L41: Fall 2024 | M41: 2026 | N41: North America | O41: N/A | P41: Yes | Q41: Lincoln Investment | R41: Richmond, VA | S41: Financial Services | T41: 2 | U41: N/A | V41: LISC | W41: Richmond, VA | X41: Financial Services | Y41: 2 | Z41: N/A | AA41: N/A | AB41: N/A | AC41: N/A | AD41: N/A | AE41: N/A | AF41: N/A | AG41: Virginia Commonwealth University | AH41: Richmond, VA | AI41: Non-target | AJ41: 3.2 | AK41: Finance | AL41: 2026 | AM41: MLT, INROADS | AN41: https://drive.google.com/open?id=1goeFpZJZRxxANhEFeZe1m9VyvPOMZSq3 | AO41: Investment Banking, Sales and Trading, Private Equity, Asset Management, Quantitative Finance (eg. Quant Trading), Management Consulting, Venture Capital, Hedge Funds, Business & Entreprenuership | AP41: all | AS41: Analyst | AT41: Merged on Nov 07, 2025 18:05:58
A42: Cristopher | B42: Ramirez | C42: BLK - 24157 | D42: Crisramirez@college.harvard.edu | E42: crismrr30@gmail.com | F42: College/Secondary email: | G42: =IF(F42="College/Secondary email:",D42,E42) -> Crisramirez@college.harvard.edu | H42: Queens, NY | I42: Analyst | J42: +19294349059 | K42: Male | L42: Fall 2024 | M42: 2028 | N42: North America | O42: Boston (U.S.) | P42: Yes | Q42: N/A | R42: N/A | S42: N/A | T42: N/A | U42: N/A | V42: N/A | W42: N/A | X42: N/A | Y42: N/A | Z42: N/A | AA42: N/A | AB42: N/A | AC42: N/A | AD42: N/A | AE42: N/A | AF42: N/A | AG42: Harvard College | AH42: Cambridge | AI42: Target | AJ42: 3.9 | AK42: Economics & Philosophy | AL42: 2028 | AM42: SEO | AN42: https://drive.google.com/open?id=1hFr5R1o8AabW93BHoTV8k0oPqyEQ7Z8w | AO42: Investment Banking, Private Equity, Hedge Funds | AP42: Alpine, Evercore, Goldman Sachs, J.P. Morgan, KKR, Lazard, Morgan Stanley, Roark, 6th Street Partners, Warburg Pincus | AS42: Analyst | AT42: Merged on Nov 07, 2025 18:06:01
A43: Immanuel | B43: Dange | C43: BLK - 24167 | D43: immanuel.dange@torontomu.ca | E43: immanueldange@gmail.com | F43: Personal email | G43: =IF(F43="College/Secondary email:",D43,E43) -> immanueldange@gmail.com | H43: Toronto | I43: Analyst | J43: +16475616054 | K43: Male | L43: Spring 2024 | M43: 2028 | N43: North America | O43: Toronto (Canada) | P43: No | Q43: N/A | R43: N/A | S43: N/A | T43: N/A | U43: N/A | V43: N/A | W43: N/A | X43: N/A | Y43: N/A | Z43: N/A | AA43: N/A | AB43: N/A | AC43: N/A | AD43: N/A | AE43: N/A | AF43: N/A | AG43: Toronto Metropolitan University | AH43: Toronto | AI43: Non-target | AJ43: 3.5 | AK43: Business Administration | AL43: 2028 | AM43: N/A | AN43: https://drive.google.com/open?id=1wPSbBuTbI6vDb--DUHYhc1qRDnlYKyTk | AO43: Investment Banking, Private Equity, Quantitative Finance (eg. Quant Trading), Business & Entreprenuership, Technology, Real Estate, HR | AP43: JPMorgan Chase, TD, RBC, Deloitte. | AR43: N/A | AS43: Analyst | AT43: Merged on Nov 07, 2025 18:06:02
A44: Fered | B44: Yousuf | C44: BLK - 23222 | D44: fyousuf2@illinois.edu | E44: feredyousuf14@icloud.com | F44: College/Secondary email: | G44: =IF(F44="College/Secondary email:",D44,E44) -> fyousuf2@illinois.edu | H44: Matteson, IL | I44: Roark fellow | J44: +17738181121 | K44: Male | L44: Fall 2023 | M44: 2027 | N44: North America | O44: N/A | P44: Yes | Q44: Charles Schwab | R44: Chicago, IL | S44: Asset Management | T44: 1 | U44: N/A | V44: Wells Fargo | W44: New York, NY | X44: Investment Banking | Y44: 2 | Z44: N/A | AA44: N/A | AB44: N/A | AC44: N/A | AD44: N/A | AE44: N/A | AF44: N/A | AG44: University of Illinois at Urbana-Champaign | AH44: Champaign | AI44: Public Flagship University | AJ44: 4 | AK44: Finance & Accounting | AL44: 2027 | AM44: MLT, SEO | AN44: https://drive.google.com/open?id=1ZOhirEyRC1NeZyo1OVbTyaJG_XGhjrhY | AO44: Investment Banking, Private Equity, Venture Capital, Hedge Funds | AP44: J.P Morgan | AS44: Community Member | AT44: Merged on Nov 07, 2025 18:06:03
A45: Arashi | B45: Hunter | C45: 24096 | D45: N/A, not currently in university | E45: Keithahunter5@gmail.com | F45: Personal email | G45: =IF(F45="College/Secondary email:",D45,E45) -> Keithahunter5@gmail.com | H45: Seattle | I45: Analyst | J45: +12069602351 | K45: Male | L45: Fall 2024 | M45: 2029 | N45: North America | O45: Boston (U.S.) | P45: Yes | Q45: N?A | R45: N/A | S45: N/A | T45: N/A | U45: N/A | V45: N/A | W45: N/A | X45: N/A | Y45: N/A | Z45: N/A | AA45: N/A | AB45: N/A | AC45: N/A | AD45: N/A | AE45: N/A | AF45: N/A | AG45: Harvard College | AH45: Cambridge | AI45: Target | AJ45: N/A | AK45: Economics | AL45: 2029 | AM45: N/A | AN45: https://drive.google.com/open?id=1mXNz0Gzx5YKWECxgQBX2JqKJZtpVJ9Ed | AO45: Investment Banking, Private Equity, Asset Management, Hedge Funds | AP45: UBS, Wolfe Research, KKR, Goldman Sachs, JP Morgan, Warburg Pincus | AQ45: I am interested in pursuing a career either within equity research, asset management, or investment banking. I am interested in equity research due to it being such a detail oriented career option. Asset management also draws me due to also requiring strategy for investments while also having a social aspect as it requires connection with clients. Finally, I am attracted to investment banking as it requires team collaboration to advise on financial transactions. | AR45: The calls with KKR and Warburg Pincus have been especially insightful. | AS45: Analyst | AT45: Merged on Nov 07, 2025 18:06:04
A46: Omoyemi | B46: Fayemi | C46: BLK-24099 | D46: liyof5@nottingham.ac.uk | E46: yfayemi29@gmail.com | F46: Personal email | G46: =IF(F46="College/Secondary email:",D46,E46) -> yfayemi29@gmail.com | H46: Purfleet | I46: Analyst | J46: +447939403335 | K46: Male | L46: Fall 2024 | M46: 2026 | N46: EMEA | O46: N/A | P46: No | Q46: Level2 | R46: London, UK | S46: Quantitative Research/Trading | T46: 1 | U46: N/A | V46: N/A | W46: N/A | X46: N/A | Y46: N/A | Z46: N/A | AA46: N/A | AB46: N/A | AC46: N/A | AD46: N/A | AE46: N/A | AF46: N/A | AG46: University of Nottingham | AH46: Nottingham | AI46: Target | AJ46: 1:1 | AK46: Finance, Accounting And Management | AL46: 2026 | AM46: SEO (EMEA), UpReach | AN46: https://drive.google.com/open?id=1mH4iNv85t1fJnIrechVblzU7GqitKYD_ | AO46: Investment Banking, Private Equity, Asset Management | AP46: Rothschild & Co interests me the most. | AS46: Analyst | AT46: Merged on Nov 07, 2025 18:06:05
A47: Dipo | B47: Adedeji | C47: BLK - 24173 | D47: maa422@student.bham.ac.uk | E47: dipoadedeji@live.co.uk | F47: Personal email | G47: =IF(F47="College/Secondary email:",D47,E47) -> dipoadedeji@live.co.uk | H47: London | I47: Analyst | J47: +447375465243 | K47: Male | L47: Fall 2024 | M47: 2027 | N47: EMEA | O47: London (EMEA) | P47: Yes | Q47: JP Morgan | R47: London | S47: Sales & trading | T47: N/A | U47: N/A | V47: N/A | W47: N/A | X47: N/A | Y47: N/A | Z47: N/a | AA47: N/a | AB47: N/a | AC47: N/a | AD47: N/a | AE47: N/a | AF47: N/a | AG47: University of Birmingham | AH47: Birmingham | AI47: Target | AJ47: First class | AK47: Economics | AL47: 2027 | AM47: Generating Genius | AN47: https://drive.google.com/open?id=1apeKY7bNjxhF6Nq9-4EhshJr4O3WzJhE | AO47: Investment Banking, Sales and Trading, Private Equity, Asset Management, Management Consulting, Hedge Funds | AP47: JP Morgan, Deutsche Bank, Goldman Sachs | AS47: Education Pathways (IB, AWM, or PE) | AT47: Merged on Nov 07, 2025 18:06:06
A48: Nicole | B48: Tettey | C48: 23426 | D48: nmdt1@st-andrews.ac.uk | E48: tetteynicole@gmail.com | F48: College/Secondary email: | G48: =IF(F48="College/Secondary email:",D48,E48) -> nmdt1@st-andrews.ac.uk | H48: Vienna | I48: Analyst | J48: +447446214091 | K48: Female | L48: Spring 2024 | M48: 2026 | N48: EMEA | O48: N/A | P48: No | Q48: N/A | R48: N/A | S48: N/A | T48: N/A | U48: N/A | V48: N/A | W48: N/A | X48: N/A | Y48: N/A | Z48: N/A | AA48: UBS | AB48: London | AC48: Investment Banking | AD48: 3 | AE48: My other offers were in Big 4 financial services consulting and in wealth management, and I felt that my exit opportunities would be wider in investment banking. | AF48: N/A | AG48: University of St Andrews | AH48: St Andrews | AI48: Non-target | AJ48: 0.75 | AK48: Economics and International Relations | AL48: 2026 | AM48: N/A | AN48: https://drive.google.com/open?id=1vhjT1LHsuLF1qmHF3J_0idz81VH6GnrM | AO48: Investment Banking, Private Equity | AP48: UBS, Goldman Sachs, J. P. Morgan, Morgan Stanley | AR48: London Tour | AS48: Analyst | AT48: Merged on Nov 07, 2025 18:06:07
A49: Ty | B49: Gichina | C49: 24233 | D49: nss23kwu@uea.ac.uk | E49: tygichina@gmail.com | F49: Personal email | G49: =IF(F49="College/Secondary email:",D49,E49) -> tygichina@gmail.com | H49: Milton Keynes | I49: Analyst | J49: +447496687771 | K49: Male | L49: Fall 2024 | M49: 2026 | N49: EMEA | O49: London (EMEA) | P49: Maybe | Q49: HSBC | R49: London | S49: Investment Banking | T49: 1 | U49: N/A | V49: Pending | W49: London | X49: Pending | Y49: Pending | Z49: Pending | AA49: N/A | AB49: N/A | AC49: N/A | AD49: N/A | AE49: N/A | AF49: N/A | AG49: University of East Anglia | AH49: Norwich | AI49: Non-target | AJ49: 2:1 | AK49: Accounting and Finance | AL49: 2026 | AM49: SEO (EMEA), Rare Recruitment | AN49: https://drive.google.com/open?id=1_GEIzMbx-gggKIWNX9kSc6EjeKsdIsbo | AO49: Investment Banking, Sales and Trading, Private Equity, Asset Management, Venture Capital, Hedge Funds | AP49: Goldman Sachs, UBS, Vanguard, J.P. Morgan, Barings, Advent International, Carlyle, DE Shaw, KKR, PWP, Wells Fargo | AQ49: Investment Banking, Sales (Sales & Trading), Private Equity, Private Banking/Wealth Management, Asset Management | AS49: Analyst | AT49: Merged on Nov 07, 2025 18:06:08
A50: Nabiel | B50: Yonas | C50: BLK-24187 | D50: kf24037@bristol.ac.uk | E50: nabielyonas123@icloud.com | F50: Personal email | G50: =IF(F50="College/Secondary email:",D50,E50) -> nabielyonas123@icloud.com | H50: London/Bristol | I50: Analyst | J50: +447376113622 | K50: Male | L50: Fall 2024 | M50: 2027 | N50: EMEA | O50: N/A | P50: No | Q50: N/A | R50: N/A | S50: N/A | T50: N/A | U50: N/A | V50: N/A | W50: N/A | X50: N/A | Y50: N/A | Z50: N/A | AA50: N/A | AB50: N/A | AC50: N/A | AD50: N/A | AE50: N/A | AF50: N/A | AG50: University of Bristol | AH50: Bristol | AI50: Semi-Target | AJ50: 2:1 | AK50: Economics | AL50: 2027 | AM50: SEO (EMEA), UpReach | AN50: https://drive.google.com/open?id=1FgeiLO_-s-zPeoK4vOG0WfXCRZ_TqnGK | AO50: Investment Banking, Sales and Trading, Private Equity, Asset Management, Quantitative Finance (eg. Quant Trading), Venture Capital, Hedge Funds, Business & Entreprenuership, Legal, Risk & Compliance | AP50: EMEA Based | AS50: Education Pathways (IB, AWM, or PE) | AT50: Merged on Nov 07, 2025 18:06:09
A51: Peter | B51: Haile | C51: BLK - 23215 | D51: Queen's University | E51: peterhaile23@gmail.com | F51: Personal email | G51: =IF(F51="College/Secondary email:",D51,E51) -> peterhaile23@gmail.com | H51: Toronto | I51: Senior analyst | J51: +16478046086 | K51: Male | L51: Fall 2023 | M51: 2026 | N51: North America | O51: Toronto (Canada) | P51: Yes | Q51: CIBC | R51: Toronto, Canada | S51: Real Estate Corporate Banking | T51: N/A | U51: N/A | V51: CIBC | W51: Toronto, Canada | X51: Risk Management | Y51: n/a | Z51: N/A | AA51: RBC | AB51: Toronto, Canada | AC51: Investment Banking | AD51: N/A | AE51: N/A | AF51: N/A | AG51: Queen's University | AH51: Kingston | AI51: Target | AJ51: N/A | AK51: Commerce | AL51: 2026 | AM51: N/A | AN51: https://drive.google.com/open?id=1DF0d2BDoDO8kEuFe4D61feyH19zF_xO5 | AO51: Investment Banking | AP51: Alpine, Evercore | AR51: Conference | AS51: Education Pathways (IB, AWM, or PE) | AT51: Merged on Nov 07, 2025 18:06:11
A52: Tia | B52: Turner | C52: 23324 | D52: tia.turner@richmond.edu | E52: litiaturner@gmail.com | F52: College/Secondary email: | G52: =IF(F52="College/Secondary email:",D52,E52) -> tia.turner@richmond.edu | H52: Richmond, VA | I52: Trainee Analyst | J52: 18047188669 | K52: Female | L52: Spring 2024 | M52: 2026 | N52: North America | O52: N/A | P52: Yes | Q52: Dominion Energy | R52: Richmond, VA | S52: Energy | T52: N/A | U52: N/A | V52: Hudson Way Capital Management | W52: Dallas, TX | X52: Hedge Fund | Y52: N/A | Z52: N/A | AA52: Bank of America | AB52: Jersey City, NJ | AC52: Wealth Management | AD52: 3 | AE52: Pay, ideal location, and job description was not ideal | AF52: N/A | AG52: University of Richmond | AH52: Richmond, VA | AI52: Liberal Arts College, Non-Target School | AJ52: 3.1 | AK52: Business Administration | AL52: 2026 | AM52: INROADS, Girls Who Invest | AN52: https://drive.google.com/open?id=1jQ4J0-cgXhYov2CZMcjtcCkCxekHObeI | AO52: Asset Management, Management Consulting, Business & Entreprenuership, HR, Wealth Management | AP52: N/A | AS52: Analyst | AT52: Merged on Nov 07, 2025 18:06:14
A53: Nhyira | B53: Boateng | C53: 24103 | D53: nb716@cam.ac.uk | E53: nhyira0206@gmail.com | F53: Personal email | G53: =IF(F53="College/Secondary email:",D53,E53) -> nhyira0206@gmail.com | H53: Wellingborough | I53: Analyst | J53: +447508624611 | K53: Male | L53: Fall 2024 | M53: 2027 | N53: EMEA | O53: N/A | P53: No | Q53: N/A | R53: N/A | S53: N/A | T53: N/A | U53: N/A | V53: N/A | W53: N/A | X53: N/A | Y53: N/A | Z53: N/A | AA53: N/A | AB53: N/A | AC53: N/A | AD53: N/A | AE53: N/A | AF53: N/A | AG53: University of Cambridge | AH53: Cambridge | AI53: University | AJ53: 3.7 | AK53: N/A | AL53: 2027 | AM53: SEO (EMEA), Rare Recruitment | AN53: https://drive.google.com/open?id=1i4dmCF0YTtPrOV6vXu4rB6qjyzvp93s4 | AO53: Investment Banking, Sales and Trading, Private Equity, Asset Management, Quantitative Finance (eg. Quant Trading), Management Consulting, Business & Entreprenuership, Technology | AP53: JPM Bain BCG McKinsey | AS53: Community Member | AT53: Merged on Nov 07, 2025 18:06:15
A54: Salah | B54: Farouqi | C54: 24206 | D54: Salah_Farouqi@student.uml.edu | E54: salahfarouqi7@gmail.com | F54: Personal email | G54: =IF(F54="College/Secondary email:",D54,E54) -> salahfarouqi7@gmail.com | H54: Melrose, MA | I54: Analyst | J54: 7814753205 | K54: Male | L54: Fall 2024 | M54: 2026 | N54: North America | O54: Boston (U.S.) | P54: Yes | Q54: Inspire Clean Energy & NRG | R54: Field Sales Role(Multiple Territories, MA) | S54: Sales & Trading, Investment Banking | T54: 0 | U54: N/A | V54: MFS Investment Management | W54: Boston, MA | X54: International Sales | Y54: N/A | Z54: N/A | AA54: Fannie Mae (Summer 2025) | AB54: Washington, D.C. | AC54: Financial services | AD54: 2 | AE54: Morgan Stanley offer was for WM with no relocation stipend. | AF54: N/A | AG54: University of Massachusetts Lowell | AH54: Lowell, MA | AI54: Non-target | AJ54: 3.6 | AK54: Finance | AL54: 2026 | AM54: SEO, Project Destined | AN54: https://drive.google.com/open?id=1PooztLna2yYDW6g9_e7gxtYHrdHhZqkW | AO54: Investment Banking, Sales and Trading, Real Estate | AP54: I’m open to any firm where I can learn and contribute meaningfully. That said, I’d be especially interested in firms with strong real estate or investment banking platforms. | AQ54: I’m interested in investment banking, specifically within the REGAL (Real Estate, Gaming, Lodging & Leisure) group. I enjoy the intersection of real assets and finance and would love to be considered for opportunities in this space | AR54: Financeable | AS54: Education Pathways (IB, AWM, or PE) | AT54: Merged on Nov 07, 2025 18:06:17
A55: Bruce | B55: Estivil | C55: BLK - 23070 | D55: psybe1@nottingham.ac.uk | E55: baestivil@gmail.com | F55: Personal email | G55: =IF(F55="College/Secondary email:",D55,E55) -> baestivil@gmail.com | H55: London | I55: Trainee Analyst | J55: +447491021879 | K55: Male | L55: Spring 2023 | M55: 2024 | N55: EMEA | O55: London (EMEA) | P55: Yes | Q55: N/A | R55: N/A | S55: N/A | T55: N/A | U55: N/A | V55: JP Morgan | W55: London, UK | X55: Software Engineering | Y55: N/A | Z55: N/A | AA55: JP Morgan | AB55: London, UK | AC55: Software Engineering | AD55: N/A | AE55: N/A | AF55: Yes | AG55: University of Nottingham | AH55: Nottingham, UK | AI55: EMEA | AJ55: 2:1 (UK system) | AK55: Computer Science | AL55: 2024 | AM55: SEO (EMEA), Rare Recruitment | AN55: https://drive.google.com/open?id=1KARNhj9Mfc9T6kXEeZxNyVNjDCLsqYE3 | AO55: Private Equity, Venture Capital, Hedge Funds | AP55: Alpine Investors BainCapital Jane Street | AQ55: Interested in tech focused growth equity or VC stage investing. A role where sharp understanding of market trends is required, whilst I remain close to & maintain a deep understanding of the tech market in software, hardware, AI or other sub-verticals. | AR55: N/A | AS55: Analyst | AT55: Merged on Nov 07, 2025 18:06:18
A56: Kaitlyn | B56: Gyamfi | C56: BLK - 23396 | D56: gyamfika@bc.edu | E56: kaitlyn.gyamfi1@gmail.com | F56: College/Secondary email: | G56: =IF(F56="College/Secondary email:",D56,E56) -> gyamfika@bc.edu | H56: Brooklyn | I56: Analyst | J56: +17189306196 | K56: Female | L56: Spring 2024 | M56: 2027 | N56: North America | O56: Boston (U.S.) | P56: Yes | Q56: Deloitte | R56: NY, NY | S56: Consulting | T56: 1 | U56: n/a | V56: Deloitte | W56: NY, NY | X56: Consulting | Y56: 1 | Z56: N/A | AA56: N/A | AB56: N/A | AC56: N/A | AD56: N/A | AE56: N/A | AF56: N/A | AG56: Boston College | AH56: Boston | AI56: Liberal Arts College, Non-Target School | AJ56: 3.67 | AK56: Finance | AL56: 2027 | AM56: MLT | AN56: https://drive.google.com/open?id=1avLIo9tH0N4Oals1Mfxkmqv3-b0s3QG8 | AO56: Sales and Trading, Private Equity, Management Consulting | AP56: Citi, MS, Mckinsey | AS56: Analyst | AT56: Merged on Nov 07, 2025 18:06:19
A57: Nelly | B57: Hayford-Jackson | C57: BLK - 23175 | D57: nhayfordjackson@ufl.edu | E57: nellyhayfordj@gmail.com | F57: Personal email | G57: =IF(F57="College/Secondary email:",D57,E57) -> nellyhayfordj@gmail.com | H57: West Palm Beach, FL | I57: Analyst | J57: +15613178862 | K57: Female | L57: Fall 2023 | M57: 2025 | N57: North America | O57: N/A | P57: Yes | Q57: N/A | R57: N/A | S57: N/A | T57: N/A | U57: N/A | V57: J.P. Morgan | W57: Houston, Texas | X57: Corporate Banking | Y57: 2 | Z57: Less opportunity for development | AA57: J.P. Morgan | AB57: Houston, Texas | AC57: Corporate Banking | AD57: 1 | AE57: N/A | AF57: J.P. Morgan | AG57: University of Florida | AH57: Gainesville, FL | AI57: Public Flagship University | AJ57: 3.97 | AK57: Economics | AL57: 2025 | AM57: MLT, SEO | AN57: https://drive.google.com/open?id=1XJh692hIV7nciaz8qfls2BkSMO-MHe_2 | AO57: Corporate Banking | AP57: UBS, Wells Fargo | AQ57: Interested in roles in: Endowments and Foundations Corporate Finance Corporate Development Investment Banking | AS57: Alumni (only select if you are graduated/graduating this year) | AT57: Merged on Nov 07, 2025 18:06:20
A58: Vanessa | B58: Iwuoha | C58: BLK - 22259 | D58: viwuoha@college.harvard.edu | E58: cviwuoha@gmail.com | F58: College/Secondary email: | G58: =IF(F58="College/Secondary email:",D58,E58) -> viwuoha@college.harvard.edu | H58: Newark | I58: Roark fellow | J58: 9733429428 | K58: Female | L58: Fall 2022 | M58: 2026 | N58: North America | O58: Boston (U.S.) | P58: Yes | Q58: N/A | R58: N/A | S58: N/A | T58: N/A | U58: N/A | V58: Morgan Stanley | W58: NYC, NY | X58: IB | Y58: 1 | Z58: N/A | AA58: Morgan Stanley | AB58: NYC, NY | AC58: IB | AD58: N/A | AE58: N/A | AF58: N/A | AG58: Harvard University | AH58: Cambridge | AI58: Target | AJ58: 3.6 | AK58: Economics | AL58: 2026 | AM58: SEO | AN58: https://drive.google.com/open?id=1QH9FtjKUu9qwid9JDYTWxsRR9YaDI03Z | AO58: Private Equity | AP58: Warburg Pincus, Silver Lake | AS58: Community Member | AT58: Merged on Nov 07, 2025 18:06:21
A59: Monae | B59: Gant | C59: BLK - 24031 | D59: monae@berkeley.edu | E59: Monaegant03@gmail.com | F59: College/Secondary email: | G59: =IF(F59="College/Secondary email:",D59,E59) -> monae@berkeley.edu | H59: Los Angeles | I59: Analyst | J59: 3233572236 | K59: Female | L59: Spring 2024 | M59: 2026 | N59: North America | O59: N/A | P59: Yes | Q59: N/A | R59: N/A | S59: N/A | T59: N/A | U59: N/A | V59: Los Angeles City Employees' Retirement System (LACERS) | W59: Los Angeles, CA | X59: asset management | Y59: 1 | Z59: n/a | AA59: Morningstar | AB59: Chicago, IL | AC59: asset management | AD59: 1 | AE59: n/a | AF59: n/a | AG59: University of California, Berkeley | AH59: Berkeley | AI59: Public Flagship University | AJ59: 3.8 | AK59: Economics | AL59: 2026 | AM59: MLT, INROADS, Girls Who Invest, Project Destined | AN59: https://drive.google.com/open?id=1yAOD8BeiAEDegjCqBOKX5ac7ICgEOTJW | AO59: Asset Management, Hedge Funds, Real Estate | AP59: Vanguard, Bain Capital , and Pimco | AQ59: im interested in investment management | AS59: Analyst | AT59: Merged on Nov 07, 2025 18:06:23
A60: Iruka | B60: Okoye | C60: 24264 | D60: irukaokoye.warwick@live.ac.uk | E60: irukaokoye.2@gmail.com | F60: Personal email | G60: =IF(F60="College/Secondary email:",D60,E60) -> irukaokoye.2@gmail.com | H60: London | I60: Analyst | J60: +447950440862 | K60: Female | L60: Fall 2024 | M60: 2027 | N60: EMEA | O60: London (EMEA) | P60: No | Q60: n/a | R60: n/a | S60: n/a | T60: n/a | U60: n/a | V60: n/a | W60: n/a | X60: n/a | Y60: n/a | Z60: n/a | AA60: n/a | AB60: n/a | AC60: n/a | AD60: n/a | AE60: n/a | AF60: n/a | AG60: University Of Warwick | AH60: Coventry | AI60: Target | AJ60: 1st Class | AK60: BASC Global Sustainable Transport | AL60: 2027 | AM60: SEO, Rare Recruitment | AN60: https://drive.google.com/open?id=1zuCjX8azgwbIFqPFisJwONELf3XZAlo9 | AO60: Asset Management, Wealth Mangement, Private Banking, Commercial Banking | AP60: Citi, UBS, Nomura, Barings | AQ60: n/a | AR60: Night of professional exchange | AS60: Analyst | AT60: Merged on Nov 07, 2025 18:06:24
A61: Timothy | B61: Brown | C61: BLK - 23044 | D61: tmb2@andrew.cmu.edu | E61: tbrown2022@yahoo.com | F61: College/Secondary email: | G61: =IF(F61="College/Secondary email:",D61,E61) -> tmb2@andrew.cmu.edu | H61: Beltsville | I61: Analyst | J61: +12404212256 | K61: Male | L61: Spring 2023 | M61: 2026 | N61: North America | O61: N/A | P61: Yes | Q61: Virginia Retirement Systems | R61: Richmond, VA | S61: Asset management | T61: 1 | U61: N/A | V61: IPI Partners | W61: Chicago, IL | X61: Private Equity | Y61: 1 | Z61: N/A | AA61: Houlihan Lokey | AB61: New York, NY | AC61: Investment Banking | AD61: 1 | AE61: N/A | AF61: N/A | AG61: Carnegie Mellon University | AH61: Pittsburgh | AI61: Semi- target | AJ61: 3.6 | AK61: Business | AL61: 2026 | AM61: MLT, SEO | AN61: https://drive.google.com/open?id=1-qLj2ye4-NPWArKDOcK_LAOQFdGhmu-- | AO61: Investment Banking, Private Equity, Real Estate | AP61: KKR | AS61: Analyst | AT61: Merged on Nov 07, 2025 18:06:25
A62: Omar | B62: Ettaleb | C62: Not sure, can’t find | D62: Omar1026@bu.edu | E62: Omarettaleb1026@gmail.com | F62: College/Secondary email: | G62: =IF(F62="College/Secondary email:",D62,E62) -> Omar1026@bu.edu | H62: Philadelphia | I62: Trainee Analyst | J62: 12676238928 | K62: Male | L62: Fall 2024 | M62: 2028 | N62: North America | O62: Boston (U.S.) | P62: Yes | Q62: N/A | R62: N/A | S62: N/A | T62: 3 | U62: Financial reasons, only being a freshmen and having already two internships under my belt I want to prioritize building my finances this summer instead of work experience. | V62: N/A | W62: N/A | X62: N/A | Y62: N/A | Z62: N/A | AA62: N/A | AB62: N/A | AC62: N/A | AD62: N/A | AE62: N/A | AF62: N/A | AG62: Boston University | AH62: Boston | AI62: Target | AJ62: 4 | AK62: Data Science & Finance | AL62: 2028 | AM62: N/A | AN62: https://drive.google.com/open?id=10T8pnvFtOr9GcYQaQM1C5uWyA0qyhk2T | AO62: Sales and Trading, Quantitative Finance (eg. Quant Trading) | AP62: JP Morgan, Goldman Sachs | AQ62: I want to gain experience in either S&T or Quant, as that’s what my resume is most catered to and it’s a sector in finance that I would like to work in. | AS62: Analyst | AT62: Merged on Nov 07, 2025 18:06:29
A63: Iyanna | B63: Favors | C63: BLK - 22282 | D63: N/A | E63: iyafav0514@gmail.com | F63: Personal email | G63: =IF(F63="College/Secondary email:",D63,E63) -> iyafav0514@gmail.com | H63: New York City | I63: Roark fellow | J63: +13025381722 | K63: Female | L63: Fall 2022 | M63: 2025 | N63: North America | O63: N/A | P63: Yes | Q63: PwC | R63: Remote | S63: Consulting | T63: N/A | U63: N/A | V63: Jefferies | W63: New York, NY | X63: Investment Banking | Y63: 2 | Z63: Declined Jefferies Return, Accepted BofA | AA63: Bank of America | AB63: New York, NY | AC63: Investment Banking | AD63: n/a | AE63: n/a | AF63: Bank of America | AG63: University of Delaware | AH63: Newark, DE | AI63: Non-target | AJ63: 3.3 | AK63: Finance, financial planning & wealth management | AL63: 2025 | AM63: SEO | AN63: https://drive.google.com/open?id=1gpmEXQWGyBOhy0ePD5PXE_jIq4LRmuEH | AO63: Investment Banking, Private Equity, Asset Management, Venture Capital, Hedge Funds | AP63: Bain Capital, Carlyle, KKR, Neuberger Berman, Warburg Pincus | AQ63: Interested in full time roles on the buyside (Private equity, Hedge fund, Asset Management) or lateraling over to another investment bank from my current investment banking firm (Senior roles after analyst). | AR63: Roark Capital Fellow | AS63: Alumni (only select if you are graduated/graduating this year) | AT63: Merged on Nov 07, 2025 18:06:30
A64: Schaun | B64: King | C64: BLK - 24166 | D64: dd006197@student.reading.ac.um | E64: 04schking@gmail.com | F64: Personal email | G64: =IF(F64="College/Secondary email:",D64,E64) -> 04schking@gmail.com | H64: London | I64: Analyst | J64: +447733097723 | K64: Male | L64: Fall 2024 | M64: 2026 | N64: EMEA | O64: London (EMEA) | P64: No | Q64: The Portman Estate | R64: London | S64: Real Estate | T64: 1 | U64: N/A | V64: N/A | W64: N/A | X64: N/A | Y64: N/A | Z64: N/A | AA64: N/A | AB64: N/A | AC64: N/A | AD64: N/A | AE64: N/A | AF64: N/A | AG64: University of Reading | AH64: N/A | AI64: Non-target | AJ64: 3.8 | AK64: Real Estate | AL64: 2026 | AM64: SEO (EMEA), Project Destined, UpReach | AN64: https://drive.google.com/open?id=14_wgoqIMyAaTTm3lIZubKXQDH8sR0oJa | AO64: Private Equity, Asset Management, Hedge Funds, Real Estate | AP64: Barrings, Morgan Stanley | AQ64: Broad Real Estate Finance | AR64: Conference | AS64: Analyst | AT64: Merged on Nov 07, 2025 18:06:32
A65: Devin | B65: Johnson | C65: 22201 | D65: N/A | E65: Devin4136@gmail.com | F65: Personal email | G65: =IF(F65="College/Secondary email:",D65,E65) -> Devin4136@gmail.com | H65: Elmont, New York | I65: Roark fellow | J65: 5165542801 | K65: Male | L65: Fall 2022 | M65: 2025 | N65: North America | O65: N/A | P65: Yes | Q65: Federal Reserve Bank of Chicago | R65: Chicago, Illinois | S65: Government Regulatory Services | T65: N/A | U65: N/A | V65: Wells Fargo | W65: New York, New York | X65: Investment Banking | Y65: 3 | Z65: Compensation | AA65: Moelis and Company | AB65: New York, New York | AC65: Investment Banking | AD65: 4 | AE65: Experience and Deal Flow | AF65: Moelis and Company | AG65: University of Chicago | AH65: Chicago | AI65: Target | AJ65: 3.4 | AK65: Economics and Political Science | AL65: 2025 | AM65: SEO, Project Destined | AN65: https://drive.google.com/open?id=1oFI80SH-m_ineNlkoryvjX6g8CUlLbJ5 | AO65: Investment Banking, Private Equity, Real Estate | AP65: Bain Capital, KKR, Carlyle, EQT, Roark, Warburg Pincus | AQ65: Interested primarily in private equity | AR65: Fall Conference, November 2022 | AS65: Alumni (only select if you are graduated/graduating this year) | AT65: Merged on Nov 07, 2025 18:06:34
A66: Joseph | B66: Olugbade | C66: BLK - 24015 | D66: N1087691@my.ntu.ac.uk | E66: Josepholugbade@hotmail.com | F66: Personal email | G66: =IF(F66="College/Secondary email:",D66,E66) -> Josepholugbade@hotmail.com | H66: London | I66: Analyst | J66: +447554944062 | K66: Male | L66: Fall 2023 | M66: 2026 | N66: EMEA | O66: London (EMEA) | P66: Yes | Q66: Sompo International | R66: London, UK | S66: Insurance | T66: 1 | U66: N/A | V66: AXA Investment Managers | W66: London, UK | X66: Asset Management | Y66: 1 | Z66: N/A | AA66: N/A | AB66: N/A | AC66: N/A | AD66: N/A | AE66: N/A | AF66: N/A | AG66: Nottingham Business School, Nottingham Trent University | AH66: Nottingham | AI66: Non-target | AJ66: 3.7 | AK66: Business Management and Accounting and Finance | AL66: 2026 | AM66: SEO (EMEA) | AN66: https://drive.google.com/open?id=15IGxN_373eqY9CfCoHvkrePgP51UleUz | AO66: Private Equity, Asset Management, Venture Capital | AP66: Carlyle, Goldman Sachs, Bain Capital, Arsenal Capital, JP Morgan, UBS, LLR Partners | AQ66: I'm interested in roles in private wealth management and private banking. I'm also interested in investing roles, especially with a keen interest in private markets. | AS66: Analyst | AT66: Merged on Nov 07, 2025 18:06:35
A67: Levi | B67: Asemota | C67: BLK - 24189 | D67: pmyla7@nottingham.ac.uk | E67: leviasemota@gmail.com | F67: Personal email | G67: =IF(F67="College/Secondary email:",D67,E67) -> leviasemota@gmail.com | H67: London | I67: Analyst | J67: +447474740560 | K67: Male | L67: Fall 2024 | M67: 2027 | N67: EMEA | O67: London (EMEA) | P67: No | Q67: N/A | R67: N/A | S67: N/A | T67: N/A | U67: N/A | V67: N/A | W67: N/A | X67: N/A | Y67: N/A | Z67: N/A | AA67: N/A | AB67: N/A | AC67: N/A | AD67: N/A | AE67: N/A | AF67: N/A | AG67: University of Nottingham | AH67: Nottingham | AI67: Non-target | AJ67: N/A | AK67: Financial Mathematics | AL67: 2027 | AM67: SEO (EMEA), UpReach | AN67: https://drive.google.com/open?id=1YTvaOn8jE9cD2e2asTkDhrlTpO49yXmb | AO67: Private Equity, Venture Capital, Hedge Funds | AP67: Blackstone, Citadel, Sequoia etc | AS67: Education Pathways (IB, AWM, or PE) | AT67: Merged on Nov 07, 2025 18:06:36
A68: Harry | B68: Appiah | C68: BLK - 24161 | D68: ha390@student.le.ac.uk | E68: harryappiah9@gmail.com | F68: Personal email | G68: =IF(F68="College/Secondary email:",D68,E68) -> harryappiah9@gmail.com | H68: Northampton | I68: Analyst | J68: +447510107524 | K68: Male | L68: Fall 2024 | M68: 2026 | N68: EMEA | O68: London (EMEA) | P68: Yes | Q68: Goldman Sachs and Citigroup | R68: London | S68: Investment banking, Sales & Trading | T68: 2 | U68: n/a | V68: Citi Private Bank | W68: London | X68: Private banking | Y68: 3 | Z68: n/a | AA68: n/a | AB68: n/a | AC68: n/a | AD68: n/a | AE68: n/a | AF68: n/a | AG68: University of Leicester | AH68: Leicester | AI68: Non-target | AJ68: First Class: 71% Average | AK68: Accounting and Finance | AL68: 2026 | AM68: SEO (EMEA), Rare Recruitment | AN68: https://drive.google.com/open?id=1FgLvfPlEWCz9NpzoHd3-MAtRvEz_Iuax | AO68: Investment Banking, Sales and Trading, Asset Management, Management Consulting | AP68: Sixth Street, Lazard, UBS, JP Morgan | AR68: Spotlight Call | AS68: Analyst | AT68: Merged on Nov 07, 2025 18:06:38
A69: Nmesomachukwu | B69: Kamalu | C69: BLK - 24169 | D69: ncck2@cam.ac.uk | E69: nmesomachukwukamalu@gmail.com | F69: Personal email | G69: =IF(F69="College/Secondary email:",D69,E69) -> nmesomachukwukamalu@gmail.com | H69: Wakefield | I69: Analyst | J69: +447479298992 | K69: Female | L69: Fall 2024 | M69: 2027 | N69: EMEA | O69: N/A | P69: No | Q69: N/A | R69: N/A | S69: N/A | T69: N/A | U69: N/A | V69: N/A | W69: N/A | X69: N/A | Y69: N/A | Z69: N/A | AA69: N/A | AB69: N/A | AC69: N/A | AD69: N/A | AE69: N/A | AF69: N/A | AG69: University of Cambridge | AH69: Cambridge | AI69: Target | AJ69: N/A | AK69: Land Economy | AL69: 2027 | AM69: Rare Recruitment | AN69: https://drive.google.com/open?id=1eDMZPuQ0ppKOxeO9fSv-CMGKfxZUtxUj | AO69: Sales and Trading, Asset Management, Management Consulting, Technology | AP69: Savills, Barings, Jane Street, KKR, UBS | AS69: Community Member | AT69: Merged on Nov 07, 2025 18:06:39
A70: Joyce | B70: Silva | C70: BLK - 24209 | D70: J.Silva6@lse.ac.uk | E70: Joyce.t.silva@outlook.com | F70: Personal email | G70: =IF(F70="College/Secondary email:",D70,E70) -> Joyce.t.silva@outlook.com | H70: London | I70: Analyst | J70: +447443919048 | K70: Female | L70: Fall 2024 | M70: 2025 | N70: EMEA | O70: London (EMEA) | P70: Require a visa | Q70: London Economics | R70: London | S70: Consulting | T70: 1 | U70: N/A | V70: Arjun Infrastructure | W70: London | X70: Asset Managment | Y70: 1 | Z70: N/A | AA70: PGIM | AB70: London | AC70: Real Estate | AD70: 1 | AE70: N/A | AF70: N/A | AG70: London School of Economics and Political Science | AH70: London | AI70: Russel Group | AJ70: 2:1 | AK70: Economics and Economic History | AL70: 2025 | AM70: SEO | AN70: https://drive.google.com/open?id=15P_DmPZHv031VsiuzUq-cXm-Lraa18w7 | AO70: Investment Banking, Quantitative Finance (eg. Quant Trading), Management Consulting, Business & Entreprenuership, Legal, Risk & Compliance | AP70: Goldman Sachs | AQ70: I am very open to exploring different avenues | AR70: BLK equity training helped increase my financial knowledge | AS70: Alumni (only select if you are graduated/graduating this year) | AT70: Merged on Nov 07, 2025 18:06:41
A71: Bahran | B71: Michael | C71: 23428 | D71: bm01083@surrey.ac.uk | E71: bahranmichael91@gmail.com | F71: Personal email | G71: =IF(F71="College/Secondary email:",D71,E71) -> bahranmichael91@gmail.com | H71: London | I71: Analyst | J71: +447491637237 | K71: Male | L71: Spring 2024 | M71: 2026 | N71: EMEA | O71: London (EMEA) | P71: No | Q71: N/A | R71: N/A | S71: N/A | T71: N/A | U71: N/A | V71: BNP Paribas | W71: London, England | X71: Global Markets | Y71: 1 | Z71: N/A | AA71: N/A | AB71: N/A | AC71: N/A | AD71: N/A | AE71: N/A | AF71: N/A | AG71: University of Surrey | AH71: Guildford | AI71: Non-target | AJ71: 2:1 | AK71: 1st Class | AL71: 2026 | AM71: SEO (EMEA), UpReach | AN71: https://drive.google.com/open?id=1pYhkY-Auoiixs0OLxVXC2zaxbP3Ty67I | AO71: Investment Banking, Sales and Trading, Private Equity, Asset Management, Quantitative Finance (eg. Quant Trading), Hedge Funds, Real Estate | AP71: DE Shaw Group | AS71: Analyst | AT71: Merged on Nov 07, 2025 18:06:42
A72: Samuel | B72: Tewodros | C72: BLK - 24266 | D72: st938@cam.ac.uk | E72: TSamuel2004@hotmail.com | F72: Personal email | G72: =IF(F72="College/Secondary email:",D72,E72) -> TSamuel2004@hotmail.com | H72: London | I72: Senior analyst | J72: 447402394837 | K72: Male | L72: Fall 2024 | M72: 2026 | N72: EMEA | O72: London (EMEA) | P72: Yes | Q72: Frontier Economics | R72: London | S72: Consulting | T72: 1 | U72: N/A | V72: Raymond James | W72: London | X72: Investment Banking | Y72: 1 | Z72: N/A | AA72: N/A | AB72: N/A | AC72: N/A | AD72: N/A | AE72: N/A | AF72: N/A | AG72: University of Cambridge | AH72: Cambridge (United Kingdom) | AI72: Target | AJ72: First Class | AK72: Economics, Law & Real Estate | AL72: 2026 | AM72: SEO (EMEA), UpReach, Rare Recruitment | AN72: https://drive.google.com/open?id=1gPYIIB_7iKSsq8-4xzoruqzJbK06zv6e | AO72: Investment Banking, Private Equity, Quantitative Finance (eg. Quant Trading), Venture Capital, Hedge Funds | AP72: Centerview, Moelis, Lazard, Bank of America | AQ72: Investment Banking, Interested in exploring Hedge Funds and VC | AR72: All in person events were extremely helpful especially ones with the opportunity for Networking | AS72: Analyst | AT72: Merged on Nov 07, 2025 18:06:46
A73: Quentin | B73: Müller | C73: BLK - 23088 | D73: quentin_jonathan.mueller@fs-students.de | E73: quentinjmueller@gmail.com | F73: Personal email | G73: =IF(F73="College/Secondary email:",D73,E73) -> quentinjmueller@gmail.com | H73: Frankfurt, Germany | I73: Analyst | J73: +4915736136945 | K73: Male | L73: Spring 2023 | M73: 2026 | N73: EMEA | O73: Frankfurt (EMEA) | P73: No | Q73: PricewaterhouseCoopers | R73: Frankfurt, Germany | S73: Advisory / Consulting | T73: N/A | U73: N/A | V73: Stifel | W73: Frankfurt, Germany | X73: Investment Banking | Y73: N/A | Z73: N/A | AA73: N/A | AB73: N/A | AC73: N/A | AD73: N/A | AE73: N/A | AF73: N/A | AG73: Frankfurt School of Finance & Management | AH73: Frankfurt, Germany | AI73: Target | AJ73: 0.75 | AK73: Business Administration | AL73: 2026 | AM73: SEO (EMEA), Rare Recruitment | AN73: https://drive.google.com/open?id=14c3vB9w_ljYe_y39RPYMqY6zBudEREux | AO73: Investment Banking, Private Equity, Venture Capital, Hedge Funds | AP73: PJT Partners, Qatalyst Partners, CVC Capital Partners | AS73: Analyst | AT73: Merged on Nov 07, 2025 18:06:47
A74: Anu | B74: Badmus | C74: BLK - 23318 | D74: Anu.Badmus-Olanrewaju@warrwick.ac.uk | E74: anubadmus1@gmail.com | F74: Personal email | G74: =IF(F74="College/Secondary email:",D74,E74) -> anubadmus1@gmail.com | H74: London | I74: Trainee Analyst | J74: +447377192170 | K74: Female | L74: Fall 2023 | M74: 2026 | N74: EMEA | O74: London (EMEA) | P74: No | Q74: Lloyds Banking Group | R74: London | S74: Commercial Banking | T74: 1 | U74: N/A | V74: UBS | W74: London | X74: Investment Banking | Y74: 2 | Z74: Goldman Sachs Asset Management but I wanted to do investment banking | AA74: Ares Management | AB74: London | AC74: Wealth Management | AD74: 2 | AE74: Wanted to try something new | AF74: N/A | AG74: University of Warwick (exchange in The University of Hong Kong) | AH74: Coventry | AI74: Russell Group | AJ74: 2:1 | AK74: Law LLB | AL74: 2026 | AM74: SEO (EMEA), Rare Recruitment | AN74: https://drive.google.com/open?id=1fLOVyBE8-XDHyUwlA8K1IbfESAzmJbPb | AO74: Private Equity, Asset Management, Wealth Management | AP74: Ares Management, Raine Group | AR74: Conference - living in Hong Kong | AS74: Community Member | AT74: Merged on Nov 07, 2025 18:06:49
A75: Moradeke | B75: Akisanya | C75: 24199 | D75: m.t.akisanya@lse.ac.uk | E75: momo_akisanya@icloud.com | F75: Personal email | G75: =IF(F75="College/Secondary email:",D75,E75) -> momo_akisanya@icloud.com | H75: London | I75: Analyst | J75: +447500144363 | K75: Female | L75: Fall 2024 | M75: 2027 | N75: EMEA | O75: London (EMEA) | P75: No | Q75: N/A | R75: N/A | S75: N/A | T75: N/A | U75: N/A | V75: N/A | W75: N/A | X75: N/A | Y75: N/A | Z75: N/A | AA75: N/A | AB75: N/A | AC75: N/A | AD75: N/A | AE75: N/A | AF75: N/A | AG75: London School of Economics and Political Science | AH75: London | AI75: Target | AJ75: First Class | AK75: BSc Economics | AL75: 2027 | AM75: Rare Recruitment | AN75: https://drive.google.com/open?id=1D3xt2o-PoPqZrz5lp7NFdf_SwKzKAfQK | AO75: Investment Banking, Private Equity | AP75: JP Morgan, Goldman Sachs, Morgan Stanley, Lazard, PWP | AR75: London Tour and NPE | AS75: Analyst | AT75: Merged on Nov 07, 2025 18:06:50
A76: Kennedy | B76: Austin | C76: 24200 | D76: KAustin665@pqc.edu | E76: kcaustin2004@gmail.com | F76: Personal email | G76: =IF(F76="College/Secondary email:",D76,E76) -> kcaustin2004@gmail.com | H76: Georgetown, Texas | I76: Analyst | J76: +16784889507 | K76: Female | L76: Fall 2024 | M76: 2026 | N76: North America | O76: N/A | P76: Yes | Q76: Early Talent Identification Program at Paul Quinn College | R76: Dallas, TX | S76: Early Childhood Education | T76: 1 | U76: N/A | V76: Velocis | W76: Dallas, TX | X76: Private Equity | Y76: 2 | Z76: The other offer paid less and was further from my desired location. Downtown Dallas, TX | AA76: Grainger | AB76: Chicago, IL | AC76: Corporate Finance | AD76: 1 | AE76: N/A | AF76: N/A | AG76: Paul Quinn College | AH76: Dallas, Texas | AI76: HBCU (Historically Black Colleges and Universities) | AJ76: 3.7 | AK76: Finance | AL76: 2026 | AM76: MLT, Project Destined | AN76: https://drive.google.com/open?id=1IYRxinUip509IYfYm-k6bw8ThXvASCda | AO76: Investment Banking, Venture Capital, Corporate Finance | AP76: Capital One, Wells Fargo, JP Morgan | AQ76: My career interests specifically include working in corporate finance. Specifically with cosmetic retail brands (Ulta, Sephora, etc.) And VC. Firms that work with clients who operate in the beauty industry. | AS76: Education Pathways (IB, AWM, or PE) | AT76: Merged on Nov 07, 2025 18:06:52
A77: Eyob | B77: Habtyehun | C77: BLK -24155 | D77: ehabtyeh@uwo.ca | E77: ehabtyehun@gmail.com | F77: College/Secondary email: | G77: =IF(F77="College/Secondary email:",D77,E77) -> ehabtyeh@uwo.ca | H77: Toronto | I77: Analyst | J77: 14372882935 | K77: Male | L77: Fall 2024 | M77: 2028 | N77: North America | O77: Toronto (Canada) | P77: No | Q77: N/A | R77: N/A | S77: N/A | T77: N/A | U77: N/A | V77: N/A | W77: N/A | X77: N/A | Y77: N/A | Z77: N/A | AA77: N/A | AB77: N/A | AC77: N/A | AD77: N/A | AE77: N/A | AF77: N/A | AG77: Western Unversity Ontario | AH77: London | AI77: Target | AJ77: 3.93 | AK77: Economics | AL77: 2028 | AM77: N/A | AN77: https://drive.google.com/open?id=1C-lTONH6winovUUh2CGurRoZQTJzEoLa | AO77: Investment Banking, Sales and Trading, Private Equity, Hedge Funds | AP77: BDT & MSD, Greenhill, | AQ77: I think you all are doing great as is | AR77: None thus far (Haven't been to active with the events). Spotlight calls has always been helpful though. | AS77: Analyst | AT77: Merged on Nov 07, 2025 18:06:53
A78: Lamake | B78: Henok | C78: BLK - 24204 | D78: lamake.henok23@imperial.ac.uk | E78: lmk.henok@gmail.com | F78: Personal email | G78: =IF(F78="College/Secondary email:",D78,E78) -> lmk.henok@gmail.com | H78: London | I78: Analyst | J78: +447735753188 | K78: Male | L78: Fall 2024 | M78: 2027 | N78: EMEA | O78: London (EMEA) | P78: No | Q78: Coller Capital | R78: London, England | S78: Private Equity | T78: 1 | U78: N/A | V78: N/A | W78: N/A | X78: N/A | Y78: N/A | Z78: N/A | AA78: N/A | AB78: N/A | AC78: N/A | AD78: N/A | AE78: N/A | AF78: N/A | AG78: Imperial College London | AH78: London | AI78: Target | AJ78: N/A | AK78: Mathematics | AL78: 2027 | AM78: SEO (EMEA) | AN78: https://drive.google.com/open?id=1t8luRN0z5Q_Xwd57LC_Rw24tqsQyp0y1 | AO78: Investment Banking, Sales and Trading, Quantitative Finance (eg. Quant Trading) | AP78: Jane Street, Goldman Sachs | AS78: Analyst | AT78: Merged on Nov 07, 2025 18:06:54
A79: Storm | B79: Lees | C79: 24013 | D79: 220130619@aston.ac.uk | E79: stormlees@gmail.com | F79: Personal email | G79: =IF(F79="College/Secondary email:",D79,E79) -> stormlees@gmail.com | H79: Wolverhampton | I79: Analyst | J79: +4407903141104 | K79: Male | L79: Spring 2024 | M79: 2026 | N79: EMEA | O79: N/A | P79: No | Q79: Citi & PwC | R79: London & Birmingham | S79: Investment Banking & Audit | T79: 1 | U79: Industrial placement so can’t attend | V79: Morgan Stanley | W79: London | X79: Sales & Trading | Y79: N/A | Z79: N/A | AA79: N/A | AB79: N/A | AC79: N/A | AD79: N/A | AE79: N/A | AF79: N/A | AG79: Aston University | AH79: Birmingham | AI79: Non-target | AJ79: 4 | AK79: Accounting and Finance | AL79: 2026 | AM79: SEO (EMEA) | AN79: https://drive.google.com/open?id=1QPazjWDGpsFVY4QEh4OF328KG4JTdVJT | AO79: Investment Banking, Sales and Trading, Private Equity, Venture Capital, Hedge Funds | AP79: N/A | AS79: Analyst | AT79: Merged on Nov 07, 2025 18:06:55
A80: Kehinde | B80: Oladugba | C80: BLK - 23305 | D80: K.Oladugba-23@student.lboro.ac.uk | E80: ko.oladugba@gmail.com | F80: Personal email | G80: =IF(F80="College/Secondary email:",D80,E80) -> ko.oladugba@gmail.com | H80: Southend on sea | I80: Analyst | J80: +447968760926 | K80: Female | L80: Spring 2024 | M80: 2027 | N80: EMEA | O80: N/A | P80: No | Q80: n/a | R80: n/a | S80: n/a | T80: n/a | U80: n/a | V80: n/a | W80: n/a | X80: n/a | Y80: 0 | Z80: n/a | AA80: n/a | AB80: n/a | AC80: n/a | AD80: n/a | AE80: n/a | AF80: n/a | AG80: Loughborough University | AH80: Midlands | AI80: Non-target | AJ80: 1st | AK80: economics | AL80: 2027 | AM80: SEO (EMEA) | AN80: https://drive.google.com/open?id=11vCQ20Pj-cNBsJErDBZZiYp4Swlv6pje | AO80: Investment Banking, Private Equity, Hedge Funds | AP80: Citi , Hamilton Lane | AS80: Community Member | AT80: Merged on Nov 07, 2025 18:06:56
A81: Anas | B81: Abdulahi | C81: BLK - 24152 | D81: anas.abdulahi@warwick.ac.uk | E81: anasabdulahi843@gmail.com | F81: Personal email | G81: =IF(F81="College/Secondary email:",D81,E81) -> anasabdulahi843@gmail.com | H81: London | I81: Trainee Analyst | J81: +447903029294 | K81: Male | L81: Fall 2024 | M81: 2027 | N81: EMEA | O81: London (EMEA) | P81: Yes | Q81: BGO | R81: London | S81: asset management | T81: 1 | U81: N/A | V81: N/A | W81: N/A | X81: N/A | Y81: N/A | Z81: N/A | AA81: N/A | AB81: N/A | AC81: N/A | AD81: N/A | AE81: N/A | AF81: N/A | AG81: University of Warwick | AH81: Coventry | AI81: Target | AJ81: 4 | AK81: Physics | AL81: 2027 | AM81: SEO, UpReach, Rare Recruitment | AN81: https://drive.google.com/open?id=1iBcOEV-o691wQYNAkuuBsMGnRj7BFH_4 | AO81: Investment Banking, Sales and Trading, Private Equity, Quantitative Finance (eg. Quant Trading), Venture Capital, Hedge Funds, Technology, Real Estate | AP81: DE Shaw and co , Barings, Goldman Sachs , Jane street , Jp Morgan , KKR , | AS81: Analyst | AT81: Merged on Nov 07, 2025 18:06:57
A82: Judah | B82: Fakile | C82: BLK - 24100 | D82: jmf200@cam.ac.uk | E82: judahm.fakile@gmail.com | F82: Personal email | G82: =IF(F82="College/Secondary email:",D82,E82) -> judahm.fakile@gmail.com | H82: St.Albans, UK | I82: Analyst | J82: 447914669588 | K82: Male | L82: Fall 2024 | M82: 2027 | N82: EMEA | O82: London (EMEA) | P82: With sponsorship | Q82: N/A | R82: N/A | S82: N/A | T82: N/A | U82: N/A | V82: PJT Partners | W82: London, UK | X82: Investment Banking | Y82: 2 | Z82: Preferred the other offer | AA82: N/A | AB82: N/A | AC82: N/A | AD82: N/A | AE82: N/A | AF82: N/A | AG82: University of Cambridge, Trinity College | AH82: Cambridge | AI82: Target | AJ82: 4 | AK82: Economics | AL82: 2027 | AM82: SEO (EMEA), UpReach, Rare Recruitment | AN82: https://drive.google.com/open?id=1AKLC_TSHz1wSsZUnsJ6jxcbWHrRFRxaK | AO82: Investment Banking, Private Equity, Quantitative Finance (eg. Quant Trading), Venture Capital, Hedge Funds | AP82: Alpine, Advent, Jane Street, EQT, Bain Capital, DE Shaw, Roark, Warburg Pincus, Carlyle, Arsenal Capital Partners | AR82: Night of Professional Exchange, Spring Conference | AS82: Analyst | AT82: Merged on Nov 07, 2025 18:07:01
